Workbook
Name a: WACC!a
Name a: [0]!a
Name AboutCompGraph: WACC!AboutCompGraph
Name AboutCompGraph: [0]!AboutCompGraph
Name acq_pv: #REF!
Name Acq15Day: #REF!
Name Acq30Day: #REF!
Name Acq60Day: #REF!
Name Acq90Day: #REF!
Name AcqDate: #REF!
Name AcqPrice: #REF!
Name AcqQ: #REF!
Name AcqResearch: #REF!
Name AcqYest: #REF!
Name Annotate_Area: #REF!
Name AnnotateClearSet: #REF!
Name AnnotateNoteClear: #REF!
Name AnnotateNoteReturn: #REF!
Name AnnotateNoteSet: #REF!
Name AnnotateStart: #REF!
Name avgBlock: #REF!
Name AvgPrice: #REF!
Name AxesFormat: WACC!AxesFormat
Name AxesFormat: [0]!AxesFormat
Name BackFromCompanySelector: WACC!BackFromCompanySelector
Name BackFromCompanySelector: [0]!BackFromCompanySelector
Name BackFromItemSelect: WACC!BackFromItemSelect
Name BackFromItemSelect: [0]!BackFromItemSelect
Name BalanceSheet: #REF!
Name bDown: WACC!bDown
Name bDown: [0]!bDown
Name BeginDate: #REF!
Name BeginDate: #REF!
Name BeginDateSet: #REF!
Name BeginReturn: #REF!
Name BlackWhiteNote: #REF!
Name BlackWhiteSet: #REF!
Name bLeft: WACC!bLeft
Name bLeft: [0]!bLeft
Name bRight: WACC!bRight
Name bRight: [0]!bRight
Name bUp: WACC!bUp
Name bUp: [0]!bUp
Name Cellsdown: #REF!
Name Cellsdown: #REF!
Name ChangeSize: WACC!ChangeSize
Name ChangeSize: [0]!ChangeSize
Name ChartOptions: WACC!ChartOptions
Name ChartOptions: [0]!ChartOptions
Name ChartType: #REF!
Name ChartType: #REF!
Name ChartTypeChange: WACC!ChartTypeChange
Name ChartTypeChange: [0]!ChartTypeChange
Name cleanup: #REF!
Name cleanup: #REF!
Name ClearCompList: WACC!ClearCompList
Name ClearCompList: [0]!ClearCompList
Name ClipBoardRange: #REF!
Name ClipBoardRange: #REF!
Name ColorNoteReturn: #REF!

Sheet Cover
A1: WD-40 Financial Model
B3: PAGE
A4: Assumptions | B4: 1
A5: Debt | B5: =B4+1 -> 2
A6: Calcs | B6: =B5+1 -> 3
A7: Income Statement | B7: =B6+1 -> 4
A8: Balance Sheet | B8: =B7+1 -> 5
A9: WACC | B9: =B8+1 -> 6
A10: Cash Flow Statement | B10: =B9+1 -> 7
A11: Trading Comps | B11: =B10+1 -> 8
A12: Transaction Comps | B12: =B11+1 -> 9
A13: AVP | B13: =B12+1 -> 10
A14: Summary | B14: =B13+1 -> 11

Sheet Balance Sheet HISTORICAL
A1: WD-40 Balance Sheet
B2: (USD in thousands, except per share data)
C4: 41882 | D4: 42247 | E4: 42613 | F4: 42978 | G4: 43343 | H4: 43708 | I4: 44074 | J4: 44439 | K4: 44804 | L4: 45169 | M4: 45535
B5: Assets:
B6: Cash and cash equivalents | C6: 57803 | D6: 53896 | E6: 50891 | F6: 37082 | G6: 48866 | H6: 27233 | I6: 56462 | J6: 85961 | K6: 37843 | L6: 48143 | M6: 46699
B7: Short-term investments | C7: 45050 | D7: 48603 | E7: 57633 | F7: 80166 | G7: 219 | H7: 0 | I7: 0 | J7: 0 | K7: 0 | L7: 0 | M7: 0
B8: Trade and other accounts receivable, net | C8: 63618 | D8: 58750 | E8: 64680 | F8: 64259 | G8: 69025 | H8: 72864 | I8: 80672 | J8: 89558 | K8: 89930 | L8: 98039 | M8: 117493
B9: Inventories | C9: 34989 | D9: 32052 | E9: 31793 | F9: 35340 | G9: 36536 | H9: 40682 | I9: 41264 | J9: 55752 | K9: 104101 | L9: 86522 | M9: 79088
B10: Current deferred tax assets, net | C10: 5855 | D10: 5824 | E10: 0 | F10: 0 | G10: 0 | H10: 0 | I10: 0 | J10: 0 | K10: 0 | L10: 0 | M10: 0
B11: Other current assets | C11: 8339 | D11: 6127 | E11: 4475 | F11: 8007 | G11: 13337 | H11: 7216 | I11: 6756 | J11: 9948 | K11: 17766 | L11: 15821 | M11: 12161
A12: * | B12: Total current assets | C12: =SUM(C6:C11) -> 215654 | D12: =SUM(D6:D11) -> 205252 | E12: =SUM(E6:E11) -> 209472 | F12: =SUM(F6:F11) -> 224854 | G12: =SUM(G6:G11) -> 167983 | H12: =SUM(H6:H11) -> 147995 | I12: =SUM(I6:I11) -> 185154 | J12: =SUM(J6:J11) -> 241219 | ... M12: =SUM(M6:M11) -> 255441
B13: Property and equipment, net | C13: 9702 | D13: 11376 | E13: 11545 | F13: 29439 | G13: 36357 | H13: 45076 | I13: 60759 | J13: 70145 | K13: 65977 | L13: 66791 | M13: 62983 | P13: Beginning | Q13: Beg PP&E
B14: Goodwill | C14: 95499 | D14: 96409 | E14: 95649 | F14: 95597 | G14: 95621 | H14: 95347 | I14: 95731 | J14: 95869 | K14: 95180 | L14: 95505 | M14: 96985 | P14: Additions | Q14: + Capex
B15: Other intangible assets, net | C15: 23671 | D15: 22961 | E15: 19191 | F15: 16244 | G15: 13513 | H15: 10652 | I15: 8633 | J15: 7244 | K15: 5588 | L15: 4670 | M15: 6222 | P15: Subtractions | Q15: - Depreciation
B16: Right-of-use assets | C16: 0 | D16: 0 | E16: 0 | F16: 0 | G16: 0 | H16: 0 | I16: 8168 | J16: 8824 | K16: 7559 | L16: 7820 | M16: 11611 | P16: Ending | Q16: = Ending PP&E
B17: Deferred tax assets, net | C17: 0 | D17: 0 | E17: 621 | F17: 495 | G17: 511 | H17: 403 | I17: 464 | J17: 858 | K17: 679 | L17: 1201 | M17: 993
B18: Other assets | C18: 3154 | D18: 3259 | E18: 3190 | F18: 3088 | G18: 3074 | H18: 3189 | I18: 3728 | J18: 6044 | K18: 9672 | L18: 13454 | M18: 14804
A19: * | B19: Total assets | C19: =SUM(C12:C18) -> 347680 | D19: =SUM(D12:D18) -> 339257 | E19: =SUM(E12:E18) -> 339668 | F19: =SUM(F12:F18) -> 369717 | G19: =SUM(G12:G18) -> 317059 | H19: =SUM(H12:H18) -> 302662 | I19: =SUM(I12:I18) -> 362637 | J19: =SUM(J12:J18) -> 430203 | ... M19: =SUM(M12:M18) -> 449039
B21: Liabilities and Shareholders' Equity:
B22: Accounts payable | C22: 18031 | D22: 17128 | E22: 18690 | F22: 20898 | G22: 19115 | H22: 18727 | I22: 21676 | J22: 33499 | K22: 32852 | L22: 30826 | M22: 35960
B23: Accrued liabilities | C23: 18382 | D23: 15200 | E23: 15757 | F23: 18997 | G23: 26240 | H23: 18513 | I23: 21660 | J23: 25658 | K23: 27161 | L23: 30000 | M23: 31272
B24: Accrued payroll and related expenses | C24: 15969 | D24: 13357 | E24: 20866 | F24: 14222 | G24: 14823 | H24: 15301 | I24: 14767 | J24: 25662 | K24: 11583 | L24: 16722 | M24: 26055
B25: Revolving credit facility, current portion | C25: 98000 | D25: 0 | E25: 0 | F25: 20000 | G25: 22800 | H25: 20405 | I25: 0 | J25: 0 | K25: =39173-800 -> 38373 | L25: 10000 | M25: =8659-800 -> 7859 | N25: Debt schedule
B26: Short-term borrowings | C26: 0 | D26: 0 | E26: 0 | F26: 0 | G26: 800 | H26: 800 | I26: 800 | J26: 800 | K26: 800 | L26: 800 | M26: 800 | N26: Debt schedule
B27: Income taxes payable | C27: 1529 | D27: 2287 | E27: 3381 | F27: 1306 | G27: 2125 | H27: 844 | I27: 1213 | J27: 317 | K27: 51 | L27: 494 | M27: 1554
A28: * | B28: Total current liabilities | C28: =SUM(C22:C27) -> 151911 | D28: =SUM(D22:D27) -> 47972 | E28: =SUM(E22:E27) -> 58694 | F28: =SUM(F22:F27) -> 75423 | G28: =SUM(G22:G27) -> 85903 | H28: =SUM(H22:H27) -> 74590 | I28: =SUM(I22:I27) -> 60116 | J28: =SUM(J22:J27) -> 85936 | ... M28: =SUM(M22:M27) -> 103500
B29: Revolving credit facility | C29: 0 | D29: 108000 | E29: 122000 | F29: 134000 | G29: 44000 | H29: 42221 | I29: 95898 | J29: 46540 | K29: =77912-(39173-800) -> 39539 | L29: =52943-10000 -> 42943 | M29: =27836-7859 -> 19977 | N29: Debt schedule
B30: Long-term borrowings | C30: 0 | D30: 0 | E30: 0 | F30: 0 | G30: 18800 | H30: 18000 | I30: 17200 | J30: =(17200-800)+26000+26000 -> 68400 | K30: =(16400-800)+26000+26000 -> 67600 | L30: =(15600-800)+26000+26000 -> 66800 | M30: =(14800-800)+26000+26000 -> 66000 | N30: Debt schedule
B31: Deferred tax liabilities, net | C31: 24253 | D31: 23145 | E31: 16365 | F31: 18949 | G31: 11050 | H31: 11688 | I31: 11291 | J31: 10401 | K31: 10528 | L31: 10305 | M31: 9066
B32: Long-term operating lease liabilities | C32: 0 | D32: 0 | E32: 0 | F32: 0 | G32: 0 | H32: 0 | I32: 6520 | J32: 7062 | K32: 5999 | L32: 5832 | M32: 5904
B33: Other long-term liabilities | C33: 2101 | D33: 2282 | E33: 2214 | F33: 1958 | G33: 1817 | H33: 10688 | I33: 11299 | J33: 11482 | K33: 11185 | L33: 13066 | M33: 14066
A34: * | B34: Total liabilities | C34: =SUM(C28:C33) -> 178265 | D34: =SUM(D28:D33) -> 181399 | E34: =SUM(E28:E33) -> 199273 | F34: =SUM(F28:F33) -> 230330 | G34: =SUM(G28:G33) -> 161570 | H34: =SUM(H28:H33) -> 157187 | I34: =SUM(I28:I33) -> 202324 | J34: =SUM(J28:J33) -> 229821 | ... M34: =SUM(M28:M33) -> 218513
B36: Shareholders' equity:
B37: Common stock | C37: 19 | D37: 20 | E37: 20 | F37: 20 | G37: 20 | H37: 20 | I37: 20 | J37: 20 | K37: 20 | L37: 20 | M37: 20
B38: Additional paid-in capital | C38: 136212 | D38: 141651 | E38: 145936 | F38: 150692 | G38: 153469 | H38: 155132 | I38: 157850 | J38: 163737 | K38: 165973 | L38: 171546 | M38: 175642
B39: Retained earnings | C39: 237596 | D39: 260683 | E39: 289642 | F39: 315764 | G39: 351266 | H39: 374060 | I39: 398731 | J39: 430735 | K39: 456076 | L39: 477488 | M39: 499931
B40: Accumulated other comprehensive income (loss) | C40: 1103 | D40: -8722 | E40: -27298 | F40: -28075 | G40: -27636 | H40: -32482 | I40: -28208 | J40: -26030 | K40: -36209 | L40: -31206 | M40: -29268
B41: Common stock held in treasury, at cost | C41: -205515 | D41: -235774 | E41: -267905 | F41: -299014 | G41: -321630 | H41: -351255 | I41: -368080 | J41: -368080 | K41: -397236 | L41: -407670 | M41: -415799
A42: * | B42: Total stockholders’ equity | C42: =SUM(C37:C41) -> 169415 | D42: =SUM(D37:D41) -> 157858 | E42: =SUM(E37:E41) -> 140395 | F42: =SUM(F37:F41) -> 139387 | G42: =SUM(G37:G41) -> 155489 | H42: =SUM(H37:H41) -> 145475 | I42: =SUM(I37:I41) -> 160313 | J42: =SUM(J37:J41) -> 200382 | ... M42: =SUM(M37:M41) -> 230526
A44: * | B44: Total liabilities and stockholders’ equity | C44: =C34+C42 -> 347680 | D44: =D34+D42 -> 339257 | E44: =E34+E42 -> 339668 | F44: =F34+F42 -> 369717 | G44: =G34+G42 -> 317059 | H44: =H34+H42 -> 302662 | I44: =I34+I42 -> 362637 | J44: =J34+J42 -> 430203 | ... M44: =M34+M42 -> 449039
B45: Check | C45: =C19-C44 -> 0 | D45: =D19-D44 -> 0 | E45: =E19-E44 -> 0 | F45: =F19-F44 -> 0 | G45: =G19-G44 -> 0 | H45: =H19-H44 -> 0 | I45: =I19-I44 -> 0 | J45: =J19-J44 -> 0 | ... M45: =M19-M44 -> 0

Sheet Assumptions
A1: WD-40 Assumptions
T2: Projected
B3: 42247 | C3: 42613 | D3: 42978 | E3: 43343 | F3: 43708 | G3: 44074 | H3: 44439 | I3: 44804 | J3: 45169 | K3: 45535 | M3: 10 yr AVG | N3: 5 yr AVG | O3: 3 yr AVG | Q3: DRIVER | S3: Rationale | T3: 45900 | U3: 46265 | V3: 46630 | W3: 46996 | X3: 47361
A4: Income Statement (non-debt items)
A5: Net sales (growth in sales) | B5: ='Income Statement'!D6/'Income Statement'!C6-1 -> -0.012655452 | C5: ='Income Statement'!E6/'Income Statement'!D6-1 -> 0.0066640222 | D5: ='Income Statement'!F6/'Income Statement'!E6-1 -> -0.00043081934 | E5: ='Income Statement'!G6/'Income Statement'!F6-1 -> 0.073617762 | F5: ='Income Statement'!H6/'Income Statement'!G6-1 -> 0.036306846 | G5: ='Income Statement'!I6/'Income Statement'!H6-1 -> -0.035082083 | H5: ='Income Statement'!J6/'Income Statement'!I6-1 -> 0.19488712 | I5: ='Income Statement'!K6/'Income Statement'!J6-1 -> 0.062918324 | ... K5: ='Income Statement'!M6/'Income Statement'!L6-1 -> 0.099211734 | M5: =AVERAGE(B5:K5) -> 0.046097001 | N5: =AVERAGE(G5:K5) -> 0.07149353 | O5: =AVERAGE(I5:K5) -> 0.065887537 | Q5: 0.07 | S5: Being conservative; Low End of 7-10% LT Segment guidance (pg. 21 of 58 - 1/10/25 Presentation) | T5: =Q5 -> 0.07 | U5: =T5 -> 0.07 | V5: =U5 -> 0.07 | W5: =V5 -> 0.07 | X5: =W5 -> 0.07
A6: Clean COGS (as % of sales) | B6: ='Income Statement'!D7/'Income Statement'!D6 -> 0.46501909 | C6: ='Income Statement'!E7/'Income Statement'!E6 -> 0.43149827 | D6: ='Income Statement'!F7/'Income Statement'!F6 -> 0.43183519 | E6: ='Income Statement'!G7/'Income Statement'!G6 -> 0.4414449 | F6: ='Income Statement'!H7/'Income Statement'!H6 -> 0.44418614 | G6: ='Income Statement'!I7/'Income Statement'!I6 -> 0.44594849 | H6: ='Income Statement'!J7/'Income Statement'!J6 -> 0.45274943 | I6: ='Income Statement'!K7/'Income Statement'!K6 -> 0.50028327 | ... K6: ='Income Statement'!M7/'Income Statement'!M6 -> 0.457743 | M6: =AVERAGE(B6:K6) -> 0.45519229 | N6: =AVERAGE(G6:K6) -> 0.46758785 | O6: =AVERAGE(I6:K6) -> 0.47974712 | Q6: 0.465 | S6: Steady increase 2016-2022, DECREASE 2022-2024; 55/30/25 Long-Term (WDFC Presentation pg. 39); 45-50% Guidance | T6: =Q6 -> 0.465 | U6: =T6 -> 0.465 | V6: =U6 -> 0.465 | W6: =V6 -> 0.465 | X6: =W6 -> 0.465
A7: Clean SG&A (as % of sales) | B7: ='Income Statement'!D9/'Income Statement'!D6 -> 0.28447185 | C7: ='Income Statement'!E9/'Income Statement'!E6 -> 0.30556796 | D7: ='Income Statement'!F9/'Income Statement'!F6 -> 0.29690759 | E7: ='Income Statement'!G9/'Income Statement'!G6 -> 0.29242729 | F7: ='Income Statement'!H9/'Income Statement'!H6 -> 0.28823148 | G7: ='Income Statement'!I9/'Income Statement'!I6 -> 0.29327423 | H7: ='Income Statement'!J9/'Income Statement'!J6 -> 0.29358592 | I7: ='Income Statement'!K9/'Income Statement'!K6 -> 0.2627039 | ... K7: ='Income Statement'!M9/'Income Statement'!M6 -> 0.30567018 | M7: =AVERAGE(B7:K7) -> 0.29058304 | N7: =AVERAGE(G7:K7) -> 0.28764484 | O7: =AVERAGE(I7:K7) -> 0.28378802 | Q7: 0.285 | S7: Steady decrease since 2016 (2024 uptick in NOTE); Being conservaitve; 55/30/25 rule (pg. 39 of 1/10/25 Presentation) | T7: =Q7 -> 0.285 | U7: =T7 -> 0.285 | V7: =U7 -> 0.285 | W7: =V7 -> 0.285 | X7: =W7 -> 0.285
A8: Advertising and sales promotion (as % of sales) | B8: ='Income Statement'!D10/'Income Statement'!D6 -> 0.060494513 | C8: ='Income Statement'!E10/'Income Statement'!E6 -> 0.05852313 | D8: ='Income Statement'!F10/'Income Statement'!F6 -> 0.053972868 | E8: ='Income Statement'!G10/'Income Statement'!G6 -> 0.054621828 | F8: ='Income Statement'!H10/'Income Statement'!H6 -> 0.055051376 | G8: ='Income Statement'!I10/'Income Statement'!I6 -> 0.052891324 | H8: ='Income Statement'!J10/'Income Statement'!J6 -> 0.057274092 | I8: ='Income Statement'!K10/'Income Statement'!K6 -> 0.052702286 | ... K8: ='Income Statement'!M10/'Income Statement'!M6 -> 0.057422061 | M8: =AVERAGE(B8:K8) -> 0.055657234 | N8: =AVERAGE(G8:K8) -> 0.054781724 | O8: =AVERAGE(I8:K8) -> 0.054581069 | Q8: 0.06 | S8: Declined 2015-2020, uptick in 2024; Mgmt guidance of 6% (pg. 46 of 1/10/25 presentation) | T8: =Q8 -> 0.06 | U8: =T8 -> 0.06 | V8: =U8 -> 0.06 | W8: =V8 -> 0.06 | X8: =W8 -> 0.06
A9: Amortization (as % of sales) | B9: ='Income Statement'!D13/'Income Statement'!D6 -> 0.0080364935 | C9: ='Income Statement'!E13/'Income Statement'!E6 -> 0.0078177949 | D9: ='Income Statement'!F13/'Income Statement'!F6 -> 0.0075662407 | E9: ='Income Statement'!G13/'Income Statement'!G6 -> 0.0072236719 | F9: ='Income Statement'!H13/'Income Statement'!H6 -> 0.0063918743 | G9: ='Income Statement'!I13/'Income Statement'!I6 -> 0.0054125112 | H9: ='Income Statement'!J13/'Income Statement'!J6 -> 0.0029685992 | I9: ='Income Statement'!K13/'Income Statement'!K6 -> 0.0027639644 | ... K9: ='Income Statement'!M13/'Income Statement'!M6 -> 0.0018728082 | M9: =AVERAGE(B9:K9) -> 0.0051924578 | N9: =AVERAGE(G9:K9) -> 0.0029777006 | O9: =AVERAGE(I9:K9) -> 0.0021691309 | Q9: 0.002 | S9: 3-yr average = 0.2%; Has been declining long-term; matching the trend; flat last 2 years | T9: =Q9 -> 0.002 | U9: =T9 -> 0.002 | V9: =U9 -> 0.002 | W9: =V9 -> 0.002 | X9: =W9 -> 0.002
A10: Other (expense) income, net (as % of sales) | B10: ='Income Statement'!D17/'Income Statement'!D6 -> -0.004387148 | C10: ='Income Statement'!E17/'Income Statement'!E6 -> 0.0064649171 | D10: ='Income Statement'!F17/'Income Statement'!F6 -> 0.0020682985 | E10: ='Income Statement'!G17/'Income Statement'!G6 -> 0.0008298288 | F10: ='Income Statement'!H17/'Income Statement'!H6 -> 0.0018282745 | G10: ='Income Statement'!I17/'Income Statement'!I6 -> 0.0015691631 | H10: ='Income Statement'!J17/'Income Statement'!J6 -> -5.7364236e-05 | I10: ='Income Statement'!K17/'Income Statement'!K6 -> -0.0011217763 | ... K10: ='Income Statement'!M17/'Income Statement'!M6 -> -0.0017441161 | M10: =AVERAGE(B10:K10) -> 0.00069800771 | N10: =AVERAGE(G10:K10) -> 3.5181225e-05 | O10: =AVERAGE(I10:K10) -> -0.00044529759 | Q10: 0 | S10: Inconsistent (4 negative / 6 positive) & ZERO will result in NO IMPACT | T10: =Q10 -> 0 | U10: =T10 -> 0 | V10: =U10 -> 0 | W10: =V10 -> 0 | X10: =W10 -> 0
A11: Provision for income taxes (Taxes / EBT) | B11: ='Income Statement'!D19/'Income Statement'!D18 -> 0.29001743 | C11: ='Income Statement'!E19/'Income Statement'!E18 -> 0.27697866 | D11: ='Income Statement'!F19/'Income Statement'!F18 -> 0.29069175 | E11: ='Income Statement'!G19/'Income Statement'!G18 -> 0.13252547 | F11: ='Income Statement'!H19/'Income Statement'!H18 -> 0.30781231 | G11: ='Income Statement'!I19/'Income Statement'!I18 -> 0.19605376 | H11: ='Income Statement'!J19/'Income Statement'!J18 -> 0.18809466 | I11: ='Income Statement'!K19/'Income Statement'!K18 -> 0.19949351 | ... K11: ='Income Statement'!M19/'Income Statement'!M18 -> 0.23892993 | M11: =AVERAGE(B11:K11) -> 0.23456952 | N11: =AVERAGE(G11:K11) -> 0.20953392 | O11: =AVERAGE(I11:K11) -> 0.22117373 | Q11: 0.23 | S11: U.S. Corp Tax Rate of 21% (since 2017 Tax Cuts and Jobs Act), but FOREIGN taxes increase this (see note) | T11: =Q11 -> 0.23 | U11: =T11 -> 0.23 | V11: =U11 -> 0.23 | W11: =V11 -> 0.23 | X11: =W11 -> 0.23
A13: Gross profit margin | B13: ='Income Statement'!D8/'Income Statement'!D6 -> 0.53498091 | C13: ='Income Statement'!E8/'Income Statement'!E6 -> 0.56850173 | D13: ='Income Statement'!F8/'Income Statement'!F6 -> 0.56816481 | E13: ='Income Statement'!G8/'Income Statement'!G6 -> 0.5585551 | F13: ='Income Statement'!H8/'Income Statement'!H6 -> 0.55581386 | G13: ='Income Statement'!I8/'Income Statement'!I6 -> 0.55405151 | H13: ='Income Statement'!J8/'Income Statement'!J6 -> 0.54725057 | I13: ='Income Statement'!K8/'Income Statement'!K6 -> 0.49971673 | ... K13: ='Income Statement'!M8/'Income Statement'!M6 -> 0.542257 | M13: =AVERAGE(B13:K13) -> 0.54480771 | N13: =AVERAGE(G13:K13) -> 0.53241215 | O13: =AVERAGE(I13:K13) -> 0.52025288 | S13: Gross margin increased until 2017; contracting since 2017-2022 due to Covid / Supply Chain / Inflation, but ticking up 2023-2024 (LT target 55/30/25 rule)
A14: EBITDA margin | B14: ='Income Statement'!D11/'Income Statement'!D6 -> 0.19001454 | C14: ='Income Statement'!E11/'Income Statement'!E6 -> 0.20441064 | D14: ='Income Statement'!F11/'Income Statement'!F6 -> 0.21728435 | E14: ='Income Statement'!G11/'Income Statement'!G6 -> 0.21150598 | F14: ='Income Statement'!H11/'Income Statement'!H6 -> 0.212531 | G14: ='Income Statement'!I11/'Income Statement'!I6 -> 0.20788596 | H14: ='Income Statement'!J11/'Income Statement'!J6 -> 0.19639056 | I14: ='Income Statement'!K11/'Income Statement'!K6 -> 0.18431055 | ... K14: ='Income Statement'!M11/'Income Statement'!M6 -> 0.17916475 | M14: =AVERAGE(B14:K14) -> 0.19856744 | N14: =AVERAGE(G14:K14) -> 0.18998558 | O14: =AVERAGE(I14:K14) -> 0.18188379 | S14: EBITDA margin increased until 2017; contracting since 2017 due to Covid / Supply Chain / Inflation (LT target 55/30/25 rule)
A15: EBIT margin | B15: ='Income Statement'!D14/'Income Statement'!D6 -> 0.1729208 | C15: ='Income Statement'!E14/'Income Statement'!E6 -> 0.18742743 | D15: ='Income Statement'!F14/'Income Statement'!F6 -> 0.19949488 | E15: ='Income Statement'!G14/'Income Statement'!G6 -> 0.19241257 | F15: ='Income Statement'!H14/'Income Statement'!H6 -> 0.19459549 | G15: ='Income Statement'!I14/'Income Statement'!I6 -> 0.18903397 | H15: ='Income Statement'!J14/'Income Statement'!J6 -> 0.18201058 | I15: ='Income Statement'!K14/'Income Statement'!K6 -> 0.16832427 | ... K15: ='Income Statement'!M14/'Income Statement'!M6 -> 0.16315275 | M15: =AVERAGE(B15:K15) -> 0.18163772 | N15: =AVERAGE(G15:K15) -> 0.17390521 | O15: =AVERAGE(I15:K15) -> 0.16616051 | S15: EBIT margin increased until 2017; contracting since 2017 due to Covid / Supply Chain / Inflation (should increase LT => 55/30/25 rule)
A16: Net income margin | B16: ='Income Statement'!D20/'Income Statement'!D6 -> 0.11849002 | C16: ='Income Statement'!E20/'Income Statement'!E6 -> 0.13825098 | D16: ='Income Statement'!F20/'Income Statement'!F6 -> 0.13910425 | E16: ='Income Statement'!G20/'Income Statement'!G6 -> 0.15963801 | F16: ='Income Statement'!H20/'Income Statement'!H6 -> 0.13206094 | G16: ='Income Statement'!I20/'Income Statement'!I6 -> 0.14861762 | H16: ='Income Statement'!J20/'Income Statement'!J6 -> 0.14387975 | I16: ='Income Statement'!K20/'Income Statement'!K6 -> 0.12977333 | ... K16: ='Income Statement'!M20/'Income Statement'!M6 -> 0.11792934 | M16: =AVERAGE(B16:K16) -> 0.13505779 | N16: =AVERAGE(G16:K16) -> 0.13260674 | O16: =AVERAGE(I16:K16) -> 0.12351211 | S16: Decreasing since 2018 higher tax rates due to expanding Int'l business has reduced net margin
A18: Shareholder Info
A19: Dividend Payout Ratio (Dividends / Net Income) | B19: =Calcs!D7/Calcs!D6 -> 0.48474569 | C19: =Calcs!E7/Calcs!E6 -> 0.44974158 | D19: =Calcs!F7/Calcs!F6 -> 0.50648026 | E19: =Calcs!G7/Calcs!G6 -> 0.4536533 | F19: =Calcs!H7/Calcs!H6 -> 0.58827002 | G19: =Calcs!I7/Calcs!I6 -> 0.59362543 | H19: =Calcs!J7/Calcs!J6 -> 0.54429082 | I19: =Calcs!K7/Calcs!K6 -> 0.62362429 | ... K19: =Calcs!M7/Calcs!M6 -> 0.67774683 | M19: =AVERAGE(B19:K19) -> 0.55977196 | N19: =AVERAGE(G19:K19) -> 0.62296574 | O19: =AVERAGE(I19:K19) -> 0.65897082 | Q19: 0.56 | S19: 10-yr avg (long-term); Investor Presentation, January 2025, pg. 41, "Annual dividends targeted at >50% of earnings" | T19: =Q19 -> 0.56 | U19: =T19 -> 0.56 | V19: =U19 -> 0.56 | W19: =V19 -> 0.56 | X19: =W19 -> 0.56
A21: Balance Sheet (Current Assets)
A22: Cash & ST Investments (REQUIRED) as % of sales | B22: =SUM('Balance Sheet HISTORICAL'!D6:D7)/'Income Statement'!D6 -> 0.27105381 | C22: =SUM('Balance Sheet HISTORICAL'!E6:E7)/'Income Statement'!E6 -> 0.28508682 | D22: =SUM('Balance Sheet HISTORICAL'!F6:F7)/'Income Statement'!F6 -> 0.30813706 | E22: =SUM('Balance Sheet HISTORICAL'!G6:G7)/'Income Statement'!G6 -> 0.12015382 | F22: =SUM('Balance Sheet HISTORICAL'!H6:H7)/'Income Statement'!H6 -> 0.064327389 | G22: =SUM('Balance Sheet HISTORICAL'!I6:I7)/'Income Statement'!I6 -> 0.13821855 | H22: =SUM('Balance Sheet HISTORICAL'!J6:J7)/'Income Statement'!J6 -> 0.17611025 | I22: =SUM('Balance Sheet HISTORICAL'!K6:K7)/'Income Statement'!K6 -> 0.072940519 | ... K22: =SUM('Balance Sheet HISTORICAL'!M6:M7)/'Income Statement'!M6 -> 0.079076194 | M22: =AVERAGE(B22:K22) -> 0.16047136 | N22: =AVERAGE(G22:K22) -> 0.11119095 | O22: =AVERAGE(I22:K22) -> 0.080541977 | Q22: 0.081 | S22: Downward trend long-term with an uptick in 2021 due to Covid so, went with the 3-yr avg, flat last 3 years | T22: =Q22 -> 0.081 | U22: =T22 -> 0.081 | V22: =U22 -> 0.081 | W22: =V22 -> 0.081 | X22: =W22 -> 0.081
A23: Accounts receivable, net as % of sales | B23: ='Balance Sheet HISTORICAL'!D8/'Income Statement'!D6 -> 0.15536163 | C23: ='Balance Sheet HISTORICAL'!E8/'Income Statement'!E6 -> 0.16991095 | D23: ='Balance Sheet HISTORICAL'!F8/'Income Statement'!F6 -> 0.16887776 | E23: ='Balance Sheet HISTORICAL'!G8/'Income Statement'!G6 -> 0.1689644 | F23: ='Balance Sheet HISTORICAL'!H8/'Income Statement'!H6 -> 0.17211291 | G23: ='Balance Sheet HISTORICAL'!I8/'Income Statement'!I6 -> 0.19748444 | H23: ='Balance Sheet HISTORICAL'!J8/'Income Statement'!J6 -> 0.18347951 | I23: ='Balance Sheet HISTORICAL'!K8/'Income Statement'!K6 -> 0.17333565 | ... K23: ='Balance Sheet HISTORICAL'!M8/'Income Statement'!M6 -> 0.19895285 | M23: =AVERAGE(B23:K23) -> 0.17709614 | N23: =AVERAGE(G23:K23) -> 0.18714675 | O23: =AVERAGE(I23:K23) -> 0.18492327 | Q23: 0.2 | S23: Avg. ex-Covid is 17.4%, average since Covid is 18.5% and on an upward trend so, I went with 20% | T23: =Q23 -> 0.2 | U23: =T23 -> 0.2 | V23: =U23 -> 0.2 | W23: =V23 -> 0.2 | X23: =W23 -> 0.2
A24: Inventories as % of COGS | B24: ='Balance Sheet HISTORICAL'!D9/'Income Statement'!D7 -> 0.18227212 | C24: ='Balance Sheet HISTORICAL'!E9/'Income Statement'!E7 -> 0.19355473 | D24: ='Balance Sheet HISTORICAL'!F9/'Income Statement'!F7 -> 0.21507355 | E24: ='Balance Sheet HISTORICAL'!G9/'Income Statement'!G7 -> 0.20259713 | F24: ='Balance Sheet HISTORICAL'!H9/'Income Statement'!H7 -> 0.21634045 | G24: ='Balance Sheet HISTORICAL'!I9/'Income Statement'!I7 -> 0.22651486 | H24: ='Balance Sheet HISTORICAL'!J9/'Income Statement'!J7 -> 0.25228169 | I24: ='Balance Sheet HISTORICAL'!K9/'Income Statement'!K7 -> 0.40107188 | ... K24: ='Balance Sheet HISTORICAL'!M9/'Income Statement'!M7 -> 0.29256816 | M24: =AVERAGE(B24:K24) -> 0.25169369 | N24: =AVERAGE(G24:K24) -> 0.30141979 | O24: =AVERAGE(I24:K24) -> 0.34276746 | Q24: 0.25 | S24: Pre-Covid avg. is 19.9%; Covid to today avg. is 33.7%; likely to be higher moving forward but not as high as recently, went with 25% | T24: =Q24 -> 0.25 | U24: =T24 -> 0.25 | V24: =U24 -> 0.25 | W24: =V24 -> 0.25 | X24: =W24 -> 0.25
A25: Other current assets as % of sales | B25: ='Balance Sheet HISTORICAL'!D11/'Income Statement'!D6 -> 0.016202565 | C25: ='Balance Sheet HISTORICAL'!E11/'Income Statement'!E6 -> 0.011755589 | D25: ='Balance Sheet HISTORICAL'!F11/'Income Statement'!F6 -> 0.021043032 | E25: ='Balance Sheet HISTORICAL'!G11/'Income Statement'!G6 -> 0.032647276 | F25: ='Balance Sheet HISTORICAL'!H11/'Income Statement'!H6 -> 0.017044998 | G25: ='Balance Sheet HISTORICAL'!I11/'Income Statement'!I6 -> 0.016538637 | H25: ='Balance Sheet HISTORICAL'!J11/'Income Statement'!J6 -> 0.020380694 | I25: ='Balance Sheet HISTORICAL'!K11/'Income Statement'!K6 -> 0.03424309 | ... K25: ='Balance Sheet HISTORICAL'!M11/'Income Statement'!M6 -> 0.020592424 | M25: =AVERAGE(B25:K25) -> 0.021989615 | N25: =AVERAGE(G25:K25) -> 0.024240537 | O25: =AVERAGE(I25:K25) -> 0.028094452 | Q25: 0.02 | S25: Pre-Covid avg. is 2.0%; Covid to today avg. is 2.8%%; on a downward trend so, went with 2% matching historical average | T25: =Q25 -> 0.02 | U25: =T25 -> 0.02 | V25: =U25 -> 0.02 | W25: =V25 -> 0.02 | X25: =W25 -> 0.02
A27: Balance Sheet (Non-Current Assets)
A28: Capital Expenditures (as % of sales) | B28: =Calcs!D20/'Income Statement'!D6 -> 0.015295518 | C28: =Calcs!E20/'Income Statement'!E6 -> 0.011437728 | D28: =Calcs!F20/'Income Statement'!F6 -> 0.052955801 | E28: =Calcs!G20/'Income Statement'!G6 -> 0.030245913 | F28: =Calcs!H20/'Income Statement'!H6 -> 0.031373568 | G28: =Calcs!I20/'Income Statement'!I6 -> 0.047263389 | H28: =Calcs!J20/'Income Statement'!J6 -> 0.030851715 | I28: =Calcs!K20/'Income Statement'!K6 -> 0.016003624 | ... K28: =Calcs!M20/'Income Statement'!M6 -> 0.0071220898 | M28: =AVERAGE(B28:K28) -> 0.025533843 | N28: =AVERAGE(G28:K28) -> 0.022805981 | O28: =AVERAGE(I28:K28) -> 0.0119716 | Q28: 0.02 | S28: Mgmt guidance, January 2025, pg. 41 "Maintenance CAPEX of 1-2% of net sales per fiscal year" (Avg. ex 2017-2021 = 1.3%) | T28: =Q28 -> 0.02 | U28: =T28 -> 0.02 | V28: =U28 -> 0.02 | W28: =V28 -> 0.02 | X28: =W28 -> 0.02
A29: Depreciation (as % of sales) | B29: =Calcs!D26/'Income Statement'!D6 -> 0.0090572524 | C29: =Calcs!E26/'Income Statement'!E6 -> 0.0091654189 | D29: =Calcs!F26/'Income Statement'!F6 -> 0.010223229 | E29: =Calcs!G26/'Income Statement'!G6 -> 0.011869734 | F29: =Calcs!H26/'Income Statement'!H6 -> 0.01154364 | G29: =Calcs!I26/'Income Statement'!I6 -> 0.013439478 | H29: =Calcs!J26/'Income Statement'!J6 -> 0.011411386 | I29: =Calcs!K26/'Income Statement'!K6 -> 0.013222312 | ... K29: =Calcs!M26/'Income Statement'!M6 -> 0.014139194 | M29: =AVERAGE(B29:K29) -> 0.011737259 | N29: =AVERAGE(G29:K29) -> 0.013102663 | O29: =AVERAGE(I29:K29) -> 0.013554151 | Q29: 0.014 | S29: Depreciation increasing after Capex build due to Real Estate purchase and development 2017-2021; went with 3-yr avg. | T29: =Q29 -> 0.014 | U29: =T29 -> 0.014 | V29: =U29 -> 0.014 | W29: =V29 -> 0.014 | X29: =W29 -> 0.014
A30: GOODWILL (ACTUAL) | B30: ='Balance Sheet HISTORICAL'!D14 -> 96409 | C30: ='Balance Sheet HISTORICAL'!E14 -> 95649 | D30: ='Balance Sheet HISTORICAL'!F14 -> 95597 | E30: ='Balance Sheet HISTORICAL'!G14 -> 95621 | F30: ='Balance Sheet HISTORICAL'!H14 -> 95347 | G30: ='Balance Sheet HISTORICAL'!I14 -> 95731 | H30: ='Balance Sheet HISTORICAL'!J14 -> 95869 | I30: ='Balance Sheet HISTORICAL'!K14 -> 95180 | ... K30: ='Balance Sheet HISTORICAL'!M14 -> 96985 | M30: =NA() -> #N/A | N30: =NA() -> #N/A | O30: =NA() -> #N/A | Q30: =K30 -> 96985 | S30: KEEP FLAT (SAME) = NO Cash Flow | T30: =Q30 -> 96985 | U30: =T30 -> 96985 | V30: =U30 -> 96985 | W30: =V30 -> 96985 | X30: =W30 -> 96985
A31: NEW Intangibles (NEW PURCHASES) | B31: =Calcs!D14 -> 2329 | C31: =Calcs!E14 -> -794 | D31: =Calcs!F14 -> -68 | E31: =Calcs!G14 -> 220 | F31: =Calcs!H14 -> -155 | G31: =Calcs!I14 -> 192 | H31: =Calcs!J14 -> 60 | I31: =Calcs!K14 -> -222 | ... K31: =Calcs!M14 -> 2658 | M31: =NA() -> #N/A | N31: =NA() -> #N/A | O31: =NA() -> #N/A | Q31: 0 | S31: Make ZERO (no assumption of increasing intangibles) | T31: =Q31 -> 0 | U31: =T31 -> 0 | V31: =U31 -> 0 | W31: =V31 -> 0 | X31: =W31 -> 0
A32: Right-of-use assets (ACTUAL) | B32: ='Balance Sheet HISTORICAL'!D16 -> 0 | C32: ='Balance Sheet HISTORICAL'!E16 -> 0 | D32: ='Balance Sheet HISTORICAL'!F16 -> 0 | E32: ='Balance Sheet HISTORICAL'!G16 -> 0 | F32: ='Balance Sheet HISTORICAL'!H16 -> 0 | G32: ='Balance Sheet HISTORICAL'!I16 -> 8168 | H32: ='Balance Sheet HISTORICAL'!J16 -> 8824 | I32: ='Balance Sheet HISTORICAL'!K16 -> 7559 | ... K32: ='Balance Sheet HISTORICAL'!M16 -> 11611 | M32: =NA() -> #N/A | N32: =NA() -> #N/A | O32: =NA() -> #N/A | Q32: =K32 -> 11611 | S32: KEEP FLAT (SAME) = NO Cash Flow | T32: =Q32 -> 11611 | U32: =T32 -> 11611 | V32: =U32 -> 11611 | W32: =V32 -> 11611 | X32: =W32 -> 11611
A33: Deferred tax assets, net (ACTUAL) | B33: ='Balance Sheet HISTORICAL'!D17 -> 0 | C33: ='Balance Sheet HISTORICAL'!E17 -> 621 | D33: ='Balance Sheet HISTORICAL'!F17 -> 495 | E33: ='Balance Sheet HISTORICAL'!G17 -> 511 | F33: ='Balance Sheet HISTORICAL'!H17 -> 403 | G33: ='Balance Sheet HISTORICAL'!I17 -> 464 | H33: ='Balance Sheet HISTORICAL'!J17 -> 858 | I33: ='Balance Sheet HISTORICAL'!K17 -> 679 | ... K33: ='Balance Sheet HISTORICAL'!M17 -> 993 | M33: =NA() -> #N/A | N33: =NA() -> #N/A | O33: =NA() -> #N/A | Q33: =K33 -> 993 | S33: KEEP FLAT (SAME) = NO Cash Flow | T33: =Q33 -> 993 | U33: =T33 -> 993 | V33: =U33 -> 993 | W33: =V33 -> 993 | X33: =W33 -> 993
A34: Other assets as % of sales | B34: ='Balance Sheet HISTORICAL'!D18/'Income Statement'!D6 -> 0.0086182732 | C34: ='Balance Sheet HISTORICAL'!E18/'Income Statement'!E6 -> 0.0083799616 | D34: ='Balance Sheet HISTORICAL'!F18/'Income Statement'!F6 -> 0.0081155093 | E34: ='Balance Sheet HISTORICAL'!G18/'Income Statement'!G6 -> 0.0075247602 | F34: ='Balance Sheet HISTORICAL'!H18/'Income Statement'!H6 -> 0.0075327743 | G34: ='Balance Sheet HISTORICAL'!I18/'Income Statement'!I6 -> 0.0091261157 | H34: ='Balance Sheet HISTORICAL'!J18/'Income Statement'!J6 -> 0.01238248 | I34: ='Balance Sheet HISTORICAL'!K18/'Income Statement'!K6 -> 0.018642304 | ... K34: ='Balance Sheet HISTORICAL'!M18/'Income Statement'!M6 -> 0.02506786 | M34: =AVERAGE(B34:K34) -> 0.013043215 | N34: =AVERAGE(G34:K34) -> 0.018052174 | O34: =AVERAGE(I34:K34) -> 0.022917425 | Q34: 0.025 | S34: Pre-Covid avg. is 0.8%; Covid to today avg. is 2.3%%; flat last 2 years so, stuck with that, 2.5% | T34: =Q34 -> 0.025 | U34: =T34 -> 0.025 | V34: =U34 -> 0.025 | W34: =V34 -> 0.025 | X34: =W34 -> 0.025
A36: Balance Sheet (NON-Debt Current Liabilities)
A37: Accounts payable as % of COGS | B37: ='Balance Sheet HISTORICAL'!D22/'Income Statement'!D7 -> 0.097402872 | C37: ='Balance Sheet HISTORICAL'!E22/'Income Statement'!E7 -> 0.1137841 | D37: ='Balance Sheet HISTORICAL'!F22/'Income Statement'!F7 -> 0.12718186 | E37: ='Balance Sheet HISTORICAL'!G22/'Income Statement'!G7 -> 0.1059953 | F37: ='Balance Sheet HISTORICAL'!H22/'Income Statement'!H7 -> 0.099587228 | G37: ='Balance Sheet HISTORICAL'!I22/'Income Statement'!I7 -> 0.11898837 | H37: ='Balance Sheet HISTORICAL'!J22/'Income Statement'!J7 -> 0.15158531 | I37: ='Balance Sheet HISTORICAL'!K22/'Income Statement'!K7 -> 0.12656952 | ... K37: ='Balance Sheet HISTORICAL'!M22/'Income Statement'!M7 -> 0.13302588 | M37: =AVERAGE(B37:K37) -> 0.11933537 | N37: =AVERAGE(G37:K37) -> 0.12988047 | O37: =AVERAGE(I37:K37) -> 0.12627623 | Q37: 0.124 | S37: Pre-Covid avg. is 10.7%; Covid to today avg. is 12.4%; choppy overall, higher post Covid, went with 3-yr avg 12.4% | T37: =Q37 -> 0.124 | U37: =T37 -> 0.124 | V37: =U37 -> 0.124 | W37: =V37 -> 0.124 | X37: =W37 -> 0.124
A38: Accrued liabilities as % of sales | B38: ='Balance Sheet HISTORICAL'!D23/'Income Statement'!D6 -> 0.04019569 | C38: ='Balance Sheet HISTORICAL'!E23/'Income Statement'!E6 -> 0.041392807 | D38: ='Balance Sheet HISTORICAL'!F23/'Income Statement'!F6 -> 0.049925625 | E38: ='Balance Sheet HISTORICAL'!G23/'Income Statement'!G6 -> 0.064232176 | F38: ='Balance Sheet HISTORICAL'!H23/'Income Statement'!H6 -> 0.043729774 | G38: ='Balance Sheet HISTORICAL'!I23/'Income Statement'!I6 -> 0.053023515 | H38: ='Balance Sheet HISTORICAL'!J23/'Income Statement'!J6 -> 0.052566128 | I38: ='Balance Sheet HISTORICAL'!K23/'Income Statement'!K6 -> 0.05235149 | ... K38: ='Balance Sheet HISTORICAL'!M23/'Income Statement'!M6 -> 0.052953398 | M38: =AVERAGE(B38:K38) -> 0.050621001 | N38: =AVERAGE(G38:K38) -> 0.053346787 | O38: =AVERAGE(I38:K38) -> 0.053714765 | Q38: 0.053 | S38: Pre-Covid avg. is 4.8%; 5-yr avg is 5.3% and it has been 5.3% in 3 out of last 5 years so, went with that | T38: =Q38 -> 0.053 | U38: =T38 -> 0.053 | V38: =U38 -> 0.053 | W38: =V38 -> 0.053 | X38: =W38 -> 0.053
A39: Accrued payroll & related expenses as % of sales | B39: ='Balance Sheet HISTORICAL'!D24/'Income Statement'!D6 -> 0.035321962 | C39: ='Balance Sheet HISTORICAL'!E24/'Income Statement'!E6 -> 0.054813881 | D39: ='Balance Sheet HISTORICAL'!F24/'Income Statement'!F6 -> 0.037376546 | E39: ='Balance Sheet HISTORICAL'!G24/'Income Statement'!G6 -> 0.036284815 | F39: ='Balance Sheet HISTORICAL'!H24/'Income Statement'!H6 -> 0.036142672 | G39: ='Balance Sheet HISTORICAL'!I24/'Income Statement'!I6 -> 0.036149504 | H39: ='Balance Sheet HISTORICAL'!J24/'Income Statement'!J6 -> 0.052574323 | I39: ='Balance Sheet HISTORICAL'!K24/'Income Statement'!K6 -> 0.022325662 | ... K39: ='Balance Sheet HISTORICAL'!M24/'Income Statement'!M6 -> 0.044119365 | M39: =AVERAGE(B39:K39) -> 0.038623361 | N39: =AVERAGE(G39:K39) -> 0.037258748 | O39: =AVERAGE(I39:K39) -> 0.032523304 | Q39: 0.04 | S39: Close to 4% long-term, recent upward trend, went with 4.0% | T39: =Q39 -> 0.04 | U39: =T39 -> 0.04 | V39: =U39 -> 0.04 | W39: =V39 -> 0.04 | X39: =W39 -> 0.04
A40: Income taxes payable as % of sales | B40: ='Balance Sheet HISTORICAL'!D27/'Income Statement'!D6 -> 0.0060478646 | C40: ='Balance Sheet HISTORICAL'!E27/'Income Statement'!E6 -> 0.0088817086 | D40: ='Balance Sheet HISTORICAL'!F27/'Income Statement'!F6 -> 0.0034322718 | E40: ='Balance Sheet HISTORICAL'!G27/'Income Statement'!G6 -> 0.0052017292 | F40: ='Balance Sheet HISTORICAL'!H27/'Income Statement'!H6 -> 0.0019936223 | G40: ='Balance Sheet HISTORICAL'!I27/'Income Statement'!I6 -> 0.0029694148 | H40: ='Balance Sheet HISTORICAL'!J27/'Income Statement'!J6 -> 0.0006494451 | I40: ='Balance Sheet HISTORICAL'!K27/'Income Statement'!K6 -> 9.8299988e-05 | ... K40: ='Balance Sheet HISTORICAL'!M27/'Income Statement'!M6 -> 0.0026314141 | M40: =AVERAGE(B40:K40) -> 0.0032825259 | N40: =AVERAGE(G40:K40) -> 0.0014536126 | O40: =AVERAGE(I40:K40) -> 0.001216401 | Q40: 0.001 | S40: Higher Pre vs. Post Covid, lower recently, 3 and 5-yr avg are the same so, went with 0.1% | T40: =Q40 -> 0.001 | U40: =T40 -> 0.001 | V40: =U40 -> 0.001 | W40: =V40 -> 0.001 | X40: =W40 -> 0.001
A42: Balance Sheet (NON-Debt Non-Current Liabilities)
A43: Deferred tax liabilities, net (ACTUAL) | B43: ='Balance Sheet HISTORICAL'!D31 -> 23145 | C43: ='Balance Sheet HISTORICAL'!E31 -> 16365 | D43: ='Balance Sheet HISTORICAL'!F31 -> 18949 | E43: ='Balance Sheet HISTORICAL'!G31 -> 11050 | F43: ='Balance Sheet HISTORICAL'!H31 -> 11688 | G43: ='Balance Sheet HISTORICAL'!I31 -> 11291 | H43: ='Balance Sheet HISTORICAL'!J31 -> 10401 | I43: ='Balance Sheet HISTORICAL'!K31 -> 10528 | ... K43: ='Balance Sheet HISTORICAL'!M31 -> 9066 | M43: =NA() -> #N/A | N43: =NA() -> #N/A | O43: =NA() -> #N/A | Q43: =K43 -> 9066 | S43: KEEP FLAT (SAME) = NO Cash Flow | T43: =Q43 -> 9066 | U43: =T43 -> 9066 | V43: =U43 -> 9066 | W43: =V43 -> 9066 | X43: =W43 -> 9066
A44: Long-term operating lease liabilities (ACTUAL) | B44: ='Balance Sheet HISTORICAL'!D32 -> 0 | C44: ='Balance Sheet HISTORICAL'!E32 -> 0 | D44: ='Balance Sheet HISTORICAL'!F32 -> 0 | E44: ='Balance Sheet HISTORICAL'!G32 -> 0 | F44: ='Balance Sheet HISTORICAL'!H32 -> 0 | G44: ='Balance Sheet HISTORICAL'!I32 -> 6520 | H44: ='Balance Sheet HISTORICAL'!J32 -> 7062 | I44: ='Balance Sheet HISTORICAL'!K32 -> 5999 | ... K44: ='Balance Sheet HISTORICAL'!M32 -> 5904 | M44: =NA() -> #N/A | N44: =NA() -> #N/A | O44: =NA() -> #N/A | Q44: =K44 -> 5904 | S44: KEEP FLAT (SAME) = NO Cash Flow | T44: =Q44 -> 5904 | U44: =T44 -> 5904 | V44: =U44 -> 5904 | W44: =V44 -> 5904 | X44: =W44 -> 5904
A45: Other long-term liabilities as % of sales | B45: ='Balance Sheet HISTORICAL'!D33/'Income Statement'!D6 -> 0.0060346423 | C45: ='Balance Sheet HISTORICAL'!E33/'Income Statement'!E6 -> 0.0058160612 | D45: ='Balance Sheet HISTORICAL'!F33/'Income Statement'!F6 -> 0.0051457796 | E45: ='Balance Sheet HISTORICAL'!G33/'Income Statement'!G6 -> 0.0044477844 | F45: ='Balance Sheet HISTORICAL'!H33/'Income Statement'!H6 -> 0.02524625 | G45: ='Balance Sheet HISTORICAL'!I33/'Income Statement'!I6 -> 0.027659866 | H45: ='Balance Sheet HISTORICAL'!J33/'Income Statement'!J6 -> 0.023523434 | I45: ='Balance Sheet HISTORICAL'!K33/'Income Statement'!K6 -> 0.021558537 | ... K45: ='Balance Sheet HISTORICAL'!M33/'Income Statement'!M6 -> 0.023818192 | M45: =AVERAGE(B45:K45) -> 0.016757047 | N45: =AVERAGE(G45:K45) -> 0.02417599 | O45: =AVERAGE(I45:K45) -> 0.023232217 | Q45: 0.024 | S45: Noticeable change 2018-2019, higher since, 2.4% 3 out of last 5 years, went with 5-yr avg of 2.4% | T45: =Q45 -> 0.024 | U45: =T45 -> 0.024 | V45: =U45 -> 0.024 | W45: =V45 -> 0.024 | X45: =W45 -> 0.024
A47: Shareholders' equity
A48: Common stock | B48: ='Balance Sheet HISTORICAL'!D37 -> 20 | C48: ='Balance Sheet HISTORICAL'!E37 -> 20 | D48: ='Balance Sheet HISTORICAL'!F37 -> 20 | E48: ='Balance Sheet HISTORICAL'!G37 -> 20 | F48: ='Balance Sheet HISTORICAL'!H37 -> 20 | G48: ='Balance Sheet HISTORICAL'!I37 -> 20 | H48: ='Balance Sheet HISTORICAL'!J37 -> 20 | I48: ='Balance Sheet HISTORICAL'!K37 -> 20 | ... K48: ='Balance Sheet HISTORICAL'!M37 -> 20 | M48: Don't Calc Anything Here | Q48: =K48 -> 20 | S48: KEEP FLAT (SAME) = NO Cash Flow | T48: =Q48 -> 20 | U48: =T48 -> 20 | V48: =U48 -> 20 | W48: =V48 -> 20 | X48: =W48 -> 20
A49: Additional paid-in capital | B49: ='Balance Sheet HISTORICAL'!D38 -> 141651 | C49: ='Balance Sheet HISTORICAL'!E38 -> 145936 | D49: ='Balance Sheet HISTORICAL'!F38 -> 150692 | E49: ='Balance Sheet HISTORICAL'!G38 -> 153469 | F49: ='Balance Sheet HISTORICAL'!H38 -> 155132 | G49: ='Balance Sheet HISTORICAL'!I38 -> 157850 | H49: ='Balance Sheet HISTORICAL'!J38 -> 163737 | I49: ='Balance Sheet HISTORICAL'!K38 -> 165973 | ... K49: ='Balance Sheet HISTORICAL'!M38 -> 175642 | M49: Don't Calc Anything Here | Q49: =K49 -> 175642 | S49: KEEP FLAT (SAME) = NO Cash Flow | T49: =Q49 -> 175642 | U49: =T49 -> 175642 | V49: =U49 -> 175642 | W49: =V49 -> 175642 | X49: =W49 -> 175642
A50: Accumulated other comprehensive income (loss) | B50: ='Balance Sheet HISTORICAL'!D40 -> -8722 | C50: ='Balance Sheet HISTORICAL'!E40 -> -27298 | D50: ='Balance Sheet HISTORICAL'!F40 -> -28075 | E50: ='Balance Sheet HISTORICAL'!G40 -> -27636 | F50: ='Balance Sheet HISTORICAL'!H40 -> -32482 | G50: ='Balance Sheet HISTORICAL'!I40 -> -28208 | H50: ='Balance Sheet HISTORICAL'!J40 -> -26030 | I50: ='Balance Sheet HISTORICAL'!K40 -> -36209 | ... K50: ='Balance Sheet HISTORICAL'!M40 -> -29268 | M50: Don't Calc Anything Here | Q50: =K50 -> -29268 | S50: KEEP FLAT (SAME) = NO Cash Flow | T50: =Q50 -> -29268 | U50: =T50 -> -29268 | V50: =U50 -> -29268 | W50: =V50 -> -29268 | X50: =W50 -> -29268
A51: Treasury stock | B51: ='Balance Sheet HISTORICAL'!D41-'Balance Sheet HISTORICAL'!C41 -> -30259 | C51: ='Balance Sheet HISTORICAL'!E41-'Balance Sheet HISTORICAL'!D41 -> -32131 | D51: ='Balance Sheet HISTORICAL'!F41-'Balance Sheet HISTORICAL'!E41 -> -31109 | E51: ='Balance Sheet HISTORICAL'!G41-'Balance Sheet HISTORICAL'!F41 -> -22616 | F51: ='Balance Sheet HISTORICAL'!H41-'Balance Sheet HISTORICAL'!G41 -> -29625 | G51: ='Balance Sheet HISTORICAL'!I41-'Balance Sheet HISTORICAL'!H41 -> -16825 | H51: ='Balance Sheet HISTORICAL'!J41-'Balance Sheet HISTORICAL'!I41 -> 0 | I51: ='Balance Sheet HISTORICAL'!K41-'Balance Sheet HISTORICAL'!J41 -> -29156 | ... K51: ='Balance Sheet HISTORICAL'!M41-'Balance Sheet HISTORICAL'!L41 -> -8129 | M51: Don't Calc Anything Here | Q51: -7000 | S51: New $50mm plan good through 8/2025. Last 4 plans averaged $60mm completed out of $75mm authorized (80% completion). As of November 30, 2024, the Company is authorized to purchase an additional $38.3 million under the 2023 Repurchase Plan. Purchased $0.0 in 4Q24, $3.6mm in 1Q25. 80% of $50mm is $40mm. Still have $38.3mm left with 9 mos remaining so, completed $11.7mm over 5 quarters ($2.34mm avg) with 3 left; 3 x 2.34 = 7.02mm | T51: =Q51 -> -7000 | U51: 0 | V51: 0 | W51: 0 | X51: 0
A53: Interest Rate
A54: Revolving Credit Facility | T54: =5.4%+1% -> 0.064 | U54: =T54 -> 0.064 | V54: =U54 -> 0.064 | W54: =V54 -> 0.064 | X54: =W54 -> 0.064
A55: Series A Notes - 3.39% fixed rate | T55: 0.0339 | U55: =T55 -> 0.0339 | V55: =U55 -> 0.0339 | W55: =V55 -> 0.0339 | X55: =W55 -> 0.0339
A56: Series B Notes - 2.50% fixed rate | T56: 0.025 | U56: =T56 -> 0.025 | V56: =U56 -> 0.025 | W56: =V56 -> 0.025 | X56: =W56 -> 0.025
A57: Series C Notes - 2.69% fixed rate | T57: 0.0269 | U57: =T57 -> 0.0269 | V57: =U57 -> 0.0269 | W57: =V57 -> 0.0269 | X57: =W57 -> 0.0269
A58: CASH | T58: 0.0475 | U58: =T58 -> 0.0475 | V58: =U58 -> 0.0475 | W58: =V58 -> 0.0475 | X58: =W58 -> 0.0475

Sheet Debt
A1: WD-40 Debt Schedule
A2: (USD in thousands, except per share data)
B4: Historical | E4: Projected
B5: 44804 | C5: 45169 | D5: 45535 | E5: 45900 | F5: 46265 | G5: 46630 | H5: 46996 | I5: 47361
A6: SHORT-TERM DEBT
A7: NEW REVOLVER | D7: 0 | E7: ='Balance Sheet PROJECTED'!N27 -> 0 | F7: ='Balance Sheet PROJECTED'!O27 -> 0 | G7: ='Balance Sheet PROJECTED'!P27 -> 0 | H7: ='Balance Sheet PROJECTED'!Q27 -> 0 | I7: ='Balance Sheet PROJECTED'!R27 -> 0
A9: Interest Rate | E9: =Assumptions!T54 -> 0.064 | F9: =Assumptions!U54 -> 0.064 | G9: =Assumptions!V54 -> 0.064 | H9: =Assumptions!W54 -> 0.064 | I9: =Assumptions!X54 -> 0.064
A11: Average Balance | E11: =AVERAGE(D7:E7) -> 0 | F11: =AVERAGE(E7:F7) -> 0 | G11: =AVERAGE(F7:G7) -> 0 | H11: =AVERAGE(G7:H7) -> 0 | I11: =AVERAGE(H7:I7) -> 0
A12: Interest Expense | E12: =E9*E11 -> 0 | F12: =F9*F11 -> 0 | G12: =G9*G11 -> 0 | H12: =H9*H11 -> 0 | I12: =I9*I11 -> 0
A14: LONG-TERM DEBT
A15: OLD REVOLVER (Beginning) | E15: =D17 -> 27836 | F15: =E17 -> 22268.8 | G15: =F17 -> 16701.6 | H15: =G17 -> 11134.4 | I15: =H17 -> 5567.2
A16: Paydown (5 years, 4/30/29) | E16: =$D$17/5 -> 5567.2 | F16: =$D$17/5 -> 5567.2 | G16: =$D$17/5 -> 5567.2 | H16: =$D$17/5 -> 5567.2 | I16: =$D$17/5 -> 5567.2
A17: OLD REVOLVER (Ending) | D17: ='Balance Sheet PROJECTED'!M30 -> 27836 | E17: =E15-E16 -> 22268.8 | F17: =F15-F16 -> 16701.6 | G17: =G15-G16 -> 11134.4 | H17: =H15-H16 -> 5567.2 | I17: =I15-I16 -> 0
A19: Interest Rate | E19: =Assumptions!T54 -> 0.064 | F19: =Assumptions!U54 -> 0.064 | G19: =Assumptions!V54 -> 0.064 | H19: =Assumptions!W54 -> 0.064 | I19: =Assumptions!X54 -> 0.064
A21: Average Balance | E21: =AVERAGE(D17:E17) -> 25052.4 | F21: =AVERAGE(E17:F17) -> 19485.2 | G21: =AVERAGE(F17:G17) -> 13918 | H21: =AVERAGE(G17:H17) -> 8350.8 | I21: =AVERAGE(H17:I17) -> 2783.6
A22: Interest Expense | E22: =E19*E21 -> 1603.3536 | F22: =F19*F21 -> 1247.0528 | G22: =G19*G21 -> 890.752 | H22: =H19*H21 -> 534.4512 | I22: =I19*I21 -> 178.1504
A24: Series A Notes Beginning | E24: =D26 -> 14800 | F24: =E26 -> 14000 | G24: =F26 -> 13200 | H24: =G26 -> 12400 | I24: =H26 -> 11600
A25: Paydown (11/15/2032) | E25: 800 | F25: 800 | G25: 800 | H25: 800 | I25: 800
A26: Series A Notes Ending | D26: ='Balance Sheet PROJECTED'!M31 -> 14800 | E26: =E24-E25 -> 14000 | F26: =F24-F25 -> 13200 | G26: =G24-G25 -> 12400 | H26: =H24-H25 -> 11600 | I26: =I24-I25 -> 10800
A28: Interest Rate | E28: =Assumptions!T55 -> 0.0339 | F28: =Assumptions!U55 -> 0.0339 | G28: =Assumptions!V55 -> 0.0339 | H28: =Assumptions!W55 -> 0.0339 | I28: =Assumptions!X55 -> 0.0339
A30: Average Balance | E30: =AVERAGE(D26:E26) -> 14400 | F30: =AVERAGE(E26:F26) -> 13600 | G30: =AVERAGE(F26:G26) -> 12800 | H30: =AVERAGE(G26:H26) -> 12000 | I30: =AVERAGE(H26:I26) -> 11200
A31: Interest Expense | E31: =E28*E30 -> 488.16 | F31: =F28*F30 -> 461.04 | G31: =G28*G30 -> 433.92 | H31: =H28*H30 -> 406.8 | I31: =I28*I30 -> 379.68
A33: Series B Notes Beginning | E33: =D35 -> 26000 | F33: =E35 -> 26000 | G33: =F35 -> 26000 | H33: =G35 -> 26000 | I33: =H35 -> 0
A34: Paydown (11/15/2027) | E34: 0 | F34: 0 | G34: 0 | H34: =H33 -> 26000 | I34: 0
A35: Series B Notes Ending | D35: ='Balance Sheet PROJECTED'!M32 -> 26000 | E35: =E33-E34 -> 26000 | F35: =F33-F34 -> 26000 | G35: =G33-G34 -> 26000 | H35: =H33-H34 -> 0 | I35: =I33-I34 -> 0
A37: Interest Rate | E37: =Assumptions!T56 -> 0.025 | F37: =Assumptions!U56 -> 0.025 | G37: =Assumptions!V56 -> 0.025 | H37: =Assumptions!W56 -> 0.025 | I37: =Assumptions!X56 -> 0.025
A39: Average Balance | E39: =AVERAGE(D35:E35) -> 26000 | F39: =AVERAGE(E35:F35) -> 26000 | G39: =AVERAGE(F35:G35) -> 26000 | H39: =AVERAGE(G35:H35) -> 13000 | I39: =AVERAGE(H35:I35) -> 0
A40: Interest Expense | E40: =E37*E39 -> 650 | F40: =F37*F39 -> 650 | G40: =G37*G39 -> 650 | H40: =H37*H39 -> 325 | I40: =I37*I39 -> 0
A42: Series C Notes Beginning | E42: =D44 -> 26000 | F42: =E44 -> 26000 | G42: =F44 -> 26000 | H42: =G44 -> 26000 | I42: =H44 -> 26000
A43: Paydown (11/15/2030) | E43: 0 | F43: 0 | G43: 0 | H43: 0 | I43: 0
A44: Series C Notes Ending | D44: ='Balance Sheet PROJECTED'!M33 -> 26000 | E44: =E42-E43 -> 26000 | F44: =F42-F43 -> 26000 | G44: =G42-G43 -> 26000 | H44: =H42-H43 -> 26000 | I44: =I42-I43 -> 26000
A46: Interest Rate | E46: =Assumptions!T57 -> 0.0269 | F46: =Assumptions!U57 -> 0.0269 | G46: =Assumptions!V57 -> 0.0269 | H46: =Assumptions!W57 -> 0.0269 | I46: =Assumptions!X57 -> 0.0269
A48: Average Balance | E48: =AVERAGE(D44:E44) -> 26000 | F48: =AVERAGE(E44:F44) -> 26000 | G48: =AVERAGE(F44:G44) -> 26000 | H48: =AVERAGE(G44:H44) -> 26000 | I48: =AVERAGE(H44:I44) -> 26000
A49: Interest Expense | E49: =E46*E48 -> 699.4 | F49: =F46*F48 -> 699.4 | G49: =G46*G48 -> 699.4 | H49: =H46*H48 -> 699.4 | I49: =I46*I48 -> 699.4
A51: Summary
A52: ST Debt | D52: =D7 -> 0 | E52: =E7 -> 0 | F52: =F7 -> 0 | G52: =G7 -> 0 | H52: =H7 -> 0 | I52: =I7 -> 0
A53: LT Debt | D53: =SUM(D17,D26,D35,D44) -> 94636 | E53: =SUM(E17,E26,E35,E44) -> 88268.8 | F53: =SUM(F17,F26,F35,F44) -> 81901.6 | G53: =SUM(G17,G26,G35,G44) -> 75534.4 | H53: =SUM(H17,H26,H35,H44) -> 43167.2 | I53: =SUM(I17,I26,I35,I44) -> 36800
A54: Total Debt | D54: =SUM(D52:D53) -> 94636 | E54: =SUM(E52:E53) -> 88268.8 | F54: =SUM(F52:F53) -> 81901.6 | G54: =SUM(G52:G53) -> 75534.4 | H54: =SUM(H52:H53) -> 43167.2 | I54: =SUM(I52:I53) -> 36800
A56: Interest Expense Summary
A57: ST Debt Interest | E57: =E12 -> 0 | F57: =F12 -> 0 | G57: =G12 -> 0 | H57: =H12 -> 0 | I57: =I12 -> 0
A58: LT Debt Interest | E58: =SUM(E22,E31,E40,E49) -> 3440.9136 | F58: =SUM(F22,F31,F40,F49) -> 3057.4928 | G58: =SUM(G22,G31,G40,G49) -> 2674.072 | H58: =SUM(H22,H31,H40,H49) -> 1965.6512 | I58: =SUM(I22,I31,I40,I49) -> 1257.2304
A59: Total Interest Expense | E59: =SUM(E57:E58) -> 3440.9136 | F59: =SUM(F57:F58) -> 3057.4928 | G59: =SUM(G57:G58) -> 2674.072 | H59: =SUM(H57:H58) -> 1965.6512 | I59: =SUM(I57:I58) -> 1257.2304
A61: CASH
A62: Required CASH | B62: ='Balance Sheet PROJECTED'!K6 -> 37843 | C62: ='Balance Sheet PROJECTED'!L6 -> 48143 | D62: ='Balance Sheet PROJECTED'!M6 -> 46699 | E62: ='Balance Sheet PROJECTED'!N6 -> 51183.575 | F62: ='Balance Sheet PROJECTED'!O6 -> 54766.425 | G62: ='Balance Sheet PROJECTED'!P6 -> 58600.075 | H62: ='Balance Sheet PROJECTED'!Q6 -> 62702.081 | I62: ='Balance Sheet PROJECTED'!R6 -> 67091.226
A63: EXCESS CASH | E63: ='Balance Sheet PROJECTED'!N7 -> 13971.342 | F63: ='Balance Sheet PROJECTED'!O7 -> 33162.133 | G63: ='Balance Sheet PROJECTED'!P7 -> 54645.131 | H63: ='Balance Sheet PROJECTED'!Q7 -> 52487.115 | I63: ='Balance Sheet PROJECTED'!R7 -> 78167.863
A64: Total CASH | D64: =SUM(D62:D63) -> 46699 | E64: =SUM(E62:E63) -> 65154.917 | F64: =SUM(F62:F63) -> 87928.558 | G64: =SUM(G62:G63) -> 113245.21 | H64: =SUM(H62:H63) -> 115189.2 | I64: =SUM(I62:I63) -> 145259.09
A66: Interest Rate | E66: =Assumptions!T58 -> 0.0475 | F66: =Assumptions!U58 -> 0.0475 | G66: =Assumptions!V58 -> 0.0475 | H66: =Assumptions!W58 -> 0.0475 | I66: =Assumptions!X58 -> 0.0475
A68: Average Balance | E68: =AVERAGE(D64:E64) -> 55926.959 | F68: =AVERAGE(E64:F64) -> 76541.738 | G68: =AVERAGE(F64:G64) -> 100586.88 | H68: =AVERAGE(G64:H64) -> 114217.2 | I68: =AVERAGE(H64:I64) -> 130224.14
A69: Interest Income | E69: =E66*E68 -> 2656.5305 | F69: =F66*F68 -> 3635.7325 | G69: =G66*G68 -> 4777.8769 | H69: =H66*H68 -> 5425.317 | I69: =I66*I68 -> 6185.6468

Sheet Calcs
A1: WD-40 Calculations
B2: (USD in thousands, except per share data) | K2: Historical | N2: Projected
C3: 41882 | D3: 42247 | E3: 42613 | F3: 42978 | G3: 43343 | H3: 43708 | I3: 44074 | J3: 44439 | K3: 44804 | L3: 45169 | M3: 45535 | N3: 45900 | O3: 46265 | P3: 46630 | Q3: 46996 | R3: 47361
A4: Retained Earnings
B5: Beginning Balance (Previous Ending) | D5: =C9 -> 237596 | E5: =D9 -> 260683 | F5: =E9 -> 289642 | G5: =F9 -> 315764 | H5: =G9 -> 351266 | I5: =H9 -> 374060 | J5: =I9 -> 398731 | K5: =J9 -> 430735 | ... R5: =Q9 -> 667138.5
B6: Net Income | D6: ='Income Statement'!D20 -> 44807 | E6: ='Income Statement'!E20 -> 52628 | F6: ='Income Statement'!F20 -> 52930 | G6: ='Income Statement'!G20 -> 65215 | H6: ='Income Statement'!H20 -> 55908 | I6: ='Income Statement'!I20 -> 60710 | J6: ='Income Statement'!J20 -> 70229 | K6: ='Income Statement'!K20 -> 67329 | ... R6: ='Income Statement'!R20 -> 115573.96
B7: Dividends Paid (from CFS) | D7: 21720 | E7: 23669 | F7: 26808 | G7: 29585 | H7: 32889 | I7: 36039 | J7: 38225 | K7: 41988 | L7: 44581 | M7: 47201 | N7: =Assumptions!T19*Calcs!N6 -> 47072.172 | O7: =Assumptions!U19*Calcs!O6 -> 50978.463 | P7: =Assumptions!V19*Calcs!P6 -> 55187.325 | Q7: =Assumptions!W19*Calcs!Q6 -> 59571.584 | R7: =Assumptions!X19*Calcs!R6 -> 64721.416
B8: Cumulative effect of change in accounting principle | D8: 0 | E8: 0 | F8: 0 | G8: -128 | H8: -225 | I8: 0 | J8: 0 | K8: 0 | L8: 0 | M8: 0 | N8: =M8 -> 0 | O8: =N8 -> 0 | P8: =O8 -> 0 | Q8: =P8 -> 0 | R8: =Q8 -> 0
B9: Ending Balance (CALCULATED) | C9: ='Balance Sheet HISTORICAL'!$C$39 -> 237596 | D9: =D5+D6-D7+D8 -> 260683 | E9: =E5+E6-E7+E8 -> 289642 | F9: =F5+F6-F7+F8 -> 315764 | G9: =G5+G6-G7+G8 -> 351266 | H9: =H5+H6-H7+H8 -> 374060 | I9: =I5+I6-I7+I8 -> 398731 | J9: =J5+J6-J7+J8 -> 430735 | K9: =K5+K6-K7+K8 -> 456076 | ... R9: =R5+R6-R7+R8 -> 717991.04
B10: Check (Actual from Balance Sheet) | D10: ='Balance Sheet HISTORICAL'!D39 -> 260683 | E10: ='Balance Sheet HISTORICAL'!E39 -> 289642 | F10: ='Balance Sheet HISTORICAL'!F39 -> 315764 | G10: ='Balance Sheet HISTORICAL'!G39 -> 351266 | H10: ='Balance Sheet HISTORICAL'!H39 -> 374060 | I10: ='Balance Sheet HISTORICAL'!I39 -> 398731 | J10: ='Balance Sheet HISTORICAL'!J39 -> 430735 | K10: ='Balance Sheet HISTORICAL'!K39 -> 456076 | ... M10: ='Balance Sheet HISTORICAL'!M39 -> 499931
D11: =D9-D10 -> 0 | E11: =E9-E10 -> 0 | F11: =F9-F10 -> 0 | G11: =G9-G10 -> 0 | H11: =H9-H10 -> 0 | I11: =I9-I10 -> 0 | J11: =J9-J10 -> 0 | K11: =K9-K10 -> 0 | ... M11: =M9-M10 -> 0
A12: Intangibles
B13: Beginning Balance (Previous Ending) | D13: =C16 -> 23671 | E13: =D16 -> 22961 | F13: =E16 -> 19191 | G13: =F16 -> 16244 | H13: =G16 -> 13513 | I13: =H16 -> 10652 | J13: =I16 -> 8633 | K13: =J16 -> 7244 | ... R13: =Q16 -> 610.83564
B14: NEW Intangibles | D14: =D16-D13+D15 -> 2329 | E14: =E16-E13+E15 -> -794 | F14: =F16-F13+F15 -> -68 | G14: =G16-G13+G15 -> 220 | H14: =H16-H13+H15 -> -155 | I14: =I16-I13+I15 -> 192 | J14: =J16-J13+J15 -> 60 | K14: =K16-K13+K15 -> -222 | ... M14: =M16-M13+M15 -> 2658 | N14: =Assumptions!T31 -> 0 | O14: =Assumptions!U31 -> 0 | P14: =Assumptions!V31 -> 0 | Q14: =Assumptions!W31 -> 0 | R14: =Assumptions!X31 -> 0
B15: Amortization | D15: ='Income Statement'!D13 -> 3039 | E15: ='Income Statement'!E13 -> 2976 | F15: ='Income Statement'!F13 -> 2879 | G15: ='Income Statement'!G13 -> 2951 | H15: ='Income Statement'!H13 -> 2706 | I15: ='Income Statement'!I13 -> 2211 | J15: ='Income Statement'!J13 -> 1449 | K15: ='Income Statement'!K13 -> 1434 | ... M15: ='Income Statement'!M13 -> 1106 | N15: =IF((Assumptions!T9*'Income Statement'!N6)>Calcs!N13,Calcs!N13,(Assumptions!T9*'Income Statement'!N6)) -> 1263.792 | O15: =IF((Assumptions!U9*'Income Statement'!O6)>Calcs!O13,Calcs!O13,(Assumptions!U9*'Income Statement'!O6)) -> 1352.2574 | P15: =IF((Assumptions!V9*'Income Statement'!P6)>Calcs!P13,Calcs!P13,(Assumptions!V9*'Income Statement'!P6)) -> 1446.9154 | Q15: =IF((Assumptions!W9*'Income Statement'!Q6)>Calcs!Q13,Calcs!Q13,(Assumptions!W9*'Income Statement'!Q6)) -> 1548.1995 | R15: =IF((Assumptions!X9*'Income Statement'!R6)>Calcs!R13,Calcs!R13,(Assumptions!X9*'Income Statement'!R6)) -> 610.83564
B16: Ending Balance (Actual from B/S) | C16: ='Balance Sheet HISTORICAL'!C15 -> 23671 | D16: ='Balance Sheet HISTORICAL'!D15 -> 22961 | E16: ='Balance Sheet HISTORICAL'!E15 -> 19191 | F16: ='Balance Sheet HISTORICAL'!F15 -> 16244 | G16: ='Balance Sheet HISTORICAL'!G15 -> 13513 | H16: ='Balance Sheet HISTORICAL'!H15 -> 10652 | I16: ='Balance Sheet HISTORICAL'!I15 -> 8633 | J16: ='Balance Sheet HISTORICAL'!J15 -> 7244 | ... M16: ='Balance Sheet HISTORICAL'!M15 -> 6222 | N16: =N13+N14-N15 -> 4958.208 | O16: =O13+O14-O15 -> 3605.9506 | P16: =P13+P14-P15 -> 2159.0352 | Q16: =Q13+Q14-Q15 -> 610.83564 | R16: =R13+R14-R15 -> 0
A18: PP&E (Property, Plant & Equipment)
B19: Beginning Balance (Previous Ending) | D19: =C22 -> 9702 | E19: =D22 -> 11376 | F19: =E22 -> 11545 | G19: =F22 -> 29439 | H19: =G22 -> 36357 | I19: =H22 -> 45076 | J19: =I22 -> 60759 | K19: =J22 -> 70145 | ... R19: =Q22 -> 79816.493
B20: Capital Expenditures (Actual from CFS) | D20: 5784 | E20: 4354 | F20: 20150 | G20: 12356 | H20: 13282 | I20: 19307 | J20: 15059 | K20: 8303 | L20: 6871 | M20: 4206 | N20: =Assumptions!T28*'Income Statement'!N6 -> 12637.92 | O20: =Assumptions!U28*'Income Statement'!O6 -> 13522.574 | P20: =Assumptions!V28*'Income Statement'!P6 -> 14469.154 | Q20: =Assumptions!W28*'Income Statement'!Q6 -> 15481.995 | R20: =Assumptions!X28*'Income Statement'!R6 -> 16565.735
B21: Depreciation (Calculated Below) | D21: =D26 -> 3425 | E21: =E26 -> 3489 | F21: =F26 -> 3890 | G21: =G26 -> 4849 | H21: =H26 -> 4887 | I21: =I26 -> 5490 | J21: =J26 -> 5570 | K21: =K26 -> 6860 | ... M21: =M26 -> 8350 | N21: =Assumptions!T29*'Income Statement'!N6 -> 8846.5439 | O21: =Assumptions!U29*'Income Statement'!O6 -> 9465.8019 | P21: =Assumptions!V29*'Income Statement'!P6 -> 10128.408 | Q21: =Assumptions!W29*'Income Statement'!Q6 -> 10837.397 | R21: =Assumptions!X29*'Income Statement'!R6 -> 11596.014
B22: Ending Balance (Actual from B/S) | C22: ='Balance Sheet HISTORICAL'!C13 -> 9702 | D22: ='Balance Sheet HISTORICAL'!D13 -> 11376 | E22: ='Balance Sheet HISTORICAL'!E13 -> 11545 | F22: ='Balance Sheet HISTORICAL'!F13 -> 29439 | G22: ='Balance Sheet HISTORICAL'!G13 -> 36357 | H22: ='Balance Sheet HISTORICAL'!H13 -> 45076 | I22: ='Balance Sheet HISTORICAL'!I13 -> 60759 | J22: ='Balance Sheet HISTORICAL'!J13 -> 70145 | ... M22: ='Balance Sheet HISTORICAL'!M13 -> 62983 | N22: =N19+N20-N21 -> 66774.376 | O22: =O19+O20-O21 -> 70831.148 | P22: =P19+P20-P21 -> 75171.895 | Q22: =Q19+Q20-Q21 -> 79816.493 | R22: =R19+R20-R21 -> 84786.214
B24: Depreciation & Amortization (from CFS) | C24: 5860 | D24: 6464 | E24: 6465 | F24: 6769 | G24: 7800 | H24: 7593 | I24: 7701 | J24: 7019 | K24: 8294 | L24: 8151 | M24: 9456
B25: Amortization of definite-lived intangible assets | C25: ='Income Statement'!C13 -> 2617 | D25: ='Income Statement'!D13 -> 3039 | E25: ='Income Statement'!E13 -> 2976 | F25: ='Income Statement'!F13 -> 2879 | G25: ='Income Statement'!G13 -> 2951 | H25: ='Income Statement'!H13 -> 2706 | I25: ='Income Statement'!I13 -> 2211 | J25: ='Income Statement'!J13 -> 1449 | ... M25: ='Income Statement'!M13 -> 1106
B26: Depreciation (D&A - A) | C26: =C24-C25 -> 3243 | D26: =D24-D25 -> 3425 | E26: =E24-E25 -> 3489 | F26: =F24-F25 -> 3890 | G26: =G24-G25 -> 4849 | H26: =H24-H25 -> 4887 | I26: =I24-I25 -> 5490 | J26: =J24-J25 -> 5570 | ... M26: =M24-M25 -> 8350
B28: Cost of products sold | C28: 184144 | D28: 177972 | E28: 166301 | F28: 166621 | G28: 183255 | H28: 191010 | I28: 185481 | J28: 224370 | K28: 264055 | L28: 263035 | M28: 275330
B29: Selling, general and administrative | C29: 108577 | D29: 108873 | E29: 117767 | F29: 114560 | G29: 121394 | H29: 123946 | I29: 121980 | J29: 145493 | K29: 138658 | L29: 154684 | M29: 183859
B30: Total Combined | C30: =SUM(C28:C29) -> 292721 | D30: =SUM(D28:D29) -> 286845 | E30: =SUM(E28:E29) -> 284068 | F30: =SUM(F28:F29) -> 281181 | G30: =SUM(G28:G29) -> 304649 | H30: =SUM(H28:H29) -> 314956 | I30: =SUM(I28:I29) -> 307461 | J30: =SUM(J28:J29) -> 369863 | ... M30: =SUM(M28:M29) -> 459189
B32: % COGS | C32: =C28/C$30 -> 0.62907683 | D32: =D28/D$30 -> 0.62044658 | E32: =E28/E$30 -> 0.58542673 | F32: =F28/F$30 -> 0.5925756 | G32: =G28/G$30 -> 0.60152832 | H32: =H28/H$30 -> 0.60646567 | I32: =I28/I$30 -> 0.60326676 | J32: =J28/J$30 -> 0.60663002 | ... M32: =M28/M$30 -> 0.5996006
B33: % SG&A | C33: =C29/C$30 -> 0.37092317 | D33: =D29/D$30 -> 0.37955342 | E33: =E29/E$30 -> 0.41457327 | F33: =F29/F$30 -> 0.4074244 | G33: =G29/G$30 -> 0.39847168 | H33: =H29/H$30 -> 0.39353433 | I33: =I29/I$30 -> 0.39673324 | J33: =J29/J$30 -> 0.39336998 | ... M33: =M29/M$30 -> 0.4003994
B35: Depreciation in COGS | C35: =C$26*C32 -> 2040.0962 | D35: =D$26*D32 -> 2125.0295 | E35: =E$26*E32 -> 2042.5539 | F35: =F$26*F32 -> 2305.1191 | G35: =G$26*G32 -> 2916.8108 | H35: =H$26*H32 -> 2963.7977 | I35: =I$26*I32 -> 3311.9345 | J35: =J$26*J32 -> 3378.9292 | ... M35: =M$26*M32 -> 5006.665
B36: Depreciation in SG&A | C36: =C$26*C33 -> 1202.9038 | D36: =D$26*D33 -> 1299.9705 | E36: =E$26*E33 -> 1446.4461 | F36: =F$26*F33 -> 1584.8809 | G36: =G$26*G33 -> 1932.1892 | H36: =H$26*H33 -> 1923.2023 | I36: =I$26*I33 -> 2178.0655 | J36: =J$26*J33 -> 2191.0708 | ... M36: =M$26*M33 -> 3343.335
B37: Total Depreciation | C37: =SUM(C35:C36) -> 3243 | D37: =SUM(D35:D36) -> 3425 | E37: =SUM(E35:E36) -> 3489 | F37: =SUM(F35:F36) -> 3890 | G37: =SUM(G35:G36) -> 4849 | H37: =SUM(H35:H36) -> 4887 | I37: =SUM(I35:I36) -> 5490 | J37: =SUM(J35:J36) -> 5570 | ... M37: =SUM(M35:M36) -> 8350
B39: Clean COGS | C39: =C28-C35 -> 182103.9 | D39: =D28-D35 -> 175846.97 | E39: =E28-E35 -> 164258.45 | F39: =F28-F35 -> 164315.88 | G39: =G28-G35 -> 180338.19 | H39: =H28-H35 -> 188046.2 | I39: =I28-I35 -> 182169.07 | J39: =J28-J35 -> 220991.07 | ... M39: =M28-M35 -> 270323.33
B40: Clean SG&A | C40: =C29-C36 -> 107374.1 | D40: =D29-D36 -> 107573.03 | E40: =E29-E36 -> 116320.55 | F40: =F29-F36 -> 112975.12 | G40: =G29-G36 -> 119461.81 | H40: =H29-H36 -> 122022.8 | I40: =I29-I36 -> 119801.93 | J40: =J29-J36 -> 143301.93 | ... M40: =M29-M36 -> 180515.67
A42: Operating Working Capital ((CA-Cash) - (CL - ST Debt))
B43: Trade and other accounts receivable, net | C43: ='Balance Sheet PROJECTED'!C8 -> 63618 | D43: ='Balance Sheet PROJECTED'!D8 -> 58750 | E43: ='Balance Sheet PROJECTED'!E8 -> 64680 | F43: ='Balance Sheet PROJECTED'!F8 -> 64259 | G43: ='Balance Sheet PROJECTED'!G8 -> 69025 | H43: ='Balance Sheet PROJECTED'!H8 -> 72864 | I43: ='Balance Sheet PROJECTED'!I8 -> 80672 | J43: ='Balance Sheet PROJECTED'!J8 -> 89558 | ... R43: ='Balance Sheet PROJECTED'!R8 -> 165657.35
B44: Inventories | C44: ='Balance Sheet PROJECTED'!C9 -> 34989 | D44: ='Balance Sheet PROJECTED'!D9 -> 32052 | E44: ='Balance Sheet PROJECTED'!E9 -> 31793 | F44: ='Balance Sheet PROJECTED'!F9 -> 35340 | G44: ='Balance Sheet PROJECTED'!G9 -> 36536 | H44: ='Balance Sheet PROJECTED'!H9 -> 40682 | I44: ='Balance Sheet PROJECTED'!I9 -> 41264 | J44: ='Balance Sheet PROJECTED'!J9 -> 55752 | ... R44: ='Balance Sheet PROJECTED'!R9 -> 96288.334
B45: Current deferred tax assets, net | C45: ='Balance Sheet PROJECTED'!C10 -> 5855 | D45: ='Balance Sheet PROJECTED'!D10 -> 5824 | E45: ='Balance Sheet PROJECTED'!E10 -> 0 | F45: ='Balance Sheet PROJECTED'!F10 -> 0 | G45: ='Balance Sheet PROJECTED'!G10 -> 0 | H45: ='Balance Sheet PROJECTED'!H10 -> 0 | I45: ='Balance Sheet PROJECTED'!I10 -> 0 | J45: ='Balance Sheet PROJECTED'!J10 -> 0 | ... R45: ='Balance Sheet PROJECTED'!R10 -> 0
B46: Other current assets | C46: ='Balance Sheet PROJECTED'!C11 -> 8339 | D46: ='Balance Sheet PROJECTED'!D11 -> 6127 | E46: ='Balance Sheet PROJECTED'!E11 -> 4475 | F46: ='Balance Sheet PROJECTED'!F11 -> 8007 | G46: ='Balance Sheet PROJECTED'!G11 -> 13337 | H46: ='Balance Sheet PROJECTED'!H11 -> 7216 | I46: ='Balance Sheet PROJECTED'!I11 -> 6756 | J46: ='Balance Sheet PROJECTED'!J11 -> 9948 | ... R46: ='Balance Sheet PROJECTED'!R11 -> 16565.735
B47: Total Operating Assets | C47: =SUM(C43:C46) -> 112801 | D47: =SUM(D43:D46) -> 102753 | E47: =SUM(E43:E46) -> 100948 | F47: =SUM(F43:F46) -> 107606 | G47: =SUM(G43:G46) -> 118898 | H47: =SUM(H43:H46) -> 120762 | I47: =SUM(I43:I46) -> 128692 | J47: =SUM(J43:J46) -> 155258 | ... R47: =SUM(R43:R46) -> 278511.42
B48: Accounts payable | C48: ='Balance Sheet PROJECTED'!C22 -> 18031 | D48: ='Balance Sheet PROJECTED'!D22 -> 17128 | E48: ='Balance Sheet PROJECTED'!E22 -> 18690 | F48: ='Balance Sheet PROJECTED'!F22 -> 20898 | G48: ='Balance Sheet PROJECTED'!G22 -> 19115 | H48: ='Balance Sheet PROJECTED'!H22 -> 18727 | I48: ='Balance Sheet PROJECTED'!I22 -> 21676 | J48: ='Balance Sheet PROJECTED'!J22 -> 33499 | ... R48: ='Balance Sheet PROJECTED'!R22 -> 47759.014
B49: Accrued liabilities | C49: ='Balance Sheet PROJECTED'!C23 -> 18382 | D49: ='Balance Sheet PROJECTED'!D23 -> 15200 | E49: ='Balance Sheet PROJECTED'!E23 -> 15757 | F49: ='Balance Sheet PROJECTED'!F23 -> 18997 | G49: ='Balance Sheet PROJECTED'!G23 -> 26240 | H49: ='Balance Sheet PROJECTED'!H23 -> 18513 | I49: ='Balance Sheet PROJECTED'!I23 -> 21660 | J49: ='Balance Sheet PROJECTED'!J23 -> 25658 | ... R49: ='Balance Sheet PROJECTED'!R23 -> 43899.197
B50: Accrued payroll and related expenses | C50: ='Balance Sheet PROJECTED'!C24 -> 15969 | D50: ='Balance Sheet PROJECTED'!D24 -> 13357 | E50: ='Balance Sheet PROJECTED'!E24 -> 20866 | F50: ='Balance Sheet PROJECTED'!F24 -> 14222 | G50: ='Balance Sheet PROJECTED'!G24 -> 14823 | H50: ='Balance Sheet PROJECTED'!H24 -> 15301 | I50: ='Balance Sheet PROJECTED'!I24 -> 14767 | J50: ='Balance Sheet PROJECTED'!J24 -> 25662 | ... R50: ='Balance Sheet PROJECTED'!R24 -> 33131.47
B51: Income taxes payable | C51: ='Balance Sheet PROJECTED'!C28 -> 1529 | D51: ='Balance Sheet PROJECTED'!D28 -> 2287 | E51: ='Balance Sheet PROJECTED'!E28 -> 3381 | F51: ='Balance Sheet PROJECTED'!F28 -> 1306 | G51: ='Balance Sheet PROJECTED'!G28 -> 2125 | H51: ='Balance Sheet PROJECTED'!H28 -> 844 | I51: ='Balance Sheet PROJECTED'!I28 -> 1213 | J51: ='Balance Sheet PROJECTED'!J28 -> 317 | ... R51: ='Balance Sheet PROJECTED'!R28 -> 828.28674
B52: Total Operating Liabilities | C52: =SUM(C48:C51) -> 53911 | D52: =SUM(D48:D51) -> 47972 | E52: =SUM(E48:E51) -> 58694 | F52: =SUM(F48:F51) -> 55423 | G52: =SUM(G48:G51) -> 62303 | H52: =SUM(H48:H51) -> 53385 | I52: =SUM(I48:I51) -> 59316 | J52: =SUM(J48:J51) -> 85136 | ... R52: =SUM(R48:R51) -> 125617.97
B54: Operating Assets (Cash Flow) | D54: =-(D47-C47) -> 10048 | E54: =-(E47-D47) -> 1805 | F54: =-(F47-E47) -> -6658 | G54: =-(G47-F47) -> -11292 | H54: =-(H47-G47) -> -1864 | I54: =-(I47-H47) -> -7930 | J54: =-(J47-I47) -> -26566 | K54: =-(K47-J47) -> -56539 | ... R54: =-(R47-Q47) -> -18220.373
B55: Operating Liabilities (Cash Flow) | D55: =D52-C52 -> -5939 | E55: =E52-D52 -> 10722 | F55: =F52-E52 -> -3271 | G55: =G52-F52 -> 6880 | H55: =H52-G52 -> -8918 | I55: =I52-H52 -> 5931 | J55: =J52-I52 -> 25820 | K55: =K52-J52 -> -13489 | ... R55: =R52-Q52 -> 8217.9979
B56: Operating Working Capital (Cash Flow) | D56: =SUM(D54:D55) -> 4109 | E56: =SUM(E54:E55) -> 12527 | F56: =SUM(F54:F55) -> -9929 | G56: =SUM(G54:G55) -> -4412 | H56: =SUM(H54:H55) -> -10782 | I56: =SUM(I54:I55) -> -1999 | J56: =SUM(J54:J55) -> -746 | K56: =SUM(K54:K55) -> -70028 | ... R56: =SUM(R54:R55) -> -10002.375

Sheet Income Statement
A1: WD-40 Income Statement
B2: (USD in thousands, except per share data)
K3: Historical | N3: Projected
C4: 41882 | D4: 42247 | E4: 42613 | F4: 42978 | G4: 43343 | H4: 43708 | I4: 44074 | J4: 44439 | K4: 44804 | L4: 45169 | M4: 45535 | N4: 45900 | O4: 46265 | P4: 46630 | Q4: 46996 | R4: 47361
B6: Net sales | C6: 382997 | D6: 378150 | E6: 380670 | F6: 380506 | G6: 408518 | H6: 423350 | I6: 408498 | J6: 488109 | K6: 518820 | L6: 537255 | M6: 590557 | N6: =(1+Assumptions!T5)*'Income Statement'!M6 -> 631895.99 | O6: =(1+Assumptions!U5)*'Income Statement'!N6 -> 676128.71 | P6: =(1+Assumptions!V5)*'Income Statement'!O6 -> 723457.72 | Q6: =(1+Assumptions!W5)*'Income Statement'!P6 -> 774099.76 | R6: =(1+Assumptions!X5)*'Income Statement'!Q6 -> 828286.74
B7: Clean COGS | C7: =Calcs!C39 -> 182103.9 | D7: =Calcs!D39 -> 175846.97 | E7: =Calcs!E39 -> 164258.45 | F7: =Calcs!F39 -> 164315.88 | G7: =Calcs!G39 -> 180338.19 | H7: =Calcs!H39 -> 188046.2 | I7: =Calcs!I39 -> 182169.07 | J7: =Calcs!J39 -> 220991.07 | ... M7: =Calcs!M39 -> 270323.33 | N7: =Assumptions!T6*'Income Statement'!N6 -> 293831.64 | O7: =Assumptions!U6*'Income Statement'!O6 -> 314399.85 | P7: =Assumptions!V6*'Income Statement'!P6 -> 336407.84 | Q7: =Assumptions!W6*'Income Statement'!Q6 -> 359956.39 | R7: =Assumptions!X6*'Income Statement'!R6 -> 385153.34
A8: * | B8: Gross profit | C8: =C6-C7 -> 200893.1 | D8: =D6-D7 -> 202303.03 | E8: =E6-E7 -> 216411.55 | F8: =F6-F7 -> 216190.12 | G8: =G6-G7 -> 228179.81 | H8: =H6-H7 -> 235303.8 | I8: =I6-I7 -> 226328.93 | J8: =J6-J7 -> 267117.93 | ... R8: =R6-R7 -> 443133.41
B9: Clean SG&A | C9: =Calcs!C40 -> 107374.1 | D9: =Calcs!D40 -> 107573.03 | E9: =Calcs!E40 -> 116320.55 | F9: =Calcs!F40 -> 112975.12 | G9: =Calcs!G40 -> 119461.81 | H9: =Calcs!H40 -> 122022.8 | I9: =Calcs!I40 -> 119801.93 | J9: =Calcs!J40 -> 143301.93 | ... M9: =Calcs!M40 -> 180515.67 | N9: =Assumptions!T7*'Income Statement'!N6 -> 180090.36 | O9: =Assumptions!U7*'Income Statement'!O6 -> 192696.68 | P9: =Assumptions!V7*'Income Statement'!P6 -> 206185.45 | Q9: =Assumptions!W7*'Income Statement'!Q6 -> 220618.43 | R9: =Assumptions!X7*'Income Statement'!R6 -> 236061.72
B10: Advertising and sales promotion | C10: 23922 | D10: 22876 | E10: 22278 | F10: 20537 | G10: 22314 | H10: 23306 | I10: 21606 | J10: 27956 | K10: 27343 | L10: 28807 | M10: 33911 | N10: =Assumptions!T8*'Income Statement'!N6 -> 37913.759 | O10: =Assumptions!U8*'Income Statement'!O6 -> 40567.723 | P10: =Assumptions!V8*'Income Statement'!P6 -> 43407.463 | Q10: =Assumptions!W8*'Income Statement'!Q6 -> 46445.986 | R10: =Assumptions!X8*'Income Statement'!R6 -> 49697.205
B11: EBITDA | C11: =C8-SUM(C9:C10) -> 69597 | D11: =D8-SUM(D9:D10) -> 71854 | E11: =E8-SUM(E9:E10) -> 77813 | F11: =F8-SUM(F9:F10) -> 82678 | G11: =G8-SUM(G9:G10) -> 86404 | H11: =H8-SUM(H9:H10) -> 89975 | I11: =I8-SUM(I9:I10) -> 84921 | J11: =J8-SUM(J9:J10) -> 95860 | ... R11: =R8-SUM(R9:R10) -> 157374.48
B12: Depreciation | C12: =Calcs!C26 -> 3243 | D12: =Calcs!D26 -> 3425 | E12: =Calcs!E26 -> 3489 | F12: =Calcs!F26 -> 3890 | G12: =Calcs!G26 -> 4849 | H12: =Calcs!H26 -> 4887 | I12: =Calcs!I26 -> 5490 | J12: =Calcs!J26 -> 5570 | ... M12: =Calcs!M26 -> 8350 | N12: =Calcs!N21 -> 8846.5439 | O12: =Calcs!O21 -> 9465.8019 | P12: =Calcs!P21 -> 10128.408 | Q12: =Calcs!Q21 -> 10837.397 | R12: =Calcs!R21 -> 11596.014
B13: Amortization of definite-lived intangible assets | C13: 2617 | D13: 3039 | E13: 2976 | F13: 2879 | G13: 2951 | H13: 2706 | I13: 2211 | J13: 1449 | K13: 1434 | L13: 1005 | M13: 1106 | N13: =Calcs!N15 -> 1263.792 | O13: =Calcs!O15 -> 1352.2574 | P13: =Calcs!P15 -> 1446.9154 | Q13: =Calcs!Q15 -> 1548.1995 | R13: =Calcs!R15 -> 610.83564
A14: * | B14: Income from operations (EBIT) | C14: =C11-SUM(C12:C13) -> 63737 | D14: =D11-SUM(D12:D13) -> 65390 | E14: =E11-SUM(E12:E13) -> 71348 | F14: =F11-SUM(F12:F13) -> 75909 | G14: =G11-SUM(G12:G13) -> 78604 | H14: =H11-SUM(H12:H13) -> 82382 | I14: =I11-SUM(I12:I13) -> 77220 | J14: =J11-SUM(J12:J13) -> 88841 | ... R14: =R11-SUM(R12:R13) -> 145167.63
B15: Interest income | C15: 596 | D15: 584 | E15: 683 | F15: 508 | G15: 454 | H15: 155 | I15: 93 | J15: 81 | K15: 102 | L15: 231 | M15: 474 | N15: =Debt!E69 -> 2656.5305 | O15: =Debt!F69 -> 3635.7325 | P15: =Debt!G69 -> 4777.8769 | Q15: =Debt!H69 -> 5425.317 | R15: =Debt!I69 -> 6185.6468
B16: Interest expense | C16: -1002 | D16: -1205 | E16: -1703 | F16: -2582 | G16: -4219 | H16: -2541 | I16: -2439 | J16: -2395 | K16: -2742 | L16: -5614 | M16: -4287 | N16: =-Debt!E59 -> -3440.9136 | O16: =-Debt!F59 -> -3057.4928 | P16: =-Debt!G59 -> -2674.072 | Q16: =-Debt!H59 -> -1965.6512 | R16: =-Debt!I59 -> -1257.2304
B17: Other (expense) income, net | C17: -372 | D17: -1659 | E17: 2461 | F17: 787 | G17: 339 | H17: 774 | I17: 641 | J17: -28 | K17: -582 | L17: 822 | M17: -1030 | N17: =Assumptions!T10*'Income Statement'!N6 -> 0 | O17: =Assumptions!U10*'Income Statement'!O6 -> 0 | P17: =Assumptions!V10*'Income Statement'!P6 -> 0 | Q17: =Assumptions!W10*'Income Statement'!Q6 -> 0 | R17: =Assumptions!X10*'Income Statement'!R6 -> 0
A18: * | B18: Income before income taxes (EBT) | C18: =SUM(C14:C17) -> 62959 | D18: =SUM(D14:D17) -> 63110 | E18: =SUM(E14:E17) -> 72789 | F18: =SUM(F14:F17) -> 74622 | G18: =SUM(G14:G17) -> 75178 | H18: =SUM(H14:H17) -> 80770 | I18: =SUM(I14:I17) -> 75515 | J18: =SUM(J14:J17) -> 86499 | ... R18: =SUM(R14:R17) -> 150096.05
B19: Provision for income taxes | C19: 19213 | D19: 18303 | E19: 20161 | F19: 21692 | G19: 9963 | H19: 24862 | I19: 14805 | J19: 16270 | K19: 16779 | L19: 19170 | M19: 21864 | N19: =Assumptions!T11*'Income Statement'!N18 -> 25108.069 | O19: =Assumptions!U11*'Income Statement'!O18 -> 27191.666 | P19: =Assumptions!V11*'Income Statement'!P18 -> 29436.653 | Q19: =Assumptions!W11*'Income Statement'!Q18 -> 31775.196 | R19: =Assumptions!X11*'Income Statement'!R18 -> 34522.091
A20: * | B20: Net income | C20: =C18-C19 -> 43746 | D20: =D18-D19 -> 44807 | E20: =E18-E19 -> 52628 | F20: =F18-F19 -> 52930 | G20: =G18-G19 -> 65215 | H20: =H18-H19 -> 55908 | I20: =I18-I19 -> 60710 | J20: =J18-J19 -> 70229 | ... R20: =R18-R19 -> 115573.96
A22: * | B22: Earnings per common share:
B23: Basic | C23: =C$20/C27 -> 2.9024682 | D23: =D$20/D27 -> 3.0727609 | E23: =E$20/E27 -> 3.6720625 | F23: =F$20/F27 -> 3.7568316 | G23: =G$20/G27 -> 4.6819585 | H23: =H$20/H27 -> 4.0515979 | I23: =I$20/I27 -> 4.4342999 | J23: =J$20/J27 -> 5.1269528 | ... R23: =R$20/R27 -> 8.5269261
B24: Diluted | C24: =C$20/C28 -> 2.887906 | D24: =D$20/D28 -> 3.0587071 | E24: =E$20/E28 -> 3.6600598 | F24: =F$20/F28 -> 3.7477873 | G24: =G$20/G28 -> 4.6708924 | H24: =H$20/H28 -> 4.0425163 | I24: =I$20/I28 -> 4.4252497 | J24: =J$20/J28 -> 5.1138863 | ... R24: =R$20/R28 -> 8.5106006
A26: * | B26: Shares used in per share calculations:
B27: Basic | C27: 15072 | D27: 14582 | E27: 14332 | F27: 14089 | G27: 13929 | H27: 13799 | I27: 13691 | J27: 13698 | K27: 13668 | L27: 13578 | M27: 13554 | N27: =M27 -> 13554 | O27: =N27 -> 13554 | P27: =O27 -> 13554 | Q27: =P27 -> 13554 | R27: =Q27 -> 13554
B28: Diluted | C28: 15148 | D28: 14649 | E28: 14379 | F28: 14123 | G28: 13962 | H28: 13830 | I28: 13719 | J28: 13733 | K28: 13696 | L28: 13604 | M28: 13580 | N28: =M28 -> 13580 | O28: =N28 -> 13580 | P28: =O28 -> 13580 | Q28: =P28 -> 13580 | R28: =Q28 -> 13580

Sheet Balance Sheet PROJECTED
A1: WD-40 Balance Sheet
B2: (USD in thousands, except per share data)
K3: Historical | N3: Projected
C4: 41882 | D4: 42247 | E4: 42613 | F4: 42978 | G4: 43343 | H4: 43708 | I4: 44074 | J4: 44439 | K4: 44804 | L4: 45169 | M4: 45535 | N4: 45900 | O4: 46265 | P4: 46630 | Q4: 46996 | R4: 47361
B5: Assets:
B6: Cash and ST Investments (REQUIRED) | C6: =57803+45050 -> 102853 | D6: =53896+48603 -> 102499 | E6: =50891+57633 -> 108524 | F6: =37082+80166 -> 117248 | G6: =48866+219 -> 49085 | H6: 27233 | I6: 56462 | J6: 85961 | K6: 37843 | L6: 48143 | M6: 46699 | N6: =Assumptions!T22*'Income Statement'!N6 -> 51183.575 | O6: =Assumptions!U22*'Income Statement'!O6 -> 54766.425 | P6: =Assumptions!V22*'Income Statement'!P6 -> 58600.075 | Q6: =Assumptions!W22*'Income Statement'!Q6 -> 62702.081 | R6: =Assumptions!X22*'Income Statement'!R6 -> 67091.226
B7: EXCESS CASH | N7: =IF('Cash Flow Statement'!F41>0,'Cash Flow Statement'!F41,0) -> 13971.342 | O7: =IF('Cash Flow Statement'!G41>0,'Cash Flow Statement'!G41,0) -> 33162.133 | P7: =IF('Cash Flow Statement'!H41>0,'Cash Flow Statement'!H41,0) -> 54645.131 | Q7: =IF('Cash Flow Statement'!I41>0,'Cash Flow Statement'!I41,0) -> 52487.115 | R7: =IF('Cash Flow Statement'!J41>0,'Cash Flow Statement'!J41,0) -> 78167.863
B8: Trade and other accounts receivable, net | C8: 63618 | D8: 58750 | E8: 64680 | F8: 64259 | G8: 69025 | H8: 72864 | I8: 80672 | J8: 89558 | K8: 89930 | L8: 98039 | M8: 117493 | N8: =Assumptions!T23*'Income Statement'!N6 -> 126379.2 | O8: =Assumptions!U23*'Income Statement'!O6 -> 135225.74 | P8: =Assumptions!V23*'Income Statement'!P6 -> 144691.54 | Q8: =Assumptions!W23*'Income Statement'!Q6 -> 154819.95 | R8: =Assumptions!X23*'Income Statement'!R6 -> 165657.35
B9: Inventories | C9: 34989 | D9: 32052 | E9: 31793 | F9: 35340 | G9: 36536 | H9: 40682 | I9: 41264 | J9: 55752 | K9: 104101 | L9: 86522 | M9: 79088 | N9: =Assumptions!T24*'Income Statement'!N7 -> 73457.909 | O9: =Assumptions!U24*'Income Statement'!O7 -> 78599.962 | P9: =Assumptions!V24*'Income Statement'!P7 -> 84101.96 | Q9: =Assumptions!W24*'Income Statement'!Q7 -> 89989.097 | R9: =Assumptions!X24*'Income Statement'!R7 -> 96288.334
B10: Current deferred tax assets, net | C10: 5855 | D10: 5824 | E10: 0 | F10: 0 | G10: 0 | H10: 0 | I10: 0 | J10: 0 | K10: 0 | L10: 0 | M10: 0 | N10: =M10 -> 0 | O10: =N10 -> 0 | P10: =O10 -> 0 | Q10: =P10 -> 0 | R10: =Q10 -> 0
B11: Other current assets | C11: 8339 | D11: 6127 | E11: 4475 | F11: 8007 | G11: 13337 | H11: 7216 | I11: 6756 | J11: 9948 | K11: 17766 | L11: 15821 | M11: 12161 | N11: =Assumptions!T25*'Income Statement'!N6 -> 12637.92 | O11: =Assumptions!U25*'Income Statement'!O6 -> 13522.574 | P11: =Assumptions!V25*'Income Statement'!P6 -> 14469.154 | Q11: =Assumptions!W25*'Income Statement'!Q6 -> 15481.995 | R11: =Assumptions!X25*'Income Statement'!R6 -> 16565.735
A12: * | B12: Total current assets | C12: =SUM(C6:C11) -> 215654 | D12: =SUM(D6:D11) -> 205252 | E12: =SUM(E6:E11) -> 209472 | F12: =SUM(F6:F11) -> 224854 | G12: =SUM(G6:G11) -> 167983 | H12: =SUM(H6:H11) -> 147995 | I12: =SUM(I6:I11) -> 185154 | J12: =SUM(J6:J11) -> 241219 | ... R12: =SUM(R6:R11) -> 423770.51
B13: Property and equipment, net | C13: 9702 | D13: 11376 | E13: 11545 | F13: 29439 | G13: 36357 | H13: 45076 | I13: 60759 | J13: 70145 | K13: 65977 | L13: 66791 | M13: 62983 | N13: =Calcs!N22 -> 66774.376 | O13: =Calcs!O22 -> 70831.148 | P13: =Calcs!P22 -> 75171.895 | Q13: =Calcs!Q22 -> 79816.493 | R13: =Calcs!R22 -> 84786.214
B14: Goodwill | C14: 95499 | D14: 96409 | E14: 95649 | F14: 95597 | G14: 95621 | H14: 95347 | I14: 95731 | J14: 95869 | K14: 95180 | L14: 95505 | M14: 96985 | N14: =Assumptions!T30 -> 96985 | O14: =Assumptions!U30 -> 96985 | P14: =Assumptions!V30 -> 96985 | Q14: =Assumptions!W30 -> 96985 | R14: =Assumptions!X30 -> 96985
B15: Other intangible assets, net | C15: 23671 | D15: 22961 | E15: 19191 | F15: 16244 | G15: 13513 | H15: 10652 | I15: 8633 | J15: 7244 | K15: 5588 | L15: 4670 | M15: 6222 | N15: =Calcs!N16 -> 4958.208 | O15: =Calcs!O16 -> 3605.9506 | P15: =Calcs!P16 -> 2159.0352 | Q15: =Calcs!Q16 -> 610.83564 | R15: =Calcs!R16 -> 0
B16: Right-of-use assets | C16: 0 | D16: 0 | E16: 0 | F16: 0 | G16: 0 | H16: 0 | I16: 8168 | J16: 8824 | K16: 7559 | L16: 7820 | M16: 11611 | N16: =Assumptions!T32 -> 11611 | O16: =Assumptions!U32 -> 11611 | P16: =Assumptions!V32 -> 11611 | Q16: =Assumptions!W32 -> 11611 | R16: =Assumptions!X32 -> 11611
B17: Deferred tax assets, net | C17: 0 | D17: 0 | E17: 621 | F17: 495 | G17: 511 | H17: 403 | I17: 464 | J17: 858 | K17: 679 | L17: 1201 | M17: 993 | N17: =Assumptions!T33 -> 993 | O17: =Assumptions!U33 -> 993 | P17: =Assumptions!V33 -> 993 | Q17: =Assumptions!W33 -> 993 | R17: =Assumptions!X33 -> 993
B18: Other assets | C18: 3154 | D18: 3259 | E18: 3190 | F18: 3088 | G18: 3074 | H18: 3189 | I18: 3728 | J18: 6044 | K18: 9672 | L18: 13454 | M18: 14804 | N18: =Assumptions!T34*'Income Statement'!N6 -> 15797.4 | O18: =Assumptions!U34*'Income Statement'!O6 -> 16903.218 | P18: =Assumptions!V34*'Income Statement'!P6 -> 18086.443 | Q18: =Assumptions!W34*'Income Statement'!Q6 -> 19352.494 | R18: =Assumptions!X34*'Income Statement'!R6 -> 20707.169
A19: * | B19: Total assets | C19: =SUM(C12:C18) -> 347680 | D19: =SUM(D12:D18) -> 339257 | E19: =SUM(E12:E18) -> 339668 | F19: =SUM(F12:F18) -> 369717 | G19: =SUM(G12:G18) -> 317059 | H19: =SUM(H12:H18) -> 302662 | I19: =SUM(I12:I18) -> 362637 | J19: =SUM(J12:J18) -> 430203 | ... R19: =SUM(R12:R18) -> 638852.89
B21: Liabilities and Shareholders' Equity:
B22: Accounts payable | C22: 18031 | D22: 17128 | E22: 18690 | F22: 20898 | G22: 19115 | H22: 18727 | I22: 21676 | J22: 33499 | K22: 32852 | L22: 30826 | M22: 35960 | N22: =Assumptions!T37*'Income Statement'!N7 -> 36435.123 | O22: =Assumptions!U37*'Income Statement'!O7 -> 38985.581 | P22: =Assumptions!V37*'Income Statement'!P7 -> 41714.572 | Q22: =Assumptions!W37*'Income Statement'!Q7 -> 44634.592 | R22: =Assumptions!X37*'Income Statement'!R7 -> 47759.014
B23: Accrued liabilities | C23: 18382 | D23: 15200 | E23: 15757 | F23: 18997 | G23: 26240 | H23: 18513 | I23: 21660 | J23: 25658 | K23: 27161 | L23: 30000 | M23: 31272 | N23: =Assumptions!T38*'Income Statement'!N6 -> 33490.487 | O23: =Assumptions!U38*'Income Statement'!O6 -> 35834.822 | P23: =Assumptions!V38*'Income Statement'!P6 -> 38343.259 | Q23: =Assumptions!W38*'Income Statement'!Q6 -> 41027.287 | R23: =Assumptions!X38*'Income Statement'!R6 -> 43899.197
B24: Accrued payroll and related expenses | C24: 15969 | D24: 13357 | E24: 20866 | F24: 14222 | G24: 14823 | H24: 15301 | I24: 14767 | J24: 25662 | K24: 11583 | L24: 16722 | M24: 26055 | N24: =Assumptions!T39*'Income Statement'!N6 -> 25275.84 | O24: =Assumptions!U39*'Income Statement'!O6 -> 27045.148 | P24: =Assumptions!V39*'Income Statement'!P6 -> 28938.309 | Q24: =Assumptions!W39*'Income Statement'!Q6 -> 30963.99 | R24: =Assumptions!X39*'Income Statement'!R6 -> 33131.47
B25: Revolving credit facility, current portion | C25: 98000 | D25: 0 | E25: 0 | F25: 20000 | G25: 22800 | H25: 20405 | I25: 0 | J25: 0 | K25: 0 | L25: 0 | M25: 0 | N25: =M25 -> 0 | O25: =N25 -> 0 | P25: =O25 -> 0 | Q25: =P25 -> 0 | R25: =Q25 -> 0
B26: Short-term borrowings | C26: 0 | D26: 0 | E26: 0 | F26: 0 | G26: 800 | H26: 800 | I26: 800 | J26: 800 | K26: 0 | L26: 0 | M26: 0 | N26: =M26 -> 0 | O26: =N26 -> 0 | P26: =O26 -> 0 | Q26: =P26 -> 0 | R26: =Q26 -> 0
B27: NEW REVOLVER | N27: =-IF('Cash Flow Statement'!F41<0,'Cash Flow Statement'!F41,0) -> 0 | O27: =-IF('Cash Flow Statement'!G41<0,'Cash Flow Statement'!G41,0) -> 0 | P27: =-IF('Cash Flow Statement'!H41<0,'Cash Flow Statement'!H41,0) -> 0 | Q27: =-IF('Cash Flow Statement'!I41<0,'Cash Flow Statement'!I41,0) -> 0 | R27: =-IF('Cash Flow Statement'!J41<0,'Cash Flow Statement'!J41,0) -> 0
B28: Income taxes payable | C28: 1529 | D28: 2287 | E28: 3381 | F28: 1306 | G28: 2125 | H28: 844 | I28: 1213 | J28: 317 | K28: 51 | L28: 494 | M28: 1554 | N28: =Assumptions!T40*'Income Statement'!N6 -> 631.89599 | O28: =Assumptions!U40*'Income Statement'!O6 -> 676.12871 | P28: =Assumptions!V40*'Income Statement'!P6 -> 723.45772 | Q28: =Assumptions!W40*'Income Statement'!Q6 -> 774.09976 | R28: =Assumptions!X40*'Income Statement'!R6 -> 828.28674
A29: * | B29: Total current liabilities | C29: =SUM(C22:C28) -> 151911 | D29: =SUM(D22:D28) -> 47972 | E29: =SUM(E22:E28) -> 58694 | F29: =SUM(F22:F28) -> 75423 | G29: =SUM(G22:G28) -> 85903 | H29: =SUM(H22:H28) -> 74590 | I29: =SUM(I22:I28) -> 60116 | J29: =SUM(J22:J28) -> 85936 | ... R29: =SUM(R22:R28) -> 125617.97
B30: Revolving credit facility | C30: 0 | D30: 108000 | E30: 122000 | F30: 134000 | G30: 44000 | H30: 42221 | I30: 95898 | J30: 46540 | K30: =77912 -> 77912 | L30: 52943 | M30: 27836 | N30: =Debt!E17 -> 22268.8 | O30: =Debt!F17 -> 16701.6 | P30: =Debt!G17 -> 11134.4 | Q30: =Debt!H17 -> 5567.2 | R30: =Debt!I17 -> 0
B31: Series A Notes - 3.39% fixed rate | C31: 0 | D31: 0 | E31: 0 | F31: 0 | G31: 18800 | H31: 18000 | I31: 17200 | J31: =(17200-800)+26000+26000 -> 68400 | K31: 16400 | L31: 15600 | M31: 14800 | N31: =Debt!E26 -> 14000 | O31: =Debt!F26 -> 13200 | P31: =Debt!G26 -> 12400 | Q31: =Debt!H26 -> 11600 | R31: =Debt!I26 -> 10800
B32: Series B Notes - 2.50% fixed rate | K32: 26000 | L32: 26000 | M32: 26000 | N32: =Debt!E35 -> 26000 | O32: =Debt!F35 -> 26000 | P32: =Debt!G35 -> 26000 | Q32: =Debt!H35 -> 0 | R32: =Debt!I35 -> 0
B33: Series C Notes - 2.69% fixed rate | K33: 26000 | L33: 26000 | M33: 26000 | N33: =Debt!E44 -> 26000 | O33: =Debt!F44 -> 26000 | P33: =Debt!G44 -> 26000 | Q33: =Debt!H44 -> 26000 | R33: =Debt!I44 -> 26000
B34: Deferred tax liabilities, net | C34: 24253 | D34: 23145 | E34: 16365 | F34: 18949 | G34: 11050 | H34: 11688 | I34: 11291 | J34: 10401 | K34: 10528 | L34: 10305 | M34: 9066 | N34: =Assumptions!T43 -> 9066 | O34: =Assumptions!U43 -> 9066 | P34: =Assumptions!V43 -> 9066 | Q34: =Assumptions!W43 -> 9066 | R34: =Assumptions!X43 -> 9066
B35: Long-term operating lease liabilities | C35: 0 | D35: 0 | E35: 0 | F35: 0 | G35: 0 | H35: 0 | I35: 6520 | J35: 7062 | K35: 5999 | L35: 5832 | M35: 5904 | N35: =Assumptions!T44 -> 5904 | O35: =Assumptions!U44 -> 5904 | P35: =Assumptions!V44 -> 5904 | Q35: =Assumptions!W44 -> 5904 | R35: =Assumptions!X44 -> 5904
B36: Other long-term liabilities | C36: 2101 | D36: 2282 | E36: 2214 | F36: 1958 | G36: 1817 | H36: 10688 | I36: 11299 | J36: 11482 | K36: 11185 | L36: 13066 | M36: 14066 | N36: =Assumptions!T45*'Income Statement'!N6 -> 15165.504 | O36: =Assumptions!U45*'Income Statement'!O6 -> 16227.089 | P36: =Assumptions!V45*'Income Statement'!P6 -> 17362.985 | Q36: =Assumptions!W45*'Income Statement'!Q6 -> 18578.394 | R36: =Assumptions!X45*'Income Statement'!R6 -> 19878.882
A37: * | B37: Total liabilities | C37: =SUM(C29:C36) -> 178265 | D37: =SUM(D29:D36) -> 181399 | E37: =SUM(E29:E36) -> 199273 | F37: =SUM(F29:F36) -> 230330 | G37: =SUM(G29:G36) -> 161570 | H37: =SUM(H29:H36) -> 157187 | I37: =SUM(I29:I36) -> 202324 | J37: =SUM(J29:J36) -> 229821 | ... R37: =SUM(R29:R36) -> 197266.85
B39: Shareholders' equity:
B40: Common stock | C40: 19 | D40: 20 | E40: 20 | F40: 20 | G40: 20 | H40: 20 | I40: 20 | J40: 20 | K40: 20 | L40: 20 | M40: 20 | N40: =Assumptions!T48 -> 20 | O40: =Assumptions!U48 -> 20 | P40: =Assumptions!V48 -> 20 | Q40: =Assumptions!W48 -> 20 | R40: =Assumptions!X48 -> 20
B41: Additional paid-in capital | C41: 136212 | D41: 141651 | E41: 145936 | F41: 150692 | G41: 153469 | H41: 155132 | I41: 157850 | J41: 163737 | K41: 165973 | L41: 171546 | M41: 175642 | N41: =Assumptions!T49 -> 175642 | O41: =Assumptions!U49 -> 175642 | P41: =Assumptions!V49 -> 175642 | Q41: =Assumptions!W49 -> 175642 | R41: =Assumptions!X49 -> 175642
B42: Retained earnings | C42: 237596 | D42: 260683 | E42: 289642 | F42: 315764 | G42: 351266 | H42: 374060 | I42: 398731 | J42: 430735 | K42: 456076 | L42: 477488 | M42: 499931 | N42: =Calcs!N9 -> 536916.28 | O42: =Calcs!O9 -> 576970.78 | P42: =Calcs!P9 -> 620332.25 | Q42: =Calcs!Q9 -> 667138.5 | R42: =Calcs!R9 -> 717991.04
B43: Accumulated other comprehensive income (loss) | C43: 1103 | D43: -8722 | E43: -27298 | F43: -28075 | G43: -27636 | H43: -32482 | I43: -28208 | J43: -26030 | K43: -36209 | L43: -31206 | M43: -29268 | N43: =Assumptions!T50 -> -29268 | O43: =Assumptions!U50 -> -29268 | P43: =Assumptions!V50 -> -29268 | Q43: =Assumptions!W50 -> -29268 | R43: =Assumptions!X50 -> -29268
B44: Common stock held in treasury, at cost | C44: -205515 | D44: -235774 | E44: -267905 | F44: -299014 | G44: -321630 | H44: -351255 | I44: -368080 | J44: -368080 | K44: -397236 | L44: -407670 | M44: -415799 | N44: =Assumptions!T51+'Balance Sheet PROJECTED'!M44 -> -422799 | O44: =Assumptions!U51+'Balance Sheet PROJECTED'!N44 -> -422799 | P44: =Assumptions!V51+'Balance Sheet PROJECTED'!O44 -> -422799 | Q44: =Assumptions!W51+'Balance Sheet PROJECTED'!P44 -> -422799 | R44: =Assumptions!X51+'Balance Sheet PROJECTED'!Q44 -> -422799
A45: * | B45: Total stockholders’ equity | C45: =SUM(C40:C44) -> 169415 | D45: =SUM(D40:D44) -> 157858 | E45: =SUM(E40:E44) -> 140395 | F45: =SUM(F40:F44) -> 139387 | G45: =SUM(G40:G44) -> 155489 | H45: =SUM(H40:H44) -> 145475 | I45: =SUM(I40:I44) -> 160313 | J45: =SUM(J40:J44) -> 200382 | ... R45: =SUM(R40:R44) -> 441586.04
A47: * | B47: Total liabilities and stockholders’ equity | C47: =C37+C45 -> 347680 | D47: =D37+D45 -> 339257 | E47: =E37+E45 -> 339668 | F47: =F37+F45 -> 369717 | G47: =G37+G45 -> 317059 | H47: =H37+H45 -> 302662 | I47: =I37+I45 -> 362637 | J47: =J37+J45 -> 430203 | ... R47: =R37+R45 -> 638852.89
B48: Check | C48: =C19-C47 -> 0 | D48: =D19-D47 -> 0 | E48: =E19-E47 -> 0 | F48: =F19-F47 -> 0 | G48: =G19-G47 -> 0 | H48: =H19-H47 -> 0 | I48: =I19-I47 -> 0 | J48: =J19-J47 -> 0 | ... R48: =R19-R47 -> 0
B50: Debt | C50: =SUM(C25:C27,C30:C33) -> 98000 | D50: =SUM(D25:D27,D30:D33) -> 108000 | E50: =SUM(E25:E27,E30:E33) -> 122000 | F50: =SUM(F25:F27,F30:F33) -> 154000 | G50: =SUM(G25:G27,G30:G33) -> 86400 | H50: =SUM(H25:H27,H30:H33) -> 81426 | I50: =SUM(I25:I27,I30:I33) -> 113898 | J50: =SUM(J25:J27,J30:J33) -> 115740 | ... R50: =SUM(R25:R27,R30:R33) -> 36800
B52: Diluted Shares Out | C52: ='Income Statement'!C28 -> 15148 | D52: ='Income Statement'!D28 -> 14649 | E52: ='Income Statement'!E28 -> 14379 | F52: ='Income Statement'!F28 -> 14123 | G52: ='Income Statement'!G28 -> 13962 | H52: ='Income Statement'!H28 -> 13830 | I52: ='Income Statement'!I28 -> 13719 | J52: ='Income Statement'!J28 -> 13733 | ... M52: ='Income Statement'!M28 -> 13580
B53: Stock Price | C53: 68.7 | D53: 83.74 | E53: 118.35 | F53: 108.95 | G53: 177.45 | H53: 182.3 | I53: 204.38 | J53: 239.63 | K53: 189.16 | L53: 214.87 | M53: 262.84
B54: Market Cap | C54: =C52*C53 -> 1040667.6 | D54: =D52*D53 -> 1226707.3 | E54: =E52*E53 -> 1701754.6 | F54: =F52*F53 -> 1538700.9 | G54: =G52*G53 -> 2477556.9 | H54: =H52*H53 -> 2521209 | I54: =I52*I53 -> 2803889.2 | J54: =J52*J53 -> 3290838.8 | ... M54: =M52*M53 -> 3569367.2
B56: Total Capital | C56: =C50+C54 -> 1138667.6 | D56: =D50+D54 -> 1334707.3 | E56: =E50+E54 -> 1823754.6 | F56: =F50+F54 -> 1692700.9 | G56: =G50+G54 -> 2563956.9 | H56: =H50+H54 -> 2602635 | I56: =I50+I54 -> 2917787.2 | J56: =J50+J54 -> 3406578.8 | ... M56: =M50+M54 -> 3664003.2
B57: Debt / Total Capital | C57: =C50/C56 -> 0.086065503 | D57: =D50/D56 -> 0.08091662 | E57: =E50/E56 -> 0.066894963 | F57: =F50/F56 -> 0.090978864 | G57: =G50/G56 -> 0.033697914 | H57: =H50/H56 -> 0.031285985 | I57: =I50/I56 -> 0.039035746 | J57: =J50/J56 -> 0.033975436 | ... M57: =M50/M56 -> 0.02582858
L58: 3-year avg | M58: =AVERAGE(K57:M57) -> 0.039629893
L59: 5-year avg | M59: =AVERAGE(I57:M57) -> 0.038380172
L60: 7-year avg | M60: =AVERAGE(G57:M57) -> 0.036697823
L61: 10-year avg | M61: =AVERAGE(D57:M57) -> 0.049567521
L62: MIN | M62: =MIN(C57:M57) -> 0.02582858
L63: MAX | M63: =MAX(C57:M57) -> 0.090978864

Sheet WACC
A1: WACC - WD-40
A3: WACC = [((kd*(1-T)*(D/(D+E)))+(ke*(E/(D+E))] | L3: Current
J4: WDFC Price (4/10/25) | L4: 221.35
A5: WACC = [((kd*(1-T)*(D/(D+E)))+((Rf+B*(Rm-Rf))*(E/(D+E))] | J5: FD Shares Out | L5: 13546.239
J6: Market Cap | L6: =L4*L5 -> 2998460
A7: kd | B7: Tax Rate | C7: Debt | D7: Equity | E7: Total Cap | F7: Rf Rate | G7: Beta | H7: MRP
A8: =F8+0.45% -> 0.0453 | B8: =Assumptions!$T$11 -> 0.23 | C8: =L13 -> 107981 | D8: =L6 -> 2998460 | E8: =SUM(C8:D8) -> 3106441 | F8: 0.0408 | G8: 0.56 | H8: 0.0412 | L8: 45626 | M8: Rate | Q8: SOFR | R8: RCF
J9: Revolving Credit Facility | L9: 41581 | M9: =Assumptions!T54 -> 0.064 | P9: 45535 | Q9: 0.054 | R9: =Q9+1% -> 0.064
C10: Debt | D10: Equity | J10: Series A Notes - 3.39% | L10: 14400 | M10: =Assumptions!T55 -> 0.0339 | P10: 45626 | Q10: 0.0459 | R10: =Q10+1% -> 0.0559
A11: Actual Capital Structure | C11: =C8/E8 -> 0.034760358 | D11: =D8/E8 -> 0.96523964 | J11: Series B Notes - 2.50% | L11: 26000 | M11: =Assumptions!T56 -> 0.025 | P11: 45730 | Q11: 0.043 | R11: =Q11+1% -> 0.053
A12: Target Capital Structure | C12: 0.06 | D12: 0.94 | J12: Series C Notes - 2.69% | L12: 26000 | M12: =Assumptions!T57 -> 0.0269 | O12: Source:
J13: Total Debt | L13: =SUM(L9:L12) -> 107981 | M13: =SUMPRODUCT(L9:L12,M9:M12)/L13 -> 0.041662367 | O13: https://www.newyorkfed.org/markets/reference-rates/sofr
A14: WACC | B14: =(A8*(1-B8)*C12)+(((F8+(G8*H8))*D12)) -> 0.06213254
J15: Source: WDFC, 10Q, 11/30/24, pg. 14
B17: 41517 | C17: 41882 | D17: 42247 | E17: 42613 | F17: 42978 | G17: 43343 | H17: 43708 | I17: 44074 | J17: 44439 | K17: 44804 | L17: 45169 | M17: 45535
A18: OCF | B18: 51569 | C18: 38730 | D18: 55064 | E18: 65302 | F18: 55572 | G18: 64822 | H18: 62851 | I18: 72664 | J18: 84714 | K18: 2604 | L18: 98391 | M18: 92034
A19: Std dev | B19: =STDEV(D18:M18) -> 26619.069
A20: Average | B20: =AVERAGE(D18:M18) -> 65401.8
B22: 45730 | C22: 45372 | D22: 45009 | E22: 44644 | F22: 44288 | G22: 43938 | H22: 43567 | I22: 43189 | J22: 42840 | K22: 42461 | L22: 42097 | M22: 41740
A23: Beta | B23: =B19/B20 -> 0.4070082 | C23: 0.4332148 | D23: 0.40279495 | E23: 0.26 | F23: 0.27165333 | G23: 0.24859785 | H23: 0.26953795 | I23: 0.27121661 | J23: 0.27052609 | K23: 0.27844842 | L23: 0.2738725 | M23: 0.2853778
A24: Yahoo! WDFC | B24: -0.11 | C24: -0.06 | D24: -0.18 | E24: -0.14 | F24: -0.17 | G24: 0.07 | H24: 0.19 | I24: 0.28 | J24: 0.34 | K24: 0.66 | L24: 0.93 | M24: 0.91
A25: CHD | B25: 0.56 | C25: 0.53 | D25: 0.45 | E25: 0.36 | F25: 0.36 | G25: 0.25 | H25: 0.02 | I25: 0.13 | J25: 0.38 | K25: 0.63 | L25: 0.61 | M25: 0.18
A26: CLX | B26: 0.44 | C26: 0.42 | D26: 0.27 | E26: 0.18 | F26: 0.18 | G26: 0.17 | H26: 0.47 | I26: 0.34 | J26: 0.23 | K26: 0.4 | L26: 0.5 | M26: 0.47
A28: Source: Yahoo! Finance as of 3/14/25.

Sheet Start here Ratings sheet
A1: Inputs for synthetic rating estimation | O1: Yes | P1: 1
A2: Please read the special cases worksheet (see below) before you use this spreadsheet. | O2: No | P2: 2
A3: Before you use this spreadsheet, make sure that the iteration box (under calculation options in excel) is checked. | P3: 3
A4: Enter the type of firm = | C4: 2 | D4: (Enter 1 if large manufacturing firm, 2 if smaller or riskier firm, 3 if financial service firm) | I4: Small: <$5 billion
A5: Do you have any operating lease or rental commitments? | F5: No | G5: Yes or No
A6: Enter current Earnings before interest and taxes (EBIT) = | F6: ='Income Statement'!M14 -> 96351 | G6: (Add back only long term interest expense for financial firms)
A7: Enter current interest expenses = | F7: =-'Income Statement'!M16 -> 4287 | G7: (Use only long term interest expense for financial firms)
A8: Enter current long term government bond rate = | F8: 0.03
A9: Output
A10: Interest coverage ratio = | D10: =IF(F5="Yes",'Operating Leases'!F32/('Start here Ratings sheet'!F7+'Operating Leases'!C29*'Start here Ratings sheet'!D13),IF('Start here Ratings sheet'!F7>0,'Start here Ratings sheet'!F6/'Start here Ratings sheet'!F7,100000)) -> 22.475157
A11: Estimated Bond Rating = | D11: =IF(C4=1,VLOOKUP(D10,A19:D33,3),(IF(C4=2,VLOOKUP(D10,A38:D52,3),VLOOKUP(D10,F19:I33,3)))) -> Aaa/AAA | F11: Note: If you get REF! All over the place, set the operating lease commitment question in cell F5
A12: Estimated Default Spread = | D12: =IF(C4=1,VLOOKUP(D10,A19:D33,4),(IF(C4=2,VLOOKUP(D10,A38:D52,4),VLOOKUP(D10,F19:I33,4)))) -> 0.0045 | F12: to No, and then reset it to Yes. It should work.
A13: Estimated Cost of Debt = | D13: =F8+D12 -> 0.0345
A15: If you want to update the spreads listed below, please visit http://www.bondsonline.com
A16: For large non-financial service firms | F16: For financial service firms (default spreads are slighty different)
A17: If interest coverage ratio is | F17: If long term interest coverage ratio is
A18: > | B18: ≤ to | C18: Rating is | D18: Spread is | F18: greater than | G18: ≤ to | H18: Rating is | I18: Spread is
A19: -100000 | B19: 0.199999 | C19: D2/D | D19: 0.19 | F19: -100000 | G19: 0.049999 | H19: D2/D | I19: 0.19
A20: 0.2 | B20: 0.649999 | C20: C2/C | D20: 0.155 | F20: 0.05 | G20: 0.099999 | H20: C2/C | I20: 0.155
A21: 0.65 | B21: 0.799999 | C21: Ca2/CC | D21: 0.101 | F21: 0.1 | G21: 0.199999 | H21: Ca2/CC | I21: 0.101
A22: 0.8 | B22: 1.249999 | C22: Caa/CCC | D22: 0.0728 | F22: 0.2 | G22: 0.299999 | H22: Caa/CCC | I22: 0.0728
A23: 1.25 | B23: 1.499999 | C23: B3/B- | D23: 0.0442 | F23: 0.3 | G23: 0.399999 | H23: B3/B- | I23: 0.0442
A24: 1.5 | B24: 1.749999 | C24: B2/B | D24: 0.03 | F24: 0.4 | G24: 0.499999 | H24: B2/B | I24: 0.03
A25: 1.75 | B25: 1.999999 | C25: B1/B+ | D25: 0.0261 | F25: 0.5 | G25: 0.599999 | H25: B1/B+ | I25: 0.0261
A26: 2 | B26: 2.2499999 | C26: Ba2/BB | D26: 0.0183 | F26: 0.6 | G26: 0.749999 | H26: Ba2/BB | I26: 0.0183
A27: 2.25 | B27: 2.49999 | C27: Ba1/BB+ | D27: 0.0155 | F27: 0.75 | G27: 0.899999 | H27: Ba1/BB+ | I27: 0.0155
A28: 2.5 | B28: 2.999999 | C28: Baa2/BBB | D28: 0.012 | F28: 0.9 | G28: 1.199999 | H28: Baa2/BBB | I28: 0.012
A29: 3 | B29: 4.249999 | C29: A3/A- | D29: 0.0095 | F29: 1.2 | G29: 1.49999 | H29: A3/A- | I29: 0.0095
A30: 4.25 | B30: 5.499999 | C30: A2/A | D30: 0.0085 | F30: 1.5 | G30: 1.99999 | H30: A2/A | I30: 0.0085
... A33: 8.5 | B33: 100000 | C33: Aaa/AAA | D33: 0.0045 | F33: 3 | G33: 100000 | H33: Aaa/AAA | I33: 0.0045
A35: For smaller and riskier firms
A36: If interest coverage ratio is
A37: greater than | B37: ≤ to | C37: Rating is | D37: Spread is
A38: -100000 | B38: 0.499999 | C38: D2/D | D38: 0.19
A39: 0.5 | B39: 0.799999 | C39: C2/C | D39: 0.155
A40: 0.8 | B40: 1.249999 | C40: Ca2/CC | D40: 0.101
A41: 1.25 | B41: 1.499999 | C41: Caa/CCC | D41: 0.0728
A42: 1.5 | B42: 1.999999 | C42: B3/B- | D42: 0.0442
A43: 2 | B43: 2.499999 | C43: B2/B | D43: 0.03
A44: 2.5 | B44: 2.999999 | C44: B1/B+ | D44: 0.0261
A45: 3 | B45: 3.499999 | C45: Ba2/BB | D45: 0.0183
A46: 3.5 | B46: 3.9999999 | C46: Ba1/BB+ | D46: 0.0155
A47: 4 | B47: 4.499999 | C47: Baa2/BBB | D47: 0.012
A48: 4.5 | B48: 5.999999 | C48: A3/A- | D48: 0.0095
A49: 6 | B49: 7.499999 | C49: A2/A | D49: 0.0085
... A52: 12.5 | B52: 100000 | C52: Aaa/AAA | D52: 0.0045

Sheet Cash Flow Statement
A1: WD-40 Cash Flow Statement
B2: (USD in thousands, except per share data)
C4: Historical | F4: Projected
C5: 44804 | D5: 45169 | E5: 45535 | F5: 45900 | G5: 46265 | H5: 46630 | I5: 46996 | J5: 47361
A6: Cash Flow from Operations
B7: Net Income | F7: ='Income Statement'!N20 -> 84057.45 | G7: ='Income Statement'!O20 -> 91032.969 | H7: ='Income Statement'!P20 -> 98548.795 | I7: ='Income Statement'!Q20 -> 106377.83 | J7: ='Income Statement'!R20 -> 115573.96
B8: Depreciation | F8: ='Income Statement'!N12 -> 8846.5439 | G8: ='Income Statement'!O12 -> 9465.8019 | H8: ='Income Statement'!P12 -> 10128.408 | I8: ='Income Statement'!Q12 -> 10837.397 | J8: ='Income Statement'!R12 -> 11596.014
B9: Amortization | F9: ='Income Statement'!N13 -> 1263.792 | G9: ='Income Statement'!O13 -> 1352.2574 | H9: ='Income Statement'!P13 -> 1446.9154 | I9: ='Income Statement'!Q13 -> 1548.1995 | J9: ='Income Statement'!R13 -> 610.83564
B10: D in Operating Working Capital | F10: =Calcs!N56 -> -2740.6808 | G10: =Calcs!O56 -> -8164.9177 | H10: =Calcs!P56 -> -8736.4619 | I10: =Calcs!Q56 -> -9348.0142 | J10: =Calcs!R56 -> -10002.375
B11: Total Cash Flow from Operations | F11: =SUM(F7:F10) -> 91427.105 | G11: =SUM(G7:G10) -> 93686.111 | H11: =SUM(H7:H10) -> 101387.66 | I11: =SUM(I7:I10) -> 109415.41 | J11: =SUM(J7:J10) -> 117778.43
A13: Cash Flow from Investing
B14: Capital Expenditures | F14: =-Calcs!N20 -> -12637.92 | G14: =-Calcs!O20 -> -13522.574 | H14: =-Calcs!P20 -> -14469.154 | I14: =-Calcs!Q20 -> -15481.995 | J14: =-Calcs!R20 -> -16565.735
B15: D in Other Non-Current Assets | F15: =-('Balance Sheet PROJECTED'!N18-'Balance Sheet PROJECTED'!M18) -> -993.39975 | G15: =-('Balance Sheet PROJECTED'!O18-'Balance Sheet PROJECTED'!N18) -> -1105.818 | H15: =-('Balance Sheet PROJECTED'!P18-'Balance Sheet PROJECTED'!O18) -> -1183.2252 | I15: =-('Balance Sheet PROJECTED'!Q18-'Balance Sheet PROJECTED'!P18) -> -1266.051 | J15: =-('Balance Sheet PROJECTED'!R18-'Balance Sheet PROJECTED'!Q18) -> -1354.6746
B16: D in Other Non-Current Liabilites | F16: ='Balance Sheet PROJECTED'!N36-'Balance Sheet PROJECTED'!M36 -> 1099.5038 | G16: ='Balance Sheet PROJECTED'!O36-'Balance Sheet PROJECTED'!N36 -> 1061.5853 | H16: ='Balance Sheet PROJECTED'!P36-'Balance Sheet PROJECTED'!O36 -> 1135.8962 | I16: ='Balance Sheet PROJECTED'!Q36-'Balance Sheet PROJECTED'!P36 -> 1215.409 | J16: ='Balance Sheet PROJECTED'!R36-'Balance Sheet PROJECTED'!Q36 -> 1300.4876
B17: Total Cash Flow from Investing | F17: =SUM(F14:F16) -> -12531.816 | G17: =SUM(G14:G16) -> -13566.807 | H17: =SUM(H14:H16) -> -14516.483 | I17: =SUM(I14:I16) -> -15532.637 | J17: =SUM(J14:J16) -> -16619.922
A19: Cash Flow from Financing
B20: OLD Revolver, current | F20: ='Balance Sheet PROJECTED'!N25-'Balance Sheet PROJECTED'!M25 -> 0 | G20: ='Balance Sheet PROJECTED'!O25-'Balance Sheet PROJECTED'!N25 -> 0 | H20: ='Balance Sheet PROJECTED'!P25-'Balance Sheet PROJECTED'!O25 -> 0 | I20: ='Balance Sheet PROJECTED'!Q25-'Balance Sheet PROJECTED'!P25 -> 0 | J20: ='Balance Sheet PROJECTED'!R25-'Balance Sheet PROJECTED'!Q25 -> 0
B21: Short-term borrowings, current | F21: ='Balance Sheet PROJECTED'!N26-'Balance Sheet PROJECTED'!M26 -> 0 | G21: ='Balance Sheet PROJECTED'!O26-'Balance Sheet PROJECTED'!N26 -> 0 | H21: ='Balance Sheet PROJECTED'!P26-'Balance Sheet PROJECTED'!O26 -> 0 | I21: ='Balance Sheet PROJECTED'!Q26-'Balance Sheet PROJECTED'!P26 -> 0 | J21: ='Balance Sheet PROJECTED'!R26-'Balance Sheet PROJECTED'!Q26 -> 0
B22: Revolving credit facility | F22: ='Balance Sheet PROJECTED'!N30-'Balance Sheet PROJECTED'!M30 -> -5567.2 | G22: ='Balance Sheet PROJECTED'!O30-'Balance Sheet PROJECTED'!N30 -> -5567.2 | H22: ='Balance Sheet PROJECTED'!P30-'Balance Sheet PROJECTED'!O30 -> -5567.2 | I22: ='Balance Sheet PROJECTED'!Q30-'Balance Sheet PROJECTED'!P30 -> -5567.2 | J22: ='Balance Sheet PROJECTED'!R30-'Balance Sheet PROJECTED'!Q30 -> -5567.2
B23: Series A Notes - 3.39% fixed rate | F23: ='Balance Sheet PROJECTED'!N31-'Balance Sheet PROJECTED'!M31 -> -800 | G23: ='Balance Sheet PROJECTED'!O31-'Balance Sheet PROJECTED'!N31 -> -800 | H23: ='Balance Sheet PROJECTED'!P31-'Balance Sheet PROJECTED'!O31 -> -800 | I23: ='Balance Sheet PROJECTED'!Q31-'Balance Sheet PROJECTED'!P31 -> -800 | J23: ='Balance Sheet PROJECTED'!R31-'Balance Sheet PROJECTED'!Q31 -> -800
B24: Series B Notes - 2.50% fixed rate | F24: ='Balance Sheet PROJECTED'!N32-'Balance Sheet PROJECTED'!M32 -> 0 | G24: ='Balance Sheet PROJECTED'!O32-'Balance Sheet PROJECTED'!N32 -> 0 | H24: ='Balance Sheet PROJECTED'!P32-'Balance Sheet PROJECTED'!O32 -> 0 | I24: ='Balance Sheet PROJECTED'!Q32-'Balance Sheet PROJECTED'!P32 -> -26000 | J24: ='Balance Sheet PROJECTED'!R32-'Balance Sheet PROJECTED'!Q32 -> 0
B25: Series C Notes - 2.69% fixed rate | F25: ='Balance Sheet PROJECTED'!N33-'Balance Sheet PROJECTED'!M33 -> 0 | G25: ='Balance Sheet PROJECTED'!O33-'Balance Sheet PROJECTED'!N33 -> 0 | H25: ='Balance Sheet PROJECTED'!P33-'Balance Sheet PROJECTED'!O33 -> 0 | I25: ='Balance Sheet PROJECTED'!Q33-'Balance Sheet PROJECTED'!P33 -> 0 | J25: ='Balance Sheet PROJECTED'!R33-'Balance Sheet PROJECTED'!Q33 -> 0
B26: Common stock | F26: ='Balance Sheet PROJECTED'!N40-'Balance Sheet PROJECTED'!M40 -> 0 | G26: ='Balance Sheet PROJECTED'!O40-'Balance Sheet PROJECTED'!N40 -> 0 | H26: ='Balance Sheet PROJECTED'!P40-'Balance Sheet PROJECTED'!O40 -> 0 | I26: ='Balance Sheet PROJECTED'!Q40-'Balance Sheet PROJECTED'!P40 -> 0 | J26: ='Balance Sheet PROJECTED'!R40-'Balance Sheet PROJECTED'!Q40 -> 0
B27: Additional paid-in capital | F27: ='Balance Sheet PROJECTED'!N41-'Balance Sheet PROJECTED'!M41 -> 0 | G27: ='Balance Sheet PROJECTED'!O41-'Balance Sheet PROJECTED'!N41 -> 0 | H27: ='Balance Sheet PROJECTED'!P41-'Balance Sheet PROJECTED'!O41 -> 0 | I27: ='Balance Sheet PROJECTED'!Q41-'Balance Sheet PROJECTED'!P41 -> 0 | J27: ='Balance Sheet PROJECTED'!R41-'Balance Sheet PROJECTED'!Q41 -> 0
B28: Accumulated other | F28: ='Balance Sheet PROJECTED'!N43-'Balance Sheet PROJECTED'!M43 -> 0 | G28: ='Balance Sheet PROJECTED'!O43-'Balance Sheet PROJECTED'!N43 -> 0 | H28: ='Balance Sheet PROJECTED'!P43-'Balance Sheet PROJECTED'!O43 -> 0 | I28: ='Balance Sheet PROJECTED'!Q43-'Balance Sheet PROJECTED'!P43 -> 0 | J28: ='Balance Sheet PROJECTED'!R43-'Balance Sheet PROJECTED'!Q43 -> 0
B29: Share repurchases | F29: ='Balance Sheet PROJECTED'!N44-'Balance Sheet PROJECTED'!M44 -> -7000 | G29: ='Balance Sheet PROJECTED'!O44-'Balance Sheet PROJECTED'!N44 -> 0 | H29: ='Balance Sheet PROJECTED'!P44-'Balance Sheet PROJECTED'!O44 -> 0 | I29: ='Balance Sheet PROJECTED'!Q44-'Balance Sheet PROJECTED'!P44 -> 0 | J29: ='Balance Sheet PROJECTED'!R44-'Balance Sheet PROJECTED'!Q44 -> 0
B30: Dividends | F30: =-Calcs!N7 -> -47072.172 | G30: =-Calcs!O7 -> -50978.463 | H30: =-Calcs!P7 -> -55187.325 | I30: =-Calcs!Q7 -> -59571.584 | J30: =-Calcs!R7 -> -64721.416
B31: Total Cash Flow from Financing | F31: =SUM(F20:F30) -> -60439.372 | G31: =SUM(G20:G30) -> -57345.663 | H31: =SUM(H20:H30) -> -61554.525 | I31: =SUM(I20:I30) -> -91938.784 | J31: =SUM(J20:J30) -> -71088.616
B33: Net Cash Flow (D in Cash) | F33: =F11+F17+F31 -> 18455.917 | G33: =G11+G17+G31 -> 22773.641 | H33: =H11+H17+H31 -> 25316.648 | I33: =I11+I17+I31 -> 1943.9892 | J33: =J11+J17+J31 -> 30069.894
A35: Cash Analysis
B36: Beginning Cash | F36: =E38 -> 46699 | G36: =F38 -> 65154.917 | H36: =G38 -> 87928.558 | I36: =H38 -> 113245.21 | J36: =I38 -> 115189.2
B37: Change in Cash from CFS | F37: =F33 -> 18455.917 | G37: =G33 -> 22773.641 | H37: =H33 -> 25316.648 | I37: =I33 -> 1943.9892 | J37: =J33 -> 30069.894
B38: Net Cash Available at end of year | E38: ='Balance Sheet PROJECTED'!$M$6 -> 46699 | F38: =SUM(F36:F37) -> 65154.917 | G38: =SUM(G36:G37) -> 87928.558 | H38: =SUM(H36:H37) -> 113245.21 | I38: =SUM(I36:I37) -> 115189.2 | J38: =SUM(J36:J37) -> 145259.09
B40: Required CASH | F40: ='Balance Sheet PROJECTED'!N6 -> 51183.575 | G40: ='Balance Sheet PROJECTED'!O6 -> 54766.425 | H40: ='Balance Sheet PROJECTED'!P6 -> 58600.075 | I40: ='Balance Sheet PROJECTED'!Q6 -> 62702.081 | J40: ='Balance Sheet PROJECTED'!R6 -> 67091.226
B41: EXCESS CASH / (REVOLVER) | F41: =F38-F40 -> 13971.342 | G41: =G38-G40 -> 33162.133 | H41: =H38-H40 -> 54645.131 | I41: =I38-I40 -> 52487.115 | J41: =J38-J40 -> 78167.863
A43: DCF Valuation
B44: EBIT | F44: ='Income Statement'!N14 -> 109949.9 | G44: ='Income Statement'!O14 -> 117646.4 | H44: ='Income Statement'!P14 -> 125881.64 | I44: ='Income Statement'!Q14 -> 134693.36 | J44: ='Income Statement'!R14 -> 145167.63
B45: Other income (expense), net | F45: ='Income Statement'!N17 -> 0 | G45: ='Income Statement'!O17 -> 0 | H45: ='Income Statement'!P17 -> 0 | I45: ='Income Statement'!Q17 -> 0 | J45: ='Income Statement'!R17 -> 0
B46: Taxes | F46: ='Income Statement'!N19 -> 25108.069 | G46: ='Income Statement'!O19 -> 27191.666 | H46: ='Income Statement'!P19 -> 29436.653 | I46: ='Income Statement'!Q19 -> 31775.196 | J46: ='Income Statement'!R19 -> 34522.091
B47: EBIAT (NOPAT) | F47: =F44+F45-F46 -> 84841.833 | G47: =G44+G45-G46 -> 90454.729 | H47: =H44+H45-H46 -> 96444.99 | I47: =I44+I45-I46 -> 102918.16 | J47: =J44+J45-J46 -> 110645.54
B49: EBIAT (NOPAT) | F49: =F47 -> 84841.833 | G49: =G47 -> 90454.729 | H49: =H47 -> 96444.99 | I49: =I47 -> 102918.16 | J49: =J47 -> 110645.54
B50: Depreciation | F50: ='Cash Flow Statement'!F8 -> 8846.5439 | G50: ='Cash Flow Statement'!G8 -> 9465.8019 | H50: ='Cash Flow Statement'!H8 -> 10128.408 | I50: ='Cash Flow Statement'!I8 -> 10837.397 | J50: ='Cash Flow Statement'!J8 -> 11596.014
B51: Amortization | F51: ='Cash Flow Statement'!F9 -> 1263.792 | G51: ='Cash Flow Statement'!G9 -> 1352.2574 | H51: ='Cash Flow Statement'!H9 -> 1446.9154 | I51: ='Cash Flow Statement'!I9 -> 1548.1995 | J51: ='Cash Flow Statement'!J9 -> 610.83564
B52: D in Operating Working Capital | F52: ='Cash Flow Statement'!F10 -> -2740.6808 | G52: ='Cash Flow Statement'!G10 -> -8164.9177 | H52: ='Cash Flow Statement'!H10 -> -8736.4619 | I52: ='Cash Flow Statement'!I10 -> -9348.0142 | J52: ='Cash Flow Statement'!J10 -> -10002.375
B53: Capital Expenditures | F53: ='Cash Flow Statement'!F14 -> -12637.92 | G53: ='Cash Flow Statement'!G14 -> -13522.574 | H53: ='Cash Flow Statement'!H14 -> -14469.154 | I53: ='Cash Flow Statement'!I14 -> -15481.995 | J53: ='Cash Flow Statement'!J14 -> -16565.735
B54: D in Other Non-Current Assets | F54: ='Cash Flow Statement'!F15 -> -993.39975 | G54: ='Cash Flow Statement'!G15 -> -1105.818 | H54: ='Cash Flow Statement'!H15 -> -1183.2252 | I54: ='Cash Flow Statement'!I15 -> -1266.051 | J54: ='Cash Flow Statement'!J15 -> -1354.6746
B55: D in Other Non-Current Liabilities | F55: ='Cash Flow Statement'!F16 -> 1099.5038 | G55: ='Cash Flow Statement'!G16 -> 1061.5853 | H55: ='Cash Flow Statement'!H16 -> 1135.8962 | I55: ='Cash Flow Statement'!I16 -> 1215.409 | J55: ='Cash Flow Statement'!J16 -> 1300.4876
B56: Unlevered FCFs | F56: =SUM(F49:F55) -> 79679.672 | G56: =SUM(G49:G55) -> 79541.064 | H56: =SUM(H49:H55) -> 84767.368 | I56: =SUM(I49:I55) -> 90423.107 | J56: =SUM(J49:J55) -> 96230.093
A58: Terminal Value
B59: Growth rate | D59: 0.02
B60: Discount rate (WACC) | D60: =WACC!B14 -> 0.06213254
B61: Terminal Value | D61: =J56*(1+D59)/(D60-D59) -> 2329664.8
F62: Today | G62: Year End | H62: Diff | I62: Year | J62: Factor
A63: Discounting Model | F63: 45730 | G63: 45900 | H63: =G63-F63 -> 170 | I63: 365.25 | J63: =H63/I63 -> 0.46543463
B64: Mid-year convention | C64: YES
B65: Year count | F65: =IF($C$64="YES",J63/2,1) -> 0.23271732 | G65: =F65+1 -> 1.2327173 | H65: =G65+1 -> 2.2327173 | I65: =H65+1 -> 3.2327173 | J65: =I65+1 -> 4.2327173
B66: Discount denominator | F66: =1/(1+$D$60)^F65 -> 0.98607003 | G66: =1/(1+$D$60)^G65 -> 0.92838699 | H66: =1/(1+$D$60)^H65 -> 0.87407829 | I66: =1/(1+$D$60)^I65 -> 0.82294653 | J66: =1/(1+$D$60)^J65 -> 0.77480587
B67: PV of Free Cash Flow | F67: =F56*F66*J63 -> 36569.077 | G67: =G56*G66 -> 73844.889 | H67: =H56*H66 -> 74093.316 | I67: =I56*I66 -> 74413.382 | J67: =J56*J66 -> 74559.641
B69: PV of FCFs | C69: =SUM(F67:J67) -> 333480.3 | E69: WACC | J69: Terminal growth
B70: PV of Terminal Value | C70: =D61*J66 -> 1805038 | E70: =$C$86 -> 153.95057 | F70: =G70-0.5% -> 0.01 | G70: =H70-0.5% -> 0.015 | H70: 0.02 | I70: =H70+0.5% -> 0.025 | J70: =I70+0.5% -> 0.03
B71: TEV (Total Enterprise Value) | C71: =SUM(C69:C70) -> 2138518.3 | E71: =E72+0.5% -> 0.07213254 | F71: 106.13337 | G71: 114.12205 | H71: 123.6431 | I71: 135.18421 | J71: 149.46456
E72: =E73+0.5% -> 0.06713254 | F72: 115.80498 | G72: 125.471 | H72: 137.18784 | I72: 151.68563 | J72: 170.08775
B73: Short-term debt | C73: 23429 | E73: 0.06213254 | F73: 127.33491 | G73: 139.231 | H73: 153.95057 | I73: 172.63421 | J73: 197.13241
B74: Long-term debt | C74: 84552 | E74: =E73-0.5% -> 0.05713254 | F74: 141.31466 | G74: 156.26049 | H74: 175.23131 | I74: 200.10607 | J74: 234.14869
B75: Total debt | C75: =SUM(C73:C74) -> 107981 | E75: =E74-0.5% -> 0.05213254 | F75: 158.61648 | G75: 177.8803 | H75: 203.13923 | I75: 237.70762 | J75: 287.89481
B77: Required Cash | C77: 54914 | E77: WACC | J77: Terminal growth
B78: Excess Cash | C78: 0 | E78: =$C$86 -> 153.95057 | F78: =G78-0.5% -> 0.01 | G78: =H78-0.5% -> 0.015 | H78: 0.02 | I78: =H78+0.5% -> 0.025 | J78: =I78+0.5% -> 0.03
B79: Total cash | C79: =SUM(C77:C78) -> 54914 | E79: =E80+0.5% -> 0.07213254 | F79: =$C$87/F71-1 -> 1.0855834 | G79: =$C$87/G71-1 -> 0.93959017 | H79: =$C$87/H71-1 -> 0.79023335 | I79: =$C$87/I71-1 -> 0.63739535 | J79: =$C$87/J71-1 -> 0.48095304
E80: =E81+0.5% -> 0.06713254 | F80: =$C$87/F72-1 -> 0.91140312 | G80: =$C$87/G72-1 -> 0.76415264 | H80: =$C$87/H72-1 -> 0.61348119 | I80: =$C$87/I72-1 -> 0.45926812 | J80: =$C$87/J72-1 -> 0.30138709
B81: Convertibles / Preferred Stock | C81: 0 | E81: 0.06213254 | F81: =$C$87/F73-1 -> 0.73832923 | G81: =$C$87/G73-1 -> 0.58980403 | H81: =$C$87/H73-1 -> 0.43779913 | I81: =$C$87/I73-1 -> 0.2821908 | J81: =$C$87/J73-1 -> 0.12284937
B82: Minority Interests | C82: 0 | E82: =E81-0.5% -> 0.05713254 | F82: =$C$87/F74-1 -> 0.56636265 | G82: =$C$87/G74-1 -> 0.41654493 | H82: =$C$87/H74-1 -> 0.26318749 | I82: =$C$87/I74-1 -> 0.10616337 | J82: =$C$87/J74-1 -> -0.054660515
B83: Associate Investments | C83: 0 | E83: =E82-0.5% -> 0.05213254 | F83: =$C$87/F75-1 -> 0.3955044 | G83: =$C$87/G75-1 -> 0.24437613 | H83: =$C$87/H75-1 -> 0.089646746 | I83: =$C$87/I75-1 -> -0.068814023 | J83: =$C$87/J75-1 -> -0.2311428
B84: Equity Value | C84: =C71-C75+C79-SUM(C81:C82)+C83 -> 2085451.3
B85: Diluted Shares Outstanding | C85: =WACC!$L$5 -> 13546.239
B86: Value per share | C86: =C84/C85 -> 153.95057
B87: Current Price (4/10/25) | C87: =WACC!$L$4 -> 221.35 | D87: Rating
B88: Premium / (Discount) to Intrinsic Value | C88: =C87/C86-1 -> 0.43779913 | D88: SELL
B90: Dividends | C90: =-F30 -> 47072.172
B91: Cost of Equity (Rf + Beta x MRP) | C91: =WACC!F8+(WACC!G8*WACC!H8) -> 0.063872
B92: Growth (perpetuity) | C92: =$D$59 -> 0.02
B93: Equity Value | C93: =(C90*(1+C92))/(C91-C92) -> 1094402.2
B94: Diluted Shares Outstanding | C94: =WACC!$L$5 -> 13546.239
B95: Value per share | C95: =C93/C94 -> 80.790118
B96: Current Price | C96: =WACC!$L$4 -> 221.35 | D96: Rating
B97: Premium / (Discount) to Intrinsic Value | C97: =C96/C95-1 -> 1.7398153 | D97: SELL
B99: Dividend per share | C99: 3.76
B100: Cost of Equity (Rf + Beta x MRP) | C100: =WACC!F8+(WACC!G8*WACC!H8) -> 0.063872
B101: Growth (perpetuity) | C101: =$D$59 -> 0.02
B102: Value per share | C102: =(C99*(1+C101))/(C100-C101) -> 87.417943
B103: Current Price | C103: =WACC!$L$4 -> 221.35 | D103: Rating
B104: Premium / (Discount) to Intrinsic Value | C104: =C103/C102-1 -> 1.5320889 | D104: SELL

Sheet Operating Leases
A1: Operating lease inputs
A2: Operating lease expense in current year = | E2: 25
A3: Operating Lease Commitments (From footnote to financials)
A4: Year | B4: Commitment | C4: ! Year 1 is next year, ….
A5: 1 | B5: 24
A6: 2 | B6: 22
A7: 3 | B7: 22
A8: 4 | B8: 21
A9: 5 | B9: 20
A10: 6 and beyond | B10: 111
A12: Pre-tax Cost of Debt = | C12: ='Start here Ratings sheet'!D13 -> 0.0345 | D12: ! If you do not have a cost of debt, use the attached ratings estimator
A14: From the current financial statements, enter the following
A15: Reported Operating Income (EBIT) = | D15: ='Start here Ratings sheet'!F6 -> 96351 | E15: ! This is the EBIT reported in the current income statement
A16: Reported Debt = | D16: 92.97 | E16: ! This is the interest-bearing debt reported on the balance sheet
A17: Reported Interest Expenses = | D17: ='Start here Ratings sheet'!F7 -> 4287
A18: Output
A19: Number of years embedded in yr 6 estimate = | D19: =ROUND(B10/AVERAGE(B5:B9),0) -> 5 | E19: ! I use the average lease expense over the first five years
E20: to estimate the number of years of expenses in yr 6
A21: Converting Operating Leases into debt
A22: Year | B22: Commitment | C22: Present Value
A23: =A5 -> 1 | B23: =B5 -> 24 | C23: =B23/(1+$C$12)^A23 -> 23.199613
A24: =A6 -> 2 | B24: =B6 -> 22 | C24: =B24/(1+$C$12)^A24 -> 20.557093
A25: =A7 -> 3 | B25: =B7 -> 22 | C25: =B25/(1+$C$12)^A25 -> 19.871525
A26: =A8 -> 4 | B26: =B8 -> 21 | C26: =B26/(1+$C$12)^A26 -> 18.335692
A27: =A9 -> 5 | B27: =B9 -> 20 | C27: =B27/(1+$C$12)^A27 -> 16.880197
A28: =A10 -> 6 and beyond | B28: =IF(B10>0,IF(D19>1,B10/D19,B10),0) -> 22.2 | C28: =IF(D19>0,(B28*(1-(1+C12)^(-D19))/C12)/(1+$C$12)^5,B28/(1+C12)^6) -> 84.718552 | D28: ! Commitment beyond year 6 converted into an annuity for ten years
A29: Debt Value of leases = | C29: =SUM(C23:C28) -> 183.56267
A31: Restated Financials
A32: Operating Income with Operating leases reclassified as debt = | F32: =D15+E2-C29/(5+D19) -> 96357.644
A33: Debt with Operating leases reclassified as debt = | F33: =D16+C29 -> 276.53267
A36: Full Operating lease adjustment
A37: Reported Operating income = | D37: =D15 -> 96351
A38: + Current year's operating lease expense = | D38: =E2 -> 25
A39: - Depreciation on leased asset = | D39: =C29/(5+D19) -> 18.356267
A40: Adjusted Operating Income | D40: =D37+D38-D39 -> 96357.644

Sheet Trading Comps
A1: Trading Comparables
A2: (in thousands)
A4: Ticker | B4: WDFC | E4: CHD | H4: CLX
A5: Company | B5: WD-40 | E5: Church & Dwight | H5: Clorox
K6: WDFC Options Calc | S6: Value per
A7: Price (as of 4/10/25) | B7: 221.35 | E7: 103.77 | H7: 140.9 | K7: # of | L7: Wgthd Avg | M7: Current | N7: In the | O7: Shares in | Q7: Price | R7: Strike | S7: Option
K8: Options Ex | L8: Strike Price | M8: Price | N8: Money? | O8: the money | Q8: 100 | R8: 50 | S8: =Q8-R8 -> 50
A9: Shares Out | B9: 13546.239 | E9: 245969.88 | H9: 123189.87 | K9: 0 | L9: 0 | M9: =B7 -> 221.35 | N9: =IF(M9>L9,"YES","NO") -> YES | O9: =IF(N9="YES",((M9-L9)/M9)*K9,0) -> 0
A10: Options Ex. | B10: =O9 -> 0 | E10: =O20 -> 1688.224 | H10: =O26 -> 0 | Q10: Value per | S10: # of Shs
A11: FD Shares Out | B11: =SUM(B9:B10) -> 13546.239 | E11: =SUM(E9:E10) -> 247658.1 | H11: =SUM(H9:H10) -> 123189.87 | K11: Source: WDFC, 10K, 8/31/24, pg. F-16 | Q11: Option | R11: Price | S11: per option
Q12: =S8 -> 50 | R12: =Q8 -> 100 | S12: =Q12/R12 -> 0.5
A13: FD Equity Value | B13: =B7*B11 -> 2998460 | E13: =E7*E11 -> 25699482 | H13: =H7*H11 -> 17357452 | K13: CHD Options Calc
K14: # of | L14: Wgthd Avg | M14: Current | N14: In the | O14: Shares in | Q14: # of | R14: # of Shs | S14: NEW
A15: Total Debt | B15: =23429+84552 -> 107981 | E15: =2204.6*1000 -> 2204600 | H15: =(189+2483)*1000 -> 2672000 | K15: Options Ex | L15: Strike Price | M15: Price | N15: Money? | O15: the money | Q15: options | R15: per option | S15: SHARES
A16: Cash | B16: 54914 | E16: =964.1*1000 -> 964100 | H16: =290*1000 -> 290000 | K16: 500 | L16: 46.72 | M16: =$E$7 -> 103.77 | N16: =IF(M16>L16,"YES","NO") -> YES | O16: =IF(N16="YES",((M16-L16)/M16)*K16,0) -> 274.88677 | Q16: 1000 | R16: =S12 -> 0.5 | S16: =Q16*R16 -> 500
A17: Net Debt | B17: =B15-B16 -> 53067 | E17: =E15-E16 -> 1240500 | H17: =H15-H16 -> 2382000 | K17: 1200 | L17: 51.31 | M17: =$E$7 -> 103.77 | N17: =IF(M17>L17,"YES","NO") -> YES | O17: =IF(N17="YES",((M17-L17)/M17)*K17,0) -> 606.64932
K18: 2200 | L18: 75.31 | M18: =$E$7 -> 103.77 | N18: =IF(M18>L18,"YES","NO") -> YES | O18: =IF(N18="YES",((M18-L18)/M18)*K18,0) -> 603.37284
A19: Preferreds/Convertibles | B19: 0 | E19: 0 | H19: 0 | K19: 1100 | L19: 84.59 | M19: =$E$7 -> 103.77 | N19: =IF(M19>L19,"YES","NO") -> YES | O19: =IF(N19="YES",((M19-L19)/M19)*K19,0) -> 203.31502
A20: Minority Interests | B20: 0 | E20: 0 | H20: =162*1000 -> 162000 | N20: NEW SHARES | O20: =SUM(O16:O19) -> 1688.224
A21: Associate Investments | B21: 0 | E21: =11.1*1000 -> 11100 | H21: 0 | K21: Source: CHD, 10K, 12/31/24, pg. 80
A22: TEV | B22: =B13+B17+SUM(B19:B20)-B21 -> 3051527 | E22: =E13+E17+SUM(E19:E20)-E21 -> 26928882 | H22: =H13+H17+SUM(H19:H20)-H21 -> 19901452
K23: CLX Options Calc
A24: Sales (P/S) | K24: # of | L24: Wgthd Avg | M24: Current | N24: In the | O24: Shares in
A25: LTM | B25: =O33 -> 603636 | C25: =$B$13/B25 -> 4.9673313 | E25: =6107.1*1000 -> 6107100 | F25: =$E$13/E25 -> 4.2081318 | H25: =O48 -> 7165000 | I25: =$H$13/H25 -> 2.4225335 | K25: Options Ex | L25: Strike Price | M25: Price | N25: Money? | O25: the money
A26: Annualized Stub | B26: =N33*4 -> 613980 | C26: =$B$13/B26 -> 4.8836444 | H26: =N48*2 -> 6896000 | I26: =$H$13/H26 -> 2.5170319 | K26: 3052 | L26: 148 | M26: =H7 -> 140.9 | N26: =IF(M26>L26,"YES","NO") -> NO | O26: =IF(N26="YES",((M26-L26)/M26*K26),0) -> 0
A28: EBITDA (TEV/EBITDA) | K28: Source: CLX, 10K, 6/30/24, pg. 53
A29: LTM | B29: =O36 -> 106559 | C29: =$B$22/B29 -> 28.636971 | E29: =(807.1+357.1+83.2+155.9)*1000 -> 1403300 | F29: =$E$22/E29 -> 19.189683 | H29: =O53 -> 1289000 | I29: =$H$22/H29 -> 15.439451
A30: Annualized Stub | B30: =N36*4 -> 108788 | C30: =$B$22/B30 -> 28.050217 | H30: =N53*2 -> 1274000 | I30: =$H$22/H30 -> 15.621234 | K30: WDFC LTM Calc
L31: 1Q | M31: Year End | N31: 1Q
A32: Earnings (P/E) | L32: 45260 | M32: 45535 | N32: 45626 | O32: LTM | U32: 1Q25
A33: LTM | B33: =O37 -> 71087 | C33: =$B$13/B33 -> 42.180145 | E33: =585.3*1000 -> 585300 | F33: =$E$13/E33 -> 43.908221 | H33: =O54 -> 457000 | I33: =$H$13/H33 -> 37.981296 | K33: Sales | L33: 140416 | M33: ='Income Statement'!M6 -> 590557 | N33: 153495 | O33: =N33+M33-L33 -> 603636 | Q33: 1Q24 | R33: 2Q24 | S33: 3Q24 | T33: 4Q24
A34: Annualized Stub | B34: =N37*4 -> 75700 | C34: =$B$13/B34 -> 39.609775 | H34: =N54*2 -> 584000 | I34: =$H$13/H34 -> 29.721665 | K34: Op Income | L34: 24184 | M34: ='Income Statement'!$M$14 -> 96351 | N34: 25122 | O34: =N34+M34-L34 -> 97289
K35: D&A | L35: 2261 | M35: =SUM('Income Statement'!M12:M13) -> 9456 | N35: 2075 | O35: =N35+M35-L35 -> 9270
A36: Capex | K36: EBITDA | L36: =SUM(L34:L35) -> 26445 | M36: =SUM(M34:M35) -> 105807 | N36: =SUM(N34:N35) -> 27197 | O36: =SUM(O34:O35) -> 106559 | U36: 1Q25 | V36: 2Q25
A37: LTM | B37: =O38 -> 4111 | E37: =179.8*1000 -> 179800 | H37: =O55 -> 228000 | K37: Net Income | L37: 17482 | M37: ='Income Statement'!$M$20 -> 69644 | N37: 18925 | O37: =N37+M37-L37 -> 71087 | Q37: 1Q24 | R37: 2Q24 | S37: 3Q24 | T37: 4Q24
A38: Annualized Stub | B38: =N38*4 -> 2764 | H38: =N55*2 -> 184000 | K38: Capex | L38: 786 | M38: =Calcs!$M$20 -> 4206 | N38: 691 | O38: =N38+M38-L38 -> 4111
K39: FCF | L39: =L36-L38 -> 25659 | M39: =M36-M38 -> 101601 | N39: =N36-N38 -> 26506 | O39: =O36-O38 -> 102448
A40: FCF (P/FCF)
A41: LTM | B41: =B29-B37 -> 102448 | C41: =$B$22/B41 -> 29.786106 | E41: =E29-E37 -> 1223500 | F41: =$E$13/E41 -> 21.004889 | H41: =H29-H37 -> 1061000 | I41: =$H$13/H41 -> 16.359521 | K41: Note: FCF = EBITDA - Capex
A42: Annualized Stub | B42: =B30-B38 -> 106024 | C42: =$B$22/B42 -> 28.781474 | H42: =H30-H38 -> 1090000 | I42: =$H$13/H42 -> 15.924268 | K42: Source: WDFC, 10Q, 11/30/24, pgs. 4 & 7
K43: WDFC, 10K, 8/31/24, F-4 & F-7
A44: Note: Prices as of market close (4/10/25). FCF = EBITDA - Capex.
A45: Source: SEC Filings and Yahoo! Finance | K45: CLX - LTM Calculations
L46: 1H | M46: Year End | N46: 1H
L47: 45291 | M47: 45473 | N47: 45657 | O47: LTM
K48: Sales | L48: =3376*1000 -> 3376000 | M48: =7093*1000 -> 7093000 | N48: =3448*1000 -> 3448000 | O48: =N48+M48-L48 -> 7165000
K49: EBT | L49: =165*1000 -> 165000 | M49: =398*1000 -> 398000 | N49: =414*1000 -> 414000 | O49: =N49+M49-L49 -> 647000
K50: Interest expense | L50: =47*1000 -> 47000 | M50: =90*1000 -> 90000 | N50: =43*1000 -> 43000 | O50: =N50+M50-L50 -> 86000
K51: Other income, net | L51: =(171+5)*1000 -> 176000 | M51: =(24+171+240)*1000 -> 435000 | N51: =(-45+118)*1000 -> 73000 | O51: =N51+M51-L51 -> 332000
K52: D&A | L52: =118*1000 -> 118000 | M52: =(235)*1000 -> 235000 | N52: =107*1000 -> 107000 | O52: =N52+M52-L52 -> 224000
K53: EBITDA | L53: =SUM(L49:L52) -> 506000 | M53: =SUM(M49:M52) -> 1158000 | N53: =SUM(N49:N52) -> 637000 | O53: =SUM(O49:O52) -> 1289000
K54: Net Income | L54: =115*1000 -> 115000 | M54: =280*1000 -> 280000 | N54: =292*1000 -> 292000 | O54: =N54+M54-L54 -> 457000
K55: Capex | L55: =76*1000 -> 76000 | M55: =212*1000 -> 212000 | N55: =92*1000 -> 92000 | O55: =N55+M55-L55 -> 228000
K56: FCF | L56: =L53-L55 -> 430000 | M56: =M53-M55 -> 946000 | N56: =N53-N55 -> 545000 | O56: =O53-O55 -> 1061000
K58: Source: CLX, 10K, 6/30/24, pgs. 26 & 30.
K59: CLX, 10Q, 12/31/24, pgs. 3 & 5.

Sheet Transaction Comps
A1: Transaction Comparables - WD-40
A3: Announced Date | B3: 39275 | C3: 40940 | D3: 40935
A4: Consideration | B4: CASH | C4: CASH | D4: Cash/stock
A5: Acquiror | B5: Hexion | C5: WLK | D5: EMN
A6: Target | B6: HUN | C6: GGC | D6: SOA
A7: Offer Price | B7: 28 | C7: 35 | D7: 27.65 | E7: Average
A8: LTM Sales | B8: =C92 -> 0.57989432 | C8: =C61 -> 0.37197359 | D8: =C31 -> 1.6232413 | E8: =AVERAGE(B8:D8) -> 0.85836974
A9: LTM EBITDA | B9: =C94 -> 10.120683 | C9: =C66 -> 7.2608037 | D9: =C36 -> 9.558633 | E9: =AVERAGE(B9:D9) -> 8.98004
A10: LTM FCF | B10: =C96 -> 17.266767 | C10: =C70 -> 7.0445518 | D10: =C40 -> 8.957729 | E10: =AVERAGE(B10:D10) -> 11.089683
A11: LTM Earnings | B11: =C98 -> 23.187353 | C11: =C72 -> 20.756406 | D11: =C42 -> 12.992126 | E11: =AVERAGE(B11:D11) -> 18.978628
A13: 1) Eastman Chemical's (EMN) buyout of Solutia (SOA) announced on 1/27/12
A15: Cash Offer | B15: 22 | E15: 40934 | F15: Stock
A16: Stock Offer | B16: =F17 -> 5.6544 | D16: EMN shs | E16: Close | F16: Offer
A17: Total Offer | B17: =SUM(B15:B16) -> 27.6544 | D17: 0.12 | E17: 47.12 | F17: =D17*E17 -> 5.6544
A18: Shs Out | B18: 122.41274
A19: Options | B19: =H22 -> 0.67570231 | D19: SOA Options Table
A20: FD Shares Out | B20: =SUM(B18:B19) -> 123.08844 | D20: # of | E20: Wghtd Avg | F20: Offer | G20: In the | H20: Shs in the
D21: Options Ex | E21: Ex Price | F21: Price | G21: Money | H21: Money
A22: FD Equity Value | B22: =B17*B20 -> 3403.937 | D22: 1.822256 | E22: 17.4 | F22: =B17 -> 27.6544 | G22: =IF($F$22>E22,"YES","NO") -> YES | H22: =IF(G22="YES",(($F$22-E22)/($F$22)*D22)) -> 0.67570231
A24: Debt | B24: 1337 | D24: Source: SOA, 10K, 12/31/11, pg. 79
A25: Cash | B25: 113
A26: Net Debt | B26: =B24-B25 -> 1224
A27: Preferreds/Converts | B27: 0
A28: Minority Interest | B28: 8
A29: TEV | B29: =B22+B26+B27+B28 -> 4635.937
A31: LTM Sales | B31: 2097 | C31: =B22/B31 -> 1.6232413
A33: Operating Income | B33: 404
A34: Other operating income, net | B34: -44
A35: Depreciation & Amortization | B35: 125
A36: LTM EBITDA | B36: =SUM(B33:B35) -> 485 | C36: =B29/B36 -> 9.558633
A38: LTM Capex | B38: 105
A40: LTM FCF | B40: =B36-B38 -> 380 | C40: =B22/B40 -> 8.957729
A42: LTM Earnings | B42: 262 | C42: =B22/B42 -> 12.992126
A44: Note: FCF defined as EBITDA less Capex.
A46: 2) Westlake Chemical's (WLK) failed buyout of Georgia Gulf (GGC) based on $35 offer on 2/1/12
A48: ($ and shares in millions, except per share data)
A50: Offer Price (2/1/12) | B50: 35 | E50: GGC Options Table
A51: Shs Out | B51: 34.240377
A52: Options | B52: =$I$57 -> 0.011843859 | E52: # of | F52: Wght Avg | G52: Offer Price | H52: In the | I52: Shares in
A53: FD Equity Value | B53: =B50*SUM(B51:B52) -> 1198.8277 | E53: options EX | F53: Ex Price | G53: 40940 | H53: Money? | I53: the money
A54: Debt | B54: =497.464+109.899 -> 607.363 | E54: 0.035705 | F54: 23.39 | G54: =B50 -> 35 | H54: =IF($G$54>F54,"YES","NO") -> YES | I54: =IF(H54="YES",((($G$54-F54)/$G$54)*E54),0) -> 0.011843859
A55: Cash | B55: 88.575 | E55: 0.033083 | F55: 212.42 | H55: =IF($G$54>F55,"YES","NO") -> NO | I55: =IF(H55="YES",((($G$54-F55)/$G$54)*E55),0) -> 0
A56: Net Debt | B56: =B54-B55 -> 518.788 | E56: 0.047113 | F56: 663.07 | H56: =IF($G$54>F56,"YES","NO") -> NO | I56: =IF(H56="YES",((($G$54-F56)/$G$54)*E56),0) -> 0
A57: Preferrreds/Converts | B57: 0 | H57: New shares | I57: =SUM(I54) -> 0.011843859
A58: Minority Interest | B58: 0
A59: TEV | B59: =B53+B56+B57+B58 -> 1717.6157 | E59: Source: GGC, 10K, 12/31/11, pg. 86
A61: LTM Sales | B61: 3222.884 | C61: =B53/B61 -> 0.37197359
A63: EBIT | B63: 124.599
A64: One-Time Items | B64: =8.318+3.271-1.15 -> 10.439
A65: D&A | B65: 101.522
A66: LTM EBITDA | B66: =B63+B64+B65 -> 236.56 | C66: =B59/B66 -> 7.2608037
A68: LTM Capex | B68: 66.382
A70: LTM FCF | B70: =B66-B68 -> 170.178 | C70: =B53/B70 -> 7.0445518
A72: LTM Earnings | B72: 57.757 | C72: =B53/B72 -> 20.756406
A74: Note: FCF defined as EBITDA less Capex.
A76: 3) Hexion's failed purchase of Huntsman (HUN) (deal proposed July 2007)
A78: ($ and shares in millions, except per share data)
A80: Offer Price (7/12/07) | B80: 28 | E80: HUN Options Table
A81: Shs Out | B81: 222.00508
A82: Options | B82: =I85 -> 0.42788036 | E82: # of | F82: Wght Avg | G82: Offer Price | H82: In the | I82: Shares in
A83: FD Equity Value | B83: =B80*SUM(B81:B82) -> 6228.123 | E83: options EX | F83: Ex Price | G83: 39275 | H83: Money? | I83: the money
A84: Debt | B84: =258.8+3524.6 -> 3783.4 | E84: 2.055 | F84: 22.17 | G84: =B80 -> 28 | H84: =IF($G$84>F84,"YES","NO") -> YES | I84: =IF(H84="YES",((($G$84-F84)/$G$84)*E84),0) -> 0.42788036
A85: Cash | B85: 167.5 | H85: New shares | I85: =SUM(I84) -> 0.42788036
A86: Net Debt | B86: =B84-B85 -> 3615.9
A87: Preferrreds/Converts | B87: 287.5 | E87: Source: HUN, 10Q, 6/30/07, pg. 34
A88: Minority Interest | B88: 23.9
A89: Associate Investment | B89: 215.9
A90: TEV | B90: =B83+B86+B87+B88-B89 -> 9939.523 | F90: 38898 | G90: 39082 | H90: 39263 | I90: LTM
E91: Sales | F91: 4688 | G91: 10623.6 | H91: 4804.5 | I91: =G91+H91-F91 -> 10740.1
A92: LTM Sales | B92: =I91 -> 10740.1 | C92: =B83/B92 -> 0.57989432 | E92: EBIT | F92: 444.7 | G92: 736.5 | H92: 242.9 | I92: =G92+H92-F92 -> 534.7
E93: One-Time | F93: =17.1-94.3 -> -77.2 | G93: =20-127.7 -> -107.7 | H93: =24.4+5.3 -> 29.7 | I93: =G93+H93-F93 -> -0.8
A94: LTM EBITDA | B94: =I95 -> 982.1 | C94: =B90/B94 -> 10.120683 | E94: D&A | F94: 234.5 | G94: 465.7 | H94: 217 | I94: =G94+H94-F94 -> 448.2
E95: EBITDA | F95: =SUM(F92:F94) -> 602 | G95: =SUM(G92:G94) -> 1094.5 | H95: =SUM(H92:H94) -> 489.6 | I95: =G95+H95-F95 -> 982.1
A96: LTM FCF | B96: =I97 -> 360.7 | C96: =B83/B96 -> 17.266767 | E96: Capex | F96: 211.3 | G96: 549.9 | H96: 282.8 | I96: =G96+H96-F96 -> 621.4
E97: FCF | F97: =F95-F96 -> 390.7 | G97: =G95-G96 -> 544.6 | H97: =H95-H96 -> 206.8 | I97: =G97+H97-F97 -> 360.7
A98: LTM Earnings | B98: =I98 -> 268.6 | C98: =B83/B98 -> 23.187353 | E98: Net Income | F98: 226.6 | G98: 393.6 | H98: 101.6 | I98: =G98+H98-F98 -> 268.6
A100: Note: FCF defined as EBITDA less Capex.

Sheet AVP
A1: WD-40 Analysis at Various Prices (AVP)
A3: WDFC Price | B3: ='Trading Comps'!B7 -> 221.35
B5: Analysis at Various Prices - Trading Comps - Sales
A6: P/S | B6: 2 | C6: =B6+0.5 -> 2.5 | D6: =C6+0.5 -> 3 | E6: =D6+0.5 -> 3.5 | F6: =E6+0.5 -> 4 | G6: =F6+0.5 -> 4.5 | H6: =G6+0.5 -> 5 | I6: =H6+0.5 -> 5.5
A7: WDFC LTM Sales | B7: ='Trading Comps'!$B$25 -> 603636 | C7: =B7 -> 603636 | D7: =C7 -> 603636 | E7: =D7 -> 603636 | F7: =E7 -> 603636 | G7: =F7 -> 603636 | H7: =G7 -> 603636 | I7: =H7 -> 603636
A8: Equity Value | B8: =B6*B7 -> 1207272 | C8: =C6*C7 -> 1509090 | D8: =D6*D7 -> 1810908 | E8: =E6*E7 -> 2112726 | F8: =F6*F7 -> 2414544 | G8: =G6*G7 -> 2716362 | H8: =H6*H7 -> 3018180 | I8: =I6*I7 -> 3319998
A9: FD Shs Out | B9: ='Trading Comps'!$B$11 -> 13546.239 | C9: =B9 -> 13546.239 | D9: =C9 -> 13546.239 | E9: =D9 -> 13546.239 | F9: =E9 -> 13546.239 | G9: =F9 -> 13546.239 | H9: =G9 -> 13546.239 | I9: =H9 -> 13546.239
A10: Value per share | B10: =B8/B9 -> 89.122302 | C10: =C8/C9 -> 111.40288 | D10: =D8/D9 -> 133.68345 | E10: =E8/E9 -> 155.96403 | F10: =F8/F9 -> 178.2446 | G10: =G8/G9 -> 200.52518 | H10: =H8/H9 -> 222.80575 | I10: =I8/I9 -> 245.08633
B12: Analysis at Various Prices - Trading Comps - EBITDA
A13: TEV/EBITDA | B13: 15 | C13: =B13+1.5 -> 16.5 | D13: =C13+1.5 -> 18 | E13: =D13+1.5 -> 19.5 | F13: =E13+1.5 -> 21 | G13: =F13+1.5 -> 22.5 | H13: =G13+1.5 -> 24 | I13: =H13+1.5 -> 25.5 | J13: =I13+1.5 -> 27 | ... L13: =K13+1.5 -> 30
A14: WDFC LTM EBITDA | B14: ='Trading Comps'!$B$29 -> 106559 | C14: =B14 -> 106559 | D14: =C14 -> 106559 | E14: =D14 -> 106559 | F14: =E14 -> 106559 | G14: =F14 -> 106559 | H14: =G14 -> 106559 | I14: =H14 -> 106559 | J14: =I14 -> 106559 | ... L14: =K14 -> 106559
A15: TEV | B15: =B13*B14 -> 1598385 | C15: =C13*C14 -> 1758223.5 | D15: =D13*D14 -> 1918062 | E15: =E13*E14 -> 2077900.5 | F15: =F13*F14 -> 2237739 | G15: =G13*G14 -> 2397577.5 | H15: =H13*H14 -> 2557416 | I15: =I13*I14 -> 2717254.5 | ... L15: =L13*L14 -> 3196770
A16: Net Debt | B16: ='Trading Comps'!$B$17 -> 53067 | C16: =B16 -> 53067 | D16: =C16 -> 53067 | E16: =D16 -> 53067 | F16: =E16 -> 53067 | G16: =F16 -> 53067 | H16: =G16 -> 53067 | I16: =H16 -> 53067 | J16: =I16 -> 53067 | ... L16: =K16 -> 53067
A17: Equity Value | B17: =B15-B16 -> 1545318 | C17: =C15-C16 -> 1705156.5 | D17: =D15-D16 -> 1864995 | E17: =E15-E16 -> 2024833.5 | F17: =F15-F16 -> 2184672 | G17: =G15-G16 -> 2344510.5 | H17: =H15-H16 -> 2504349 | I17: =I15-I16 -> 2664187.5 | ... L17: =L15-L16 -> 3143703
A18: FD Shs Out | B18: ='Trading Comps'!$B$11 -> 13546.239 | C18: =B18 -> 13546.239 | D18: =C18 -> 13546.239 | E18: =D18 -> 13546.239 | F18: =E18 -> 13546.239 | G18: =F18 -> 13546.239 | H18: =G18 -> 13546.239 | I18: =H18 -> 13546.239 | J18: =I18 -> 13546.239 | ... L18: =K18 -> 13546.239
A19: Value per share | B19: =B17/B18 -> 114.07727 | C19: =C17/C18 -> 125.87675 | D19: =D17/D18 -> 137.67622 | E19: =E17/E18 -> 149.4757 | F19: =F17/F18 -> 161.27517 | G19: =G17/G18 -> 173.07464 | H19: =H17/H18 -> 184.87412 | I19: =I17/I18 -> 196.67359 | ... L19: =L17/L18 -> 232.07202
B21: Analysis at Various Prices - Transaction Comps - Sales
A22: P/S | B22: 0.3 | C22: =B22+0.2 -> 0.5 | D22: =C22+0.2 -> 0.7 | E22: =D22+0.2 -> 0.9 | F22: =E22+0.2 -> 1.1 | G22: =F22+0.2 -> 1.3 | H22: =G22+0.2 -> 1.5 | I22: =H22+0.2 -> 1.7
A23: WDFC LTM Sales | B23: ='Trading Comps'!$B$25 -> 603636 | C23: =B23 -> 603636 | D23: =C23 -> 603636 | E23: =D23 -> 603636 | F23: =E23 -> 603636 | G23: =F23 -> 603636 | H23: =G23 -> 603636 | I23: =H23 -> 603636
A24: Equity Value | B24: =B22*B23 -> 181090.8 | C24: =C22*C23 -> 301818 | D24: =D22*D23 -> 422545.2 | E24: =E22*E23 -> 543272.4 | F24: =F22*F23 -> 663999.6 | G24: =G22*G23 -> 784726.8 | H24: =H22*H23 -> 905454 | I24: =I22*I23 -> 1026181.2
A25: FD Shs Out | B25: ='Trading Comps'!$B$11 -> 13546.239 | C25: =B25 -> 13546.239 | D25: =C25 -> 13546.239 | E25: =D25 -> 13546.239 | F25: =E25 -> 13546.239 | G25: =F25 -> 13546.239 | H25: =G25 -> 13546.239 | I25: =H25 -> 13546.239
A26: Value per share | B26: =B24/B25 -> 13.368345 | C26: =C24/C25 -> 22.280575 | D26: =D24/D25 -> 31.192806 | E26: =E24/E25 -> 40.105036 | F26: =F24/F25 -> 49.017266 | G26: =G24/G25 -> 57.929496 | H26: =H24/H25 -> 66.841726 | I26: =I24/I25 -> 75.753957
B28: Analysis at Various Prices - Transaction Comps - EBITDA
A29: TEV/EBITDA | B29: 7.25 | C29: =B29+0.25 -> 7.5 | D29: =C29+0.25 -> 7.75 | E29: =D29+0.25 -> 8 | F29: =E29+0.25 -> 8.25 | G29: =F29+0.25 -> 8.5 | H29: =G29+0.25 -> 8.75 | I29: =H29+0.25 -> 9 | J29: =I29+0.25 -> 9.25 | ... O29: =N29+0.25 -> 10.5
A30: WDFC LTM EBITDA | B30: ='Trading Comps'!$B$29 -> 106559 | C30: =B30 -> 106559 | D30: =C30 -> 106559 | E30: =D30 -> 106559 | F30: =E30 -> 106559 | G30: =F30 -> 106559 | H30: =G30 -> 106559 | I30: =H30 -> 106559 | J30: =I30 -> 106559 | ... O30: =N30 -> 106559
A31: TEV | B31: =B29*B30 -> 772552.75 | C31: =C29*C30 -> 799192.5 | D31: =D29*D30 -> 825832.25 | E31: =E29*E30 -> 852472 | F31: =F29*F30 -> 879111.75 | G31: =G29*G30 -> 905751.5 | H31: =H29*H30 -> 932391.25 | I31: =I29*I30 -> 959031 | ... O31: =O29*O30 -> 1118869.5
A32: Net Debt | B32: ='Trading Comps'!$B$17 -> 53067 | C32: =B32 -> 53067 | D32: =C32 -> 53067 | E32: =D32 -> 53067 | F32: =E32 -> 53067 | G32: =F32 -> 53067 | H32: =G32 -> 53067 | I32: =H32 -> 53067 | J32: =I32 -> 53067 | ... O32: =N32 -> 53067
A33: Equity Value | B33: =B31-B32 -> 719485.75 | C33: =C31-C32 -> 746125.5 | D33: =D31-D32 -> 772765.25 | E33: =E31-E32 -> 799405 | F33: =F31-F32 -> 826044.75 | G33: =G31-G32 -> 852684.5 | H33: =H31-H32 -> 879324.25 | I33: =I31-I32 -> 905964 | ... O33: =O31-O32 -> 1065802.5
A34: FD Shs Out | B34: ='Trading Comps'!$B$11 -> 13546.239 | C34: =B34 -> 13546.239 | D34: =C34 -> 13546.239 | E34: =D34 -> 13546.239 | F34: =E34 -> 13546.239 | G34: =F34 -> 13546.239 | H34: =G34 -> 13546.239 | I34: =H34 -> 13546.239 | J34: =I34 -> 13546.239 | ... O34: =N34 -> 13546.239
A35: Value per share | B35: =B33/B34 -> 53.113322 | C35: =C33/C34 -> 55.079901 | D35: =D33/D34 -> 57.04648 | E35: =E33/E34 -> 59.013059 | F35: =F33/F34 -> 60.979638 | G35: =G33/G34 -> 62.946217 | H35: =H33/H34 -> 64.912796 | I35: =I33/I34 -> 66.879375 | ... O35: =O33/O34 -> 78.67885

Sheet Summary
A1: WD-40 - Summary
A2: ($ in thousands)
C4: Historical | F4: Projected
B5: 44439 | C5: 44804 | D5: 45169 | E5: 45535 | F5: 45900 | G5: 46265 | H5: 46630 | I5: 46996 | J5: 47361
A6: Size
A7: Sales | B7: ='Income Statement'!J6 -> 488109 | C7: ='Income Statement'!K6 -> 518820 | D7: ='Income Statement'!L6 -> 537255 | E7: ='Income Statement'!M6 -> 590557 | F7: ='Income Statement'!N6 -> 631895.99 | G7: ='Income Statement'!O6 -> 676128.71 | H7: ='Income Statement'!P6 -> 723457.72 | I7: ='Income Statement'!Q6 -> 774099.76 | J7: ='Income Statement'!R6 -> 828286.74
A8: COGS | B8: ='Income Statement'!J7 -> 220991.07 | C8: ='Income Statement'!K7 -> 259556.96 | D8: ='Income Statement'!L7 -> 258535.21 | E8: ='Income Statement'!M7 -> 270323.33 | F8: ='Income Statement'!N7 -> 293831.64 | G8: ='Income Statement'!O7 -> 314399.85 | H8: ='Income Statement'!P7 -> 336407.84 | I8: ='Income Statement'!Q7 -> 359956.39 | J8: ='Income Statement'!R7 -> 385153.34
A9: Gross Profit | B9: =B7-B8 -> 267117.93 | C9: =C7-C8 -> 259263.04 | D9: =D7-D8 -> 278719.79 | E9: =E7-E8 -> 320233.67 | F9: =F7-F8 -> 338064.35 | G9: =G7-G8 -> 361728.86 | H9: =H7-H8 -> 387049.88 | I9: =I7-I8 -> 414143.37 | J9: =J7-J8 -> 443133.41
A10: EBITDA | B10: ='Income Statement'!J11 -> 95860 | C10: ='Income Statement'!K11 -> 95624 | D10: ='Income Statement'!L11 -> 97875 | E10: ='Income Statement'!M11 -> 105807 | F10: ='Income Statement'!N11 -> 120060.24 | G10: ='Income Statement'!O11 -> 128464.45 | H10: ='Income Statement'!P11 -> 137456.97 | I10: ='Income Statement'!Q11 -> 147078.95 | J10: ='Income Statement'!R11 -> 157374.48
A11: EBIT | B11: ='Income Statement'!J14 -> 88841 | C11: ='Income Statement'!K14 -> 87330 | D11: ='Income Statement'!L14 -> 89724 | E11: ='Income Statement'!M14 -> 96351 | F11: ='Income Statement'!N14 -> 109949.9 | G11: ='Income Statement'!O14 -> 117646.4 | H11: ='Income Statement'!P14 -> 125881.64 | I11: ='Income Statement'!Q14 -> 134693.36 | J11: ='Income Statement'!R14 -> 145167.63
A12: Interest Expense | B12: =-'Income Statement'!J16 -> 2395 | C12: =-'Income Statement'!K16 -> 2742 | D12: =-'Income Statement'!L16 -> 5614 | E12: =-'Income Statement'!M16 -> 4287 | F12: =-'Income Statement'!N16 -> 3440.9136 | G12: =-'Income Statement'!O16 -> 3057.4928 | H12: =-'Income Statement'!P16 -> 2674.072 | I12: =-'Income Statement'!Q16 -> 1965.6512 | J12: =-'Income Statement'!R16 -> 1257.2304
A13: Taxes | B13: ='Income Statement'!J19 -> 16270 | C13: ='Income Statement'!K19 -> 16779 | D13: ='Income Statement'!L19 -> 19170 | E13: ='Income Statement'!M19 -> 21864 | F13: ='Income Statement'!N19 -> 25108.069 | G13: ='Income Statement'!O19 -> 27191.666 | H13: ='Income Statement'!P19 -> 29436.653 | I13: ='Income Statement'!Q19 -> 31775.196 | J13: ='Income Statement'!R19 -> 34522.091
A14: Net Income | B14: ='Income Statement'!J20 -> 70229 | C14: ='Income Statement'!K20 -> 67329 | D14: ='Income Statement'!L20 -> 65993 | E14: ='Income Statement'!M20 -> 69644 | F14: ='Income Statement'!N20 -> 84057.45 | G14: ='Income Statement'!O20 -> 91032.969 | H14: ='Income Statement'!P20 -> 98548.795 | I14: ='Income Statement'!Q20 -> 106377.83 | J14: ='Income Statement'!R20 -> 115573.96
A15: OCF | B15: =WACC!J18 -> 84714 | C15: =WACC!K18 -> 2604 | D15: =WACC!L18 -> 98391 | E15: =WACC!M18 -> 92034 | F15: ='Cash Flow Statement'!F11 -> 91427.105 | G15: ='Cash Flow Statement'!G11 -> 93686.111 | H15: ='Cash Flow Statement'!H11 -> 101387.66 | I15: ='Cash Flow Statement'!I11 -> 109415.41 | J15: ='Cash Flow Statement'!J11 -> 117778.43
A16: Capex | B16: =Calcs!J20 -> 15059 | C16: =Calcs!K20 -> 8303 | D16: =Calcs!L20 -> 6871 | E16: =Calcs!M20 -> 4206 | F16: =Calcs!N20 -> 12637.92 | G16: =Calcs!O20 -> 13522.574 | H16: =Calcs!P20 -> 14469.154 | I16: =Calcs!Q20 -> 15481.995 | J16: =Calcs!R20 -> 16565.735
A17: Dividends | B17: =Calcs!J7 -> 38225 | C17: =Calcs!K7 -> 41988 | D17: =Calcs!L7 -> 44581 | E17: =Calcs!M7 -> 47201 | F17: =Calcs!N7 -> 47072.172 | G17: =Calcs!O7 -> 50978.463 | H17: =Calcs!P7 -> 55187.325 | I17: =Calcs!Q7 -> 59571.584 | J17: =Calcs!R7 -> 64721.416
A18: Receivables | B18: ='Balance Sheet PROJECTED'!J8 -> 89558 | C18: ='Balance Sheet PROJECTED'!K8 -> 89930 | D18: ='Balance Sheet PROJECTED'!L8 -> 98039 | E18: ='Balance Sheet PROJECTED'!M8 -> 117493 | F18: ='Balance Sheet PROJECTED'!N8 -> 126379.2 | G18: ='Balance Sheet PROJECTED'!O8 -> 135225.74 | H18: ='Balance Sheet PROJECTED'!P8 -> 144691.54 | I18: ='Balance Sheet PROJECTED'!Q8 -> 154819.95 | J18: ='Balance Sheet PROJECTED'!R8 -> 165657.35
A19: Inventories | B19: ='Balance Sheet PROJECTED'!J9 -> 55752 | C19: ='Balance Sheet PROJECTED'!K9 -> 104101 | D19: ='Balance Sheet PROJECTED'!L9 -> 86522 | E19: ='Balance Sheet PROJECTED'!M9 -> 79088 | F19: ='Balance Sheet PROJECTED'!N9 -> 73457.909 | G19: ='Balance Sheet PROJECTED'!O9 -> 78599.962 | H19: ='Balance Sheet PROJECTED'!P9 -> 84101.96 | I19: ='Balance Sheet PROJECTED'!Q9 -> 89989.097 | J19: ='Balance Sheet PROJECTED'!R9 -> 96288.334
A20: Accounts Payable | B20: ='Balance Sheet PROJECTED'!J22 -> 33499 | C20: ='Balance Sheet PROJECTED'!K22 -> 32852 | D20: ='Balance Sheet PROJECTED'!L22 -> 30826 | E20: ='Balance Sheet PROJECTED'!M22 -> 35960 | F20: ='Balance Sheet PROJECTED'!N22 -> 36435.123 | G20: ='Balance Sheet PROJECTED'!O22 -> 38985.581 | H20: ='Balance Sheet PROJECTED'!P22 -> 41714.572 | I20: ='Balance Sheet PROJECTED'!Q22 -> 44634.592 | J20: ='Balance Sheet PROJECTED'!R22 -> 47759.014
A21: Assets | B21: ='Balance Sheet PROJECTED'!J19 -> 430203 | C21: ='Balance Sheet PROJECTED'!K19 -> 434295 | D21: ='Balance Sheet PROJECTED'!L19 -> 437966 | E21: ='Balance Sheet PROJECTED'!M19 -> 449039 | F21: ='Balance Sheet PROJECTED'!N19 -> 474748.93 | G21: ='Balance Sheet PROJECTED'!O19 -> 516206.15 | H21: ='Balance Sheet PROJECTED'!P19 -> 561514.24 | I21: ='Balance Sheet PROJECTED'!Q19 -> 584849.06 | J21: ='Balance Sheet PROJECTED'!R19 -> 638852.89
A22: Debt | B22: ='Balance Sheet PROJECTED'!J50 -> 115740 | C22: ='Balance Sheet PROJECTED'!K50 -> 146312 | D22: ='Balance Sheet PROJECTED'!L50 -> 120543 | E22: ='Balance Sheet PROJECTED'!M50 -> 94636 | F22: ='Balance Sheet PROJECTED'!N50 -> 88268.8 | G22: ='Balance Sheet PROJECTED'!O50 -> 81901.6 | H22: ='Balance Sheet PROJECTED'!P50 -> 75534.4 | I22: ='Balance Sheet PROJECTED'!Q50 -> 43167.2 | J22: ='Balance Sheet PROJECTED'!R50 -> 36800
A23: Equity | B23: ='Balance Sheet PROJECTED'!J45 -> 200382 | C23: ='Balance Sheet PROJECTED'!K45 -> 188624 | D23: ='Balance Sheet PROJECTED'!L45 -> 210178 | E23: ='Balance Sheet PROJECTED'!M45 -> 230526 | F23: ='Balance Sheet PROJECTED'!N45 -> 260511.28 | G23: ='Balance Sheet PROJECTED'!O45 -> 300565.78 | H23: ='Balance Sheet PROJECTED'!P45 -> 343927.25 | I23: ='Balance Sheet PROJECTED'!Q45 -> 390733.5 | J23: ='Balance Sheet PROJECTED'!R45 -> 441586.04
A24: Total Capital | B24: =SUM(B22:B23) -> 316122 | C24: =SUM(C22:C23) -> 334936 | D24: =SUM(D22:D23) -> 330721 | E24: =SUM(E22:E23) -> 325162 | F24: =SUM(F22:F23) -> 348780.08 | G24: =SUM(G22:G23) -> 382467.38 | H24: =SUM(H22:H23) -> 419461.65 | I24: =SUM(I22:I23) -> 433900.7 | J24: =SUM(J22:J23) -> 478386.04
A26: Profitability
A27: Sales growth | C27: =C7/B7-1 -> 0.062918324 | D27: =D7/C7-1 -> 0.035532555 | E27: =E7/D7-1 -> 0.099211734 | F27: =F7/E7-1 -> 0.07 | G27: =G7/F7-1 -> 0.07 | H27: =H7/G7-1 -> 0.07 | I27: =I7/H7-1 -> 0.07 | J27: =J7/I7-1 -> 0.07
A28: Gross margin | B28: =B9/B$7 -> 0.54725057 | C28: =C9/C$7 -> 0.49971673 | D28: =D9/D$7 -> 0.51878492 | E28: =E9/E$7 -> 0.542257 | F28: =F9/F$7 -> 0.535 | G28: =G9/G$7 -> 0.535 | H28: =H9/H$7 -> 0.535 | I28: =I9/I$7 -> 0.535 | J28: =J9/J$7 -> 0.535
A29: EBITDA margin | B29: =B10/B$7 -> 0.19639056 | C29: =C10/C$7 -> 0.18431055 | D29: =D10/D$7 -> 0.18217606 | E29: =E10/E$7 -> 0.17916475 | F29: =F10/F$7 -> 0.19 | G29: =G10/G$7 -> 0.19 | H29: =H10/H$7 -> 0.19 | I29: =I10/I$7 -> 0.19 | J29: =J10/J$7 -> 0.19
A30: EBIT margin | B30: =B11/B$7 -> 0.18201058 | C30: =C11/C$7 -> 0.16832427 | D30: =D11/D$7 -> 0.1670045 | E30: =E11/E$7 -> 0.16315275 | F30: =F11/F$7 -> 0.174 | G30: =G11/G$7 -> 0.174 | H30: =H11/H$7 -> 0.174 | I30: =I11/I$7 -> 0.174 | J30: =J11/J$7 -> 0.17526253
A31: Net Income | B31: =B14 -> 70229 | C31: =C14 -> 67329 | D31: =D14 -> 65993 | E31: =E14 -> 69644 | F31: =F14 -> 84057.45 | G31: =G14 -> 91032.969 | H31: =H14 -> 98548.795 | I31: =I14 -> 106377.83 | J31: =J14 -> 115573.96
A32: Revenue | B32: =B7 -> 488109 | C32: =C7 -> 518820 | D32: =D7 -> 537255 | E32: =E7 -> 590557 | F32: =F7 -> 631895.99 | G32: =G7 -> 676128.71 | H32: =H7 -> 723457.72 | I32: =I7 -> 774099.76 | J32: =J7 -> 828286.74
A33: Profit margin | B33: =B31/B32 -> 0.14387975 | C33: =C31/C32 -> 0.12977333 | D33: =D31/D32 -> 0.12283366 | E33: =E31/E32 -> 0.11792934 | F33: =F31/F32 -> 0.13302419 | G33: =G31/G32 -> 0.13463852 | H33: =H31/H32 -> 0.13621915 | I33: =I31/I32 -> 0.13742134 | J33: =J31/J32 -> 0.13953375
A34: Revenue | B34: =B7 -> 488109 | C34: =C7 -> 518820 | D34: =D7 -> 537255 | E34: =E7 -> 590557 | F34: =F7 -> 631895.99 | G34: =G7 -> 676128.71 | H34: =H7 -> 723457.72 | I34: =I7 -> 774099.76 | J34: =J7 -> 828286.74
A35: Total Assets (AVG) | C35: =AVERAGE(B21:C21) -> 432249 | D35: =AVERAGE(C21:D21) -> 436130.5 | E35: =AVERAGE(D21:E21) -> 443502.5 | F35: =AVERAGE(E21:F21) -> 461893.96 | G35: =AVERAGE(F21:G21) -> 495477.54 | H35: =AVERAGE(G21:H21) -> 538860.2 | I35: =AVERAGE(H21:I21) -> 573181.65 | J35: =AVERAGE(I21:J21) -> 611850.98
A36: Asset Utilization | C36: =C34/C35 -> 1.2002804 | D36: =D34/D35 -> 1.2318675 | E36: =E34/E35 -> 1.3315754 | F36: =F34/F35 -> 1.3680542 | G36: =G34/G35 -> 1.3646001 | H36: =H34/H35 -> 1.3425703 | I36: =I34/I35 -> 1.3505313 | J36: =J34/J35 -> 1.3537394
A37: ROA | C37: =C33*C36 -> 0.15576439 | D37: =D33*D36 -> 0.1513148 | E37: =E33*E36 -> 0.15703181 | F37: =F33*F36 -> 0.1819843 | G37: =G33*G36 -> 0.18372774 | H37: =H33*H36 -> 0.18288379 | I37: =I33*I36 -> 0.18559183 | J37: =J33*J36 -> 0.18889233
A38: Total Assets (AVG) | C38: =AVERAGE(B21:C21) -> 432249 | D38: =AVERAGE(C21:D21) -> 436130.5 | E38: =AVERAGE(D21:E21) -> 443502.5 | F38: =AVERAGE(E21:F21) -> 461893.96 | G38: =AVERAGE(F21:G21) -> 495477.54 | H38: =AVERAGE(G21:H21) -> 538860.2 | I38: =AVERAGE(H21:I21) -> 573181.65 | J38: =AVERAGE(I21:J21) -> 611850.98
A39: Common Equity (AVG) | C39: =AVERAGE(B23:C23) -> 194503 | D39: =AVERAGE(C23:D23) -> 199401 | E39: =AVERAGE(D23:E23) -> 220352 | F39: =AVERAGE(E23:F23) -> 245518.64 | G39: =AVERAGE(F23:G23) -> 280538.53 | H39: =AVERAGE(G23:H23) -> 322246.52 | I39: =AVERAGE(H23:I23) -> 367330.38 | J39: =AVERAGE(I23:J23) -> 416159.77
A40: Leverage | C40: =C38/C39 -> 2.2223256 | D40: =D38/D39 -> 2.1872032 | E40: =E38/E39 -> 2.0127001 | F40: =F38/F39 -> 1.881299 | G40: =G38/G39 -> 1.7661657 | H40: =H38/H39 -> 1.6721987 | I40: =I38/I39 -> 1.5603982 | J40: =J38/J39 -> 1.470231
A41: ROE | C41: =C37*C40 -> 0.34615919 | D41: =D37*D40 -> 0.33095621 | E41: =E37*E40 -> 0.31605794 | F41: =F37*F40 -> 0.34236688 | G41: =G37*G40 -> 0.32449364 | H41: =H37*H40 -> 0.30581803 | I41: =I37*I40 -> 0.28959715 | J41: =J37*J40 -> 0.27771535
A42: EBIT | B42: =B11 -> 88841 | C42: =C11 -> 87330 | D42: =D11 -> 89724 | E42: =E11 -> 96351 | F42: =F11 -> 109949.9 | G42: =G11 -> 117646.4 | H42: =H11 -> 125881.64 | I42: =I11 -> 134693.36 | J42: =J11 -> 145167.63
A43: Taxes | B43: =B13 -> 16270 | C43: =C13 -> 16779 | D43: =D13 -> 19170 | E43: =E13 -> 21864 | F43: =F13 -> 25108.069 | G43: =G13 -> 27191.666 | H43: =H13 -> 29436.653 | I43: =I13 -> 31775.196 | J43: =J13 -> 34522.091
A44: NOPAT | B44: =B42-B43 -> 72571 | C44: =C42-C43 -> 70551 | D44: =D42-D43 -> 70554 | E44: =E42-E43 -> 74487 | F44: =F42-F43 -> 84841.833 | G44: =G42-G43 -> 90454.729 | H44: =H42-H43 -> 96444.99 | I44: =I42-I43 -> 102918.16 | J44: =J42-J43 -> 110645.54
A45: Total Capital (AVG) | C45: =AVERAGE(B24:C24) -> 325529 | D45: =AVERAGE(C24:D24) -> 332828.5 | E45: =AVERAGE(D24:E24) -> 327941.5 | F45: =AVERAGE(E24:F24) -> 336971.04 | G45: =AVERAGE(F24:G24) -> 365623.73 | H45: =AVERAGE(G24:H24) -> 400964.52 | I45: =AVERAGE(H24:I24) -> 426681.18 | J45: =AVERAGE(I24:J24) -> 456143.37
A46: ROIC | C46: =C44/C45 -> 0.21672723 | D46: =D44/D45 -> 0.21198305 | E46: =E44/E45 -> 0.22713502 | F46: =F44/F45 -> 0.25177782 | G46: =G44/G45 -> 0.24739841 | H46: =H44/H45 -> 0.24053248 | I46: =I44/I45 -> 0.24120624 | J46: =J44/J45 -> 0.24256746
A47: Dividends | B47: =B17 -> 38225 | C47: =C17 -> 41988 | D47: =D17 -> 44581 | E47: =E17 -> 47201 | F47: =F17 -> 47072.172 | G47: =G17 -> 50978.463 | H47: =H17 -> 55187.325 | I47: =I17 -> 59571.584 | J47: =J17 -> 64721.416
A48: Net Income | B48: =B14 -> 70229 | C48: =C14 -> 67329 | D48: =D14 -> 65993 | E48: =E14 -> 69644 | F48: =F14 -> 84057.45 | G48: =G14 -> 91032.969 | H48: =H14 -> 98548.795 | I48: =I14 -> 106377.83 | J48: =J14 -> 115573.96
A49: Payout ratio | B49: =B47/B48 -> 0.54429082 | C49: =C47/C48 -> 0.62362429 | D49: =D47/D48 -> 0.67554135 | E49: =E47/E48 -> 0.67774683 | F49: =F47/F48 -> 0.56 | G49: =G47/G48 -> 0.56 | H49: =H47/H48 -> 0.56 | I49: =I47/I48 -> 0.56 | J49: =J47/J48 -> 0.56
A51: Leverage & Coverage
A52: Debt to Total Capital | B52: =B22/B24 -> 0.36612447 | C52: =C22/C24 -> 0.43683569 | D52: =D22/D24 -> 0.36448547 | E52: =E22/E24 -> 0.29104262 | F52: =F22/F24 -> 0.25307868 | G52: =G22/G24 -> 0.21414009 | H52: =H22/H24 -> 0.18007462 | I52: =I22/I24 -> 0.099486357 | J52: =J22/J24 -> 0.076925322
A53: Debt to EBITDA | B53: =B22/B10 -> 1.2073858 | C53: =C22/C10 -> 1.5300761 | D53: =D22/D10 -> 1.2316015 | E53: =E22/E10 -> 0.89442097 | F53: =F22/F10 -> 0.73520427 | G53: =G22/G10 -> 0.63754289 | H53: =H22/H10 -> 0.54951307 | I53: =I22/I10 -> 0.29349678 | J53: =J22/J10 -> 0.23383715
A54: FCF / Interest | B54: =(B10-B16)/B12 -> 33.73737 | C54: =(C10-C16)/C12 -> 31.845733 | D54: =(D10-D16)/D12 -> 16.210189 | E54: =(E10-E16)/E12 -> 23.69979 | F54: =(F10-F16)/F12 -> 31.219127 | G54: =(G10-G16)/G12 -> 37.593508 | H54: =(H10-H16)/H12 -> 45.992708 | I54: =(I10-I16)/I12 -> 66.948276 | J54: =(J10-J16)/J12 -> 111.99916
A56: Working Capital
A57: Capex Intensity | B57: =B16/B7 -> 0.030851715 | C57: =C16/C7 -> 0.016003624 | D57: =D16/D7 -> 0.012789085 | E57: =E16/E7 -> 0.0071220898 | F57: =F16/F7 -> 0.02 | G57: =G16/G7 -> 0.02 | H57: =H16/H7 -> 0.02 | I57: =I16/I7 -> 0.02 | J57: =J16/J7 -> 0.02
A58: Revenues | B58: =B7 -> 488109 | C58: =C7 -> 518820 | D58: =D7 -> 537255 | E58: =E7 -> 590557 | F58: =F7 -> 631895.99 | G58: =G7 -> 676128.71 | H58: =H7 -> 723457.72 | I58: =I7 -> 774099.76 | J58: =J7 -> 828286.74
A59: Revenues per day | B59: =B58/365 -> 1337.2849 | C59: =C58/365 -> 1421.4247 | D59: =D58/365 -> 1471.9315 | E59: =E58/365 -> 1617.9644 | F59: =F58/365 -> 1731.2219 | G59: =G58/365 -> 1852.4074 | H59: =H58/365 -> 1982.0759 | I59: =I58/365 -> 2120.8213 | J59: =J58/365 -> 2269.2787
A60: Receivables (AVG) | C60: =AVERAGE(B18:C18) -> 89744 | D60: =AVERAGE(C18:D18) -> 93984.5 | E60: =AVERAGE(D18:E18) -> 107766 | F60: =AVERAGE(E18:F18) -> 121936.1 | G60: =AVERAGE(F18:G18) -> 130802.47 | H60: =AVERAGE(G18:H18) -> 139958.64 | I60: =AVERAGE(H18:I18) -> 149755.75 | J60: =AVERAGE(I18:J18) -> 160238.65
A61: Days Sales Outstanding | C61: =C60/C59 -> 63.136656 | D61: =D60/D59 -> 63.851137 | E61: =E60/E59 -> 66.605916 | F61: =F60/F59 -> 70.433547 | G61: =G60/G59 -> 70.61215 | H61: =H60/H59 -> 70.61215 | I61: =I60/I59 -> 70.61215 | J61: =J60/J59 -> 70.61215
A62: COGS | B62: =B8 -> 220991.07 | C62: =C8 -> 259556.96 | D62: =D8 -> 258535.21 | E62: =E8 -> 270323.33 | F62: =F8 -> 293831.64 | G62: =G8 -> 314399.85 | H62: =H8 -> 336407.84 | I62: =I8 -> 359956.39 | J62: =J8 -> 385153.34
A63: COGS per day | B63: =B62/365 -> 605.45499 | C63: =C62/365 -> 711.11497 | D63: =D62/365 -> 708.31564 | E63: =E62/365 -> 740.61188 | F63: =F62/365 -> 805.01818 | G63: =G62/365 -> 861.36945 | H63: =H62/365 -> 921.66531 | I63: =I62/365 -> 986.18189 | J63: =J62/365 -> 1055.2146
A64: Inventories (AVG) | C64: =AVERAGE(B19:C19) -> 79926.5 | D64: =AVERAGE(C19:D19) -> 95311.5 | E64: =AVERAGE(D19:E19) -> 82805 | F64: =AVERAGE(E19:F19) -> 76272.954 | G64: =AVERAGE(F19:G19) -> 76028.936 | H64: =AVERAGE(G19:H19) -> 81350.961 | I64: =AVERAGE(H19:I19) -> 87045.528 | J64: =AVERAGE(I19:J19) -> 93138.715
A65: Days Inventory Outstanding | C65: =C64/C63 -> 112.39603 | D65: =D64/D63 -> 134.56077 | E65: =E64/E63 -> 111.8062 | F65: =F64/F63 -> 94.746872 | G65: =G64/G63 -> 88.265187 | H65: =H64/H63 -> 88.265187 | I65: =I64/I63 -> 88.265187 | J65: =J64/J63 -> 88.265187
A66: COGS | B66: =B8 -> 220991.07 | C66: =C8 -> 259556.96 | D66: =D8 -> 258535.21 | E66: =E8 -> 270323.33 | F66: =F8 -> 293831.64 | G66: =G8 -> 314399.85 | H66: =H8 -> 336407.84 | I66: =I8 -> 359956.39 | J66: =J8 -> 385153.34
A67: COGS per day | B67: =B66/365 -> 605.45499 | C67: =C66/365 -> 711.11497 | D67: =D66/365 -> 708.31564 | E67: =E66/365 -> 740.61188 | F67: =F66/365 -> 805.01818 | G67: =G66/365 -> 861.36945 | H67: =H66/365 -> 921.66531 | I67: =I66/365 -> 986.18189 | J67: =J66/365 -> 1055.2146
A68: Payables (AVG) | C68: =AVERAGE(B20:C20) -> 33175.5 | D68: =AVERAGE(C20:D20) -> 31839 | E68: =AVERAGE(D20:E20) -> 33393 | F68: =AVERAGE(E20:F20) -> 36197.561 | G68: =AVERAGE(F20:G20) -> 37710.352 | H68: =AVERAGE(G20:H20) -> 40350.077 | I68: =AVERAGE(H20:I20) -> 43174.582 | J68: =AVERAGE(I20:J20) -> 46196.803
A69: Days Payables Outstanding | C69: =C68/C67 -> 46.652794 | D69: =D68/D67 -> 44.950299 | E69: =E68/E67 -> 45.088394 | F69: =F68/F67 -> 44.964899 | G69: =G68/G67 -> 43.779533 | H69: =H68/H67 -> 43.779533 | I69: =I68/I67 -> 43.779533 | J69: =J68/J67 -> 43.779533
A70: Cash Conversion Cycle | C70: =C61+C65-C69 -> 128.87989 | D70: =D61+D65-D69 -> 153.46161 | E70: =E61+E65-E69 -> 133.32372 | F70: =F61+F65-F69 -> 120.21552 | G70: =G61+G65-G69 -> 115.0978 | H70: =H61+H65-H69 -> 115.0978 | I70: =I61+I65-I69 -> 115.0978 | J70: =J61+J65-J69 -> 115.0978
A72: Note: FCF Defined as EBITDA less Capex
